Workbook

Sheet BACKEND1
A1: KICTHEN COMMON ITEM DATA COLLECTION SHEET 2025
B2: WHOLE | C2: REMAINDER | D2: R.U.O.M Per W.U.O.M | F2: Weight
A3: Item | B3: Whole Unit of Measurement (W.U.O.M) | C3: Remainder Unit of Measurement (R.U.O.M) | D3: U.O.M | E3: Qty or No. | F3: Empty Tin or Container Or Bottle Weight (Kg)
A4: Condiments
A5: Bread Loaf | B5: Loaf | C5: kg | D5: Kg Per Loaf | E5: 1
A6: Burger Buns | B6: Pcs | C6: Pcs | D6: Pc Per Pkts | E6: 1
A7: Slider Buns | B7: Pcs | C7: Pcs | D7: Pc Per Pkts | E7: 1
A8: Soup Buns | B8: Pcs | C8: Pcs | D8: Pc Per Pkts | E8: 1
A9: Baguette Bread | B9: Pcs | C9: Pcs | D9: Pc Per Pkts | E9: 1
A10: Foccacia Bread | B10: Pcs | C10: Pcs | D10: Pc Per Pkts | E10: 1
A11: White vinegar | B11: Bottles | C11: Liters | D11: Ltrs per Btl | E11: 0.7 | F11: 0.006
A12: Heinz ketchup bottles | B12: Bottles | C12: Bottles | D12: Btls per Btls | E12: 0.305 | F12: 0.195
A13: Apple cider vinegar | B13: Pcs | C13: kg | D13: Ltrs per Btl | E13: 0.473 | F13: 0.037
A14: Balsamic Vinegar | B14: Bottles | C14: Litre | D14: Litre per Bottle | E14: 0.5 | F14: 0.4
A15: Tomato paste | B15: Tins | C15: Kg | D15: Kg Per Tin | E15: 0.4 | F15: 0.063
A16: Tabasco | B16: Pcs | C16: Litre | D16: Kgs per Pc | E16: 0.06 | F16: 0.086
A17: Ketchup sachets | B17: Packet | C17: Pcs | D17: Pcs per Pkt | E17: 100 | F17: 0
A18: Mustard | B18: Bottles | C18: Kg | D18: Kgs per Btl | E18: 0.397 | F18: 0.032
A19: Pancake syrup 710ml | B19: Bottles | C19: Liters | D19: Ltrs per Btl | E19: 0.71 | F19: 0.293
A20: Vanilla esscence | B20: Bottles | C20: Liters | D20: Ltrs per Btl | E20: 1 | F20: 0.056
A21: Srawberry Syrup | B21: Btls | C21: Ltr | D21: Ltr per Btl | E21: 0.623 | F21: 0.057
A22: Caramel syrup | B22: Btls | C22: Ltr | D22: Ltr per Btl | E22: 0.623 | F22: 0.057
... A25: Ketchup 5L | B25: Jerrycan | C25: kg | D25: Ltrs per Btl | E25: 5 | F25: 0.3
A26: Dry Foods
A27: Baking flour | B27: Pkts | C27: Kg | D27: Kg Per Pkts | E27: 2 | F27: 0.05
A28: Baking Powder | B28: Pkts | C28: Kg | D28: Kg Per Pkts | E28: 0.1 | F28: 0.01
A29: Basmati rice | B29: Kg | C29: Kg | D29: Kg Per Kg | E29: 1 | F29: 0.1
A30: Corn flour | B30: Pkts | C30: Kg | D30: Kg Per Pkts | E30: 0.4 | F30: 0.05
A31: Oils, Fats & Creams
A32: Cooking oil 20L | B32: Jerrycan | C32: Liters | D32: Liters Per Jerrycan | E32: 18.4 | F32: 0.81
A33: Croma Butter | B33: Kg | C33: Kg | D33: kg per kg | E33: 1
A34: Prestige | B34: Kg | C34: Kg | D34: Kg Per Kg | E34: 1
A35: Cooking cream | B35: Packs | C35: Liters | D35: Ltrs per Pc | E35: 1 | F35: 0.062
A36: Sunseed Oil 5L | B36: Pcs | C36: Liters | D36: Liters Per Pc | E36: 5 | F36: 0.18
A37: Whipping cream | B37: Packs | C37: Kg | D37: Ltrs per Pc | E37: 1 | F37: 0.062
A38: Olive Oil | B38: Can | C38: Liters | D38: Liters Per Can | E38: 4 | F38: 0.08
A39: Coconut Oil | B39: Jerrycan | C39: Kg | D39: Kg per Jerry | F39: 0.06
A40: Seseame Oil | B40: Bottle | C40: Kg | D40: Kg per Bottle | E40: 0.5 | F40: 0.18
A41: Sauces
A42: Light soy sauce | B42: Bottle | C42: Liters | D42: Ltrs per Btl | E42: 0.5 | F42: 0.412
A43: Dark soy sauce | B43: Bottle | C43: Liters | D43: Ltrs per Btl | E43: 0.5 | F43: 0.477
A44: Sweet chilli sauce | B44: Bottle | C44: Liters | D44: Ltrs per Btl | E44: 0.81 | F44: 0.5
A45: Oyster sauce | B45: Bottle | C45: Liters | D45: Ltrs per Btl | E45: 0.51 | F45: 0.293
A46: Worcestershire sauce | B46: Bottles | C46: Liters | D46: Ltrs per Btl | E46: 0.295 | F46: 0.062
A47: Top up sauce | B47: Jerrycan | C47: Liters | D47: Ltrs per Pc | E47: 5 | F47: 0.12
A48: Fish Sauce | B48: Bottle | C48: Liters | D48: Ltrs per Btl | E48: 0.75 | F48: 0.7
A49: Red Wine | B49: Bottle | C49: Liters | D49: Mls per Bottle | E49: 0.75 | F49: 0.42
A50: White Wine | B50: Bottle | C50: Liters | D50: Mls per Bottle | E50: 0.75 | F50: 0.42
A51: Spices
A52: Turmeric | B52: Packet | C52: Kg | D52: Kgs per Pkt | E52: 1 | F52: 0.011
A53: Paprika | B53: Packet | C53: Kg | D53: Kgs per Pkt | E53: 1 | F53: 0.006
A54: Origano | B54: Packet | C54: Kg | D54: Kgs per Pkt | E54: 0.25 | F54: 0.017
A55: Curry powder | B55: Packet | C55: Kg | D55: Kgs per Pkt | E55: 1 | F55: 0.004
A56: Black pepper powder | B56: Packet | C56: Kg | D56: Kgs per Pkt | E56: 1 | F56: 0.004
A57: Black pepper Seeds | B57: Packet | C57: Kg | D57: Kgs per Pkt | E57: 1 | F57: 0.004
A58: Cumin seeds | B58: Packet | C58: Kg | D58: Kgs per Pkt | E58: 0.5 | F58: 0.017
A59: Simba mbili | B59: Tin | C59: Kg | D59: Kgs per Tin | E59: 1 | F59: 0.107
A60: Cinnamon powder | B60: Packet | C60: Kg | D60: Kgs per Pkt | E60: 1 | F60: 0.004
A61: Ground cloves | B61: Packet | C61: Kg | D61: Kgs per Pkt | E61: 1 | F61: 0.011
A62: Pilau masala | B62: Packet | C62: Kg | D62: Kgs per Pkt | E62: 1 | F62: 0.006
A63: Cocoa powder | B63: Packet | C63: Kg | D63: Kgs per Pkt | E63: 0.5 | F63: 0.013
... A85: Meat Tenderizer 100g | B85: tin | C85: Kg | D85: Kg per Tin | E85: 0.1 | F85: 0.05
A86: Chicken Cubes | B86: Piece | C86: Kg | D86: Kg Per Piece | E86: 0.48
A87: Chicken Tikka Masala 100g | B87: Packet | C87: Kg | D87: Kg Per Packet | E87: 0.1 | F87: 0.02
A88: Chilli Powder | B88: Packet | C88: Kg | D88: Kg Per Packet | E88: 1 | F88: 0.02
A89: Onion powder | B89: Packet | C89: Kg | D89: Kg Per Packet | E89: 1
A90: Sweeteners
A91: Brown sugar | B91: Packet | C91: Kg | D91: Kgs per Pkt | E91: 1 | F91: 0.012
A92: Sugar | B92: Kg | C92: Kg | D92: Kg Per Kg | E92: 1
A93: Icing sugar | B93: Packet | C93: Kg | D93: Kgs per Pkt | E93: 0.5 | F93: 0.1
A94: Bbq sauce | B94: Bottles | C94: Liters | D94: Ltrs per Btl | E94: 0.51 | F94: 0.052
A95: Canned goods
A96: Aromat | B96: Tin | C96: Kg | D96: Kig per Tin | E96: 0.2 | F96: 0.036
A97: Salt | B97: Pkt | C97: Kg | D97: Kg per Packet | E97: 0.5 | F97: 0.012
A98: Sweet corn | B98: Tins | C98: Kg | D98: Kg Per Tin | E98: 0.425 | F98: 0.055
A99: Coconut Milk | B99: Tins | C99: Kg | D99: Kg Per Tin | E99: 0.425 | F99: 0.056
A100: Peanut butter | B100: Tins | C100: Kg | D100: Kg Per Tin | E100: 0.454 | F100: 0.04
A101: Black olives | B101: Tins | C101: Kg | D101: Kg Per Tin | E101: 0.335 | F101: 0.234
A102: Green olives | B102: Tins | C102: Kg | D102: Kg Per Tin | E102: 0.34 | F102: 0.228
A103: Mushroom Tin | B103: Tins | C103: Kg | D103: Kg Per Tin | E103: 0.4 | F103: 0.12
A104: Pickles | B104: Tins | C104: Kg | D104: Kg Per Tin | E104: 0.37 | F104: 0.31
A105: Grapes | B105: Pkt | C105: Kg | D105: Kg Per Packet | E105: 0.5 | F105: 0.104
A106: Dates | B106: Pkt | C106: Kg | D106: Kg Per Packet | E106: 0.5 | F106: 0.014
A107: Mayonnaise big tin | B107: Tin | C107: Kg | D107: Kg Per Tin | E107: 3.78 | F107: 0.2
... A114: Sprinkles | B114: Tin | C114: Kg | D114: Kg Per Tin | E114: 0.5 | F114: 0.115
A115: Dairy
A116: Fresh milk/Jesa | B116: Liters | C116: Liters | D116: Liters Per Liters | E116: 1
A117: Mozzarella cheese | B117: Kg | C117: Kg | D117: Kgs Per Pc | E117: 0.5 | F117: 0.012
A118: Parmesan cheese | B118: Kg | C118: Kg | D118: Kgs Per Pc | E118: 1.1 | F118: 0.012
A119: Cheddar cheese | B119: Kg | C119: Kg | D119: Kgs Per Pc | E119: 1.188 | F119: 0.012
A120: Plain yoghurt | B120: Kg | C120: Kg | D120: Kgs per Pc | E120: 0.48 | F120: 0.02
A121: Lato ghee | B121: Kg | C121: kg | D121: Kgs per Tin | E121: 0.5 | F121: 0.096
A122: Fruits & Vegetables
A123: Hard lettuce | B123: Pcs | C123: Pcs | D123: Pcs Per Pcs | E123: 1 | F123: 0
A124: Soft lettuce | B124: Pcs | C124: Pcs | D124: Pcs Per Pcs | E124: 1 | F124: 0
A125: Onions | B125: Kg | C125: Kg | D125: Kg Per Kg | E125: 1 | F125: 0
A126: White cabbage | B126: Pcs | C126: Pcs | D126: Pcs Per Pcs | E126: 1 | F126: 0
A127: Red cabbage | B127: Pcs | C127: Pcs | D127: Pcs Per Pcs | E127: 1 | F127: 0
A128: Carrots | B128: Kg | C128: Kg | D128: Kg Per Kg | E128: 1 | F128: 0
A129: Fresh Mushroom | B129: Kg | C129: Kg | D129: Kg Per Kg | E129: 1 | F129: 0
...

Sheet Printables
A1: PATIO BELLA — KITCHEN COMMON ITEMS COUNTING STOCK CARD
A2: DATE: | C2: SHIFT / SESSION: | E2: COUNTED BY:
A3: ITEM | B3: WHOLE | D3: REMAINDER | F3: UNITS OPENED
A4: ITEM | B4: U.O.M | C4: QTY | D4: U.O.M | E4: QTY | F4: Bottles / Tins / Packets
A5: CONDIMENTS & BREAD
A6: Bread Loaf | B6: Loaf | D6: Loaf
A7: Burger Buns | B7: Pcs | D7: Pcs
A8: Slinder Buns / Mini Burger Buns | B8: Pcs | D8: Pcs
A9: Soup Buns | B9: Pcs | D9: Pcs
A10: Baguette Bread | B10: Pcs | D10: Pcs
A11: Breadcrumbs | B11: Packets | D11: Kg
A12: Chapati Flour | B12: Kg | D12: Kg
A13: DRY FOODS & GRAINS
A14: Baking Flour / Azam | B14: Packets | D14: Kg
A15: Baking Powder | B15: Packets | D15: Kg
A16: Basmati Rice | B16: Sack | D16: Kg
A17: Corn Flour (Starch) | B17: Packets | D17: Kg
A18: Eggs | B18: Tray | D18: Pcs
A19: Penne Pasta | B19: Packets | D19: Kg
A20: Spaghettini | B20: Packets | D20: Kg
A21: Yeast 500g | B21: Packets | D21: Kg
A22: Salt | B22: Packets | D22: Kg
A23: Aji-no-Moto | B23: Packets | D23: Kg
A24: Raisins | B24: Packets | D24: Kg
A25: Sesame Seeds | B25: Packets | D25: Kg
... A27: Black Beans | B27: Kg | D27: Kg
A28: OILS, FATS & CREAMS
A29: Cooking Oil 20L | B29: Jerrycan | D29: Litres
A30: Sunseed Oil 5L | B30: Pcs | D30: Litres
A31: Olive Oil | B31: Can | D31: Litres
A32: Sesame Oil | B32: Tin | D32: Litres
A33: Coconut Oil | B33: Tin | D33: Litres
A34: Croma Butter | B34: Kg | D34: Kg
A35: Unsalted Butter | B35: Kg | D35: Kg
A36: Cooking Cream | B36: Packs | D36: Kg
A37: Whipping Cream | B37: Packs | D37: Kg
A38: Lato Ghee | B38: Tin | D38: Kg
A39: SAUCES & CONDIMENTS
A40: Light Soy Sauce | B40: Bottle | D40: Litres
A41: Dark Soy Sauce | B41: Bottle | D41: Litres
A42: Sweet Chilli Sauce | B42: Bottle | D42: Litres
A43: Oyster Sauce | B43: Bottle | D43: Litres
A44: Fish Sauce 750ml | B44: Bottle | D44: Litres
A45: Worcestershire Sauce | B45: Bottle | D45: Litres
A46: Top Up Sauce (Tomato Sauce) | B46: Jerrycan | D46: Kg
A47: Heinz Ketchup Bottle | B47: Bottle | D47: Litres
A48: Heinz Ketchup Jerrycan | B48: Jerrycan | D48: Kg
A49: Tomato Paste | B49: Tin | D49: Kg
A50: BBQ Sauce | B50: Bottle | D50: Litres
A51: Tabasco | B51: Bottle | D51: Litres
... A64: White Wine (cooking) | B64: Bottle | D64: Litres
A65: SPICES & HERBS
A66: Turmeric Powder | B66: Packet | D66: Kg
A67: Paprika | B67: Packet | D67: Kg
A68: Oregano | B68: Packet | D68: Kg
A69: Curry Powder | B69: Packet | D69: Kg
A70: Black Pepper Powder | B70: Packet | D70: Kg
A71: Black Pepper Seeds | B71: Packet | D71: Kg
A72: Simba Mbili | B72: Tin | D72: Kg
A73: Cinnamon Powder | B73: Packet | D73: Kg
A74: Cloves | B74: Packet | D74: Kg
A75: Pilau Masala | B75: Packet | D75: Kg
A76: Thyme | B76: Packet | D76: Kg
A77: Nutmeg | B77: Packet | D77: Kg
... A96: Aromat | B96: Tin | D96: Kg
A97: SWEETENERS
A98: White Sugar | B98: Kg | D98: Kg
A99: Brown Sugar | B99: Packet | D99: Kg
A100: Icing Sugar | B100: Packet | D100: Kg
A101: CANNED GOODS
A102: Sweet Corn | B102: Tin | D102: Kg
A103: Coconut Milk | B103: Tin | D103: Kg
A104: Black Olives | B104: Tin | D104: Kg
A105: Green Olives | B105: Tin | D105: Kg
A106: Mushroom Tin | B106: Tin | D106: Kg
A107: Pickles | B107: Tin | D107: Kg
A108: Grapes | B108: Packet | D108: Kg
A109: Baked Beans | B109: Tin | D109: Kg
A110: Zesta Jam | B110: Tin | D110: Kg
A111: Red Cherries | B111: Tin | D111: Kg
A112: Green Cherries | B112: Tin | D112: Kg
A113: Muesli Fruit & Nut 357g | B113: Packet | D113: Kg
... A115: Tomato Paste (Canned) | B115: Tin | D115: Kg
A116: DAIRY
A117: Fresh Milk / Jesa | B117: Litres | D117: Litres
A118: Mozzarella Cheese | B118: Kg | D118: Kg
A119: Parmesan Cheese | B119: Kg | D119: Kg
A120: Feta Cheese | B120: Kg | D120: Kg
A121: Cheddar Cheese | B121: Kg | D121: Kg
A122: Plain Yoghurt | B122: Pcs | D122: Kg
A123: Cream Cheese | B123: Kg | D123: Kg
A124: FRUITS & VEGETABLES
A125: Hard Lettuce | B125: Pcs | D125: Pcs
A126: Soft Lettuce | B126: Pcs | D126: Pcs
A127: Onions | B127: Kg | D127: Kg
A128: White Cabbage | B128: Pcs | D128: Pcs
A129: Red Cabbage | B129: Pcs | D129: Pcs
A130: Carrots | B130: Kg | D130: Kg
A131: Fresh Mushroom | B131: Kg | D131: Kg
A132: Tomatoes | B132: Kg | D132: Kg
...

Sheet BACKEND2
B2: WHOLE | C2: REMAINDER | D2: R.U.O.M Per W.U.O.M | F2: Weight
A3: Item | B3: Whole Unit of Measurement (W.U.O.M) | C3: Remainder Unit of Measurement (R.U.O.M) | D3: U.O.M | E3: Qty or No. | F3: Portion Weight (Kg)
A4: Carribean jerk | B4: Portions | C4: Pcs | D4: Pcs per ptn | E4: 3 | F4: 450g
A5: Chicken breast | B5: Ptns | C5: Pcs | D5: Pcs per ptn | E5: 2 | F5: 250g
A6: Chicken wings | B6: Ptns | C6: Pcs | D6: Pcs per ptn | E6: 5 | F6: 510g
A7: Chicken burger | B7: Ptns | C7: Ptns | D7: Ptn per ptn | E7: 1 | F7: 130g
A8: Min Chicken burger | B8: Ptns | C8: Pcs | D8: Pcs per ptn | E8: 1 | F8: 75g
A9: Chicken lollipos | B9: Ptns | C9: Pcs | D9: Pcs per ptn | E9: 8 | F9: 420g
A10: Chicken pizza | B10: Ptns | C10: Ptns | D10: Ptn per ptn | E10: 1 | F10: 130g
A11: Chicken Tenders | B11: Ptns | C11: Ptns | D11: Ptn per ptn | E11: 1 | F11: 170g
A12: Chicken skewers | B12: Ptns | C12: Pcs | D12: Pcs per ptn | E12: 9 | F12: 300g
A13: Chicken stroganoff | B13: Ptns | C13: Ptns | D13: Ptn per ptn | E13: 1 | F13: 270g
A14: Chicken spring rolls | B14: Ptns | C14: Pcs | D14: Pcs per ptn | E14: 4 | F14: 200g
A15: Chicken Samosas | B15: Ptns | C15: Pcs | D15: Pcs per ptn | E15: 4 | F15: 200g
... A27: Beef pizza | B27: Ptns | C27: Ptns | D27: Ptn per ptn | E27: 1 | F27: 130g
A28: Beef sausages | B28: Ptns | C28: Pcs | D28: Pcs per ptn | E28: 2
A29: Beef burger patty | B29: Ptns | C29: Ptns | D29: Ptns per ptn | E29: 1 | F29: 150g
A30: Bolognese | B30: Ptns | C30: Ptns | D30: Ptns per ptn | E30: 1 | F30: 150g
A31: Beef samosas | B31: Ptns | C31: Pcs | D31: Pcs per ptn | E31: 4 | F31: 200g
A32: Beef mini burger | B32: Ptns | C32: Ptns | D32: Ptns per ptn | E32: 1 | F32: 75g
A33: Whole fish | B33: Ptns | C33: Ptns | D33: Ptn per ptn | E33: 1 | F33: 1100g
A34: Salmon | B34: Ptns | C34: Ptns | D34: Ptn per ptn | E34: 1 | F34: 27g
A35: Tilapia fillet | B35: Ptns | C35: Pcs | D35: Pcs per ptn | E35: 2 | F35: 300g
A36: Fish fingers | B36: Ptns | C36: Pcs | D36: Pcs per ptn | E36: 4 | F36: 180g
A37: Veg Springs rolls | B37: Ptns | C37: Pcs | D37: Pcs per ptn | E37: 4 | F37: 180g
A38: Veg Samosas | B38: Ptns | C38: Pcs | D38: Pcs per ptn | E38: 4 | F38: 180g
A39: Beef Stew | B39: Ptns | C39: Pcs | D39: Pcs per ptn | E39: 1 | F39: 270g
A40: Beef Minced Meat | B40: Ptns | C40: Pcs | D40: Pcs per ptn | E40: 1 | F40: 150g
A41: Chicken Minced Meat | B41: Ptns | C41: Pcs | D41: Pcs per ptn | E41: 1 | F41: 150g

Sheet Prices
A1: Item | B1: WHOLE W.U.O.M | C1: PURCHASING PRICE (W.U.O.M) | D1: REMAINDER R.U.O.M | E1: R.U.O.M Per W.U.O.M U.O.M | F1: Qty or No. | G1: R.U.O.M Cost Equivalet
A2: Baking Flour / Azam | B2: Packet | C2: 6666 | D2: Kilogram | E2: Kilogram Per Packet | F2: 2 | G2: =C2/F2 -> 3333
A3: Corn flour | B3: Packet | C3: 4000 | D3: Kilogram | E3: Kg Per Packet | F3: 0.4 | G3: =C3/F3 -> 10000
A4: Baking powder | B4: Packet | C4: 1500 | D4: Kilogram | E4: Kg Per Packet | F4: 0.1 | G4: =C4/F4 -> 15000
A5: Oyester Sauce | B5: Bottles | C5: 20000 | D5: Litres | E5: Liters Per Bottle | F5: 0.51 | G5: =C5/F5 -> 39215.686
A6: Worcestershires sauce | B6: Bottles | C6: 15000 | D6: Litres | E6: Litres Per Bottle | F6: 0.295 | G6: =C6/F6 -> 50847.458
A7: Sweet Corn | B7: Tins | C7: 5000 | D7: kg | E7: Kg Per Tin | F7: 0.4 | G7: =C7/F7 -> 12500
A8: Us Mustard | B8: Bottle | C8: 16000 | D8: Kg | E8: Kg Per Tin | F8: 0.4 | G8: =C8/F8 -> 40000
A9: White vinegar | B9: Bottle | C9: 1500 | D9: Litres | E9: Litres Per Bottle | F9: 0.7 | G9: =C9/F9 -> 2142.8571
A10: Apple cider vinegar | B10: Bottles | C10: 13000 | D10: Litres | E10: Litres Per Bottle | F10: 0.473 | G10: =C10/F10 -> 27484.144
A11: Balsamic Vinegar | B11: Bottles | C11: 13000 | D11: Litres | E11: Litres Per Bottle | F11: 0.5 | G11: =C11/F11 -> 26000
A12: Aromat | B12: Tins | C12: 9000 | D12: Kg | E12: Kg Per Tin | F12: 0.2 | G12: =C12/F12 -> 45000
A13: Baked beans | B13: Tins | C13: 7000 | D13: Kg | E13: Kg Per Tin | F13: 0.415 | G13: =C13/F13 -> 16867.47
... A46: Milk fresh | B46: Litres | C46: 2400 | D46: Liters | E46: Litres Per Packet | F46: 1 | G46: =C46/F46 -> 2400
A47: Cumin powder | B47: Pkts | C47: 20000 | D47: Kg | E47: Kg Per Packet | F47: 1 | G47: 20000
A48: Cumin seeds | B48: pkts | C48: 23000 | D48: Kg | E48: Kg Per Packet | F48: 1 | G48: 23000
A49: Chicken tika masala | B49: pkts | C49: 6500 | D49: Kg | E49: Kg Per Packet | F49: 1 | G49: =6500/0.1 -> 65000
A50: Thyme rubbed | B50: pkts | C50: 20000 | D50: Kg | E50: Kg Per Packet | F50: 1 | G50: =C50/F50 -> 20000
A51: Chicken Tikka | B51: pkts | C51: 7400 | D51: kg | E51: Kg Per Packet | F51: 1 | G51: =7400/0.1 -> 74000
A52: Pure tumeric powder | B52: pkts | C52: 35000 | D52: Kg | E52: Kg Per Packet | F52: 1 | G52: =F52*C52 -> 35000
A53: Cinnamon sticks | B53: pkts | C53: 12000 | D53: Kg | E53: Kg Per Packet | F53: 1 | G53: =F53*C53 -> 12000
A54: Oregano powder | B54: pkts | C54: 25000 | D54: Kg | E54: Kg Per Packet | F54: 1 | G54: =F54*C54 -> 25000
A55: Black pepper Powder | B55: pkts | C55: 40000 | D55: Kg | E55: Kg Per Packet | F55: 1 | G55: =F55*C55 -> 40000
A56: Black pepper Seeds | B56: pkts | C56: 40000 | D56: kg | E56: Kg Per Packet | F56: 1 | G56: =F56*C56 -> 40000
A57: Black pepper tin powder | B57: Tins | C57: 13000 | D57: kg | E57: King Per Tin | F57: 1 | G57: =13000/0.1 -> 130000
A58: Sesame seeds | B58: pkts | C58: 23000 | D58: Kg | E58: Kg Per Packet | F58: 1 | G58: =F58*C58 -> 23000
A59: Onion powder | B59: pkts | C59: 22000 | D59: Kg | E59: Kg Per Packet | F59: 1 | G59: =F59*C59 -> 22000
A60: Cloves | B60: pkts | C60: 30000 | D60: Kg | E60: Kg Per Packet | F60: 1 | G60: =F60*C60 -> 30000
A61: Garam masala powder | B61: pkts | C61: 35000 | D61: Kg | E61: Kg Per Packet | F61: 1 | G61: =F61*C61 -> 35000
A62: Brown sugar | B62: Kg | C62: 13000 | D62: Kg | E62: Kg Per Kg | F62: 1 | G62: =F62*C62 -> 13000
A63: Chilli Powder | B63: pkts | C63: 20000 | D63: Kg | E63: Kg Per Packet | F63: 1 | G63: =F63*C63 -> 20000
A64: Cinnamon powder | B64: pkts | C64: 20000 | D64: Kg | E64: Kg Per Packet | F64: 1 | G64: =F64*C64 -> 20000
A65: White pepper powder | B65: pkts | C65: 50000 | D65: Kg | E65: Kg Per Packet | F65: 1 | G65: =F65*C65 -> 50000
A66: Garlic powder | B66: pkts | C66: 20000 | D66: Kg | E66: Kg Per Packet | F66: 1 | G66: =F66*C66 -> 20000
A67: Pillao masala | B67: pkts | C67: 20000 | D67: Kg | E67: Kg Per Packet | F67: 1 | G67: =F67*C67 -> 20000
A68: Nutmeg powder | B68: pkts | C68: 40000 | D68: Kg | E68: Kg Per Packet | F68: 1 | G68: =F68*C68 -> 40000
A69: Corriander powder | B69: pkts | C69: 12000 | D69: Kg | E69: Kg Per Packet | F69: 1 | G69: =12000/0.5 -> 24000
A70: Take away ketchup | B70: pcs | C70: 200 | D70: Pcs | E70: Pcs Per Pcs | F70: 1 | G70: =C70/F70 -> 200
A71: Red onions | B71: kg | C71: 3400 | D71: kg | E71: Kg Per Kg | F71: 1 | G71: =C71/F71 -> 3400
A72: Tomatoes | B72: kg | C72: 2800 | D72: Kg | E72: Kg Per Kg | F72: 1 | G72: =C72/F72 -> 2800
A73: Green pepper | B73: kg | C73: 3800 | D73: Kg | E73: Kg Per Kg | F73: 1 | G73: =C73/F73 -> 3800
A74: Yellow pepper | B74: kg | C74: 9000 | D74: kg | E74: Kg Per Kg | F74: 1 | G74: =C74/F74 -> 9000
A75: Red pepper | B75: kg | C75: 9000 | D75: kg | E75: Kg Per Kg | F75: 1 | G75: =C75/F75 -> 9000
A76: Irish potatoes | B76: kg | C76: 2300 | D76: Kg | E76: Kg Per Kg | F76: 1 | G76: =C76/F76 -> 2300
A77: Plantain | B77: Cluster | C77: =60000/7 -> 8571.4286 | D77: Clusters | E77: Clusters Per Cluster | F77: 1 | G77: =C77/F77 -> 8571.4286
A78: Pumpkin | B78: pcs | C78: 4800 | D78: Pcs | E78: Pcs Per Pc | F78: 1 | G78: =C78/F78 -> 4800
A79: Baby Marow | B79: kg | C79: 3500 | D79: Kg | E79: Kg Per Kg | F79: 1 | G79: =C79/F79 -> 3500
A80: Cucumber | B80: kg | C80: 2500 | D80: Kg | E80: Kg Per Kg | F80: 1 | G80: =C80/F80 -> 2500
A81: English Cucumber | B81: kg | C81: 6000 | D81: Kg | E81: Kg Per kg | F81: 1 | G81: =C81/F81 -> 6000
A82: Beetroot | B82: Kg | C82: 5000 | D82: Kg | E82: Kg Per kg | F82: 1 | G82: =C82/F82 -> 5000
A83: Corriander leaves | B83: bundle | C83: 1900 | D83: bundles | E83: Bundles Per Bundle | F83: 1 | G83: =C83/F83 -> 1900
A84: Parsey | B84: bundle | C84: 3000 | D84: bundles | E84: Bundles Per Bundle | F84: 1 | G84: =C84/F84 -> 3000
A85: Spinach | B85: bundle | C85: 2000 | D85: bundles | E85: Bundles Per Bundle | F85: 1 | G85: =C85/F85 -> 2000
A86: Basil leaves | B86: bundle | C86: 1900 | D86: bundles | E86: Bundles Per Bundle | F86: 1 | G86: =C86/F86 -> 1900
A87: Spring onions | B87: bundle | C87: 2000 | D87: bundles | E87: Bundles Per Bundle | F87: 1 | G87: =C87/F87 -> 2000
A88: Cauli flower | B88: pcs | C88: 3800 | D88: Pcs | E88: Pcs Per Pc | F88: 1 | G88: =C88/F88 -> 3800
A89: Watermelon | B89: pcs | C89: 6000 | D89: Pcs | E89: Pcs Per Pc | F89: 1 | G89: =C89/F89 -> 6000
... A97: Hard lettuce | B97: pcs | C97: 2800 | D97: Pcs | E97: Pcs Per Pc | F97: 1 | G97: =C97/F97 -> 2800
A98: Cow ghee | B98: Tins | D98: Kg | E98: Kg Per Tin | G98: =C98/F98 -> #DIV/0!
A99: Basmal rice | B99: kg | C99: 10000 | D99: Kg | E99: Kg Per Kg | F99: 1 | G99: =C99/F99 -> 10000
A100: Cling film | B100: Roll | C100: 90000 | D100: kg | E100: Kg Per roll | F100: 4.925 | G100: =C100/F100 -> 18274.112
A101: Tomato sauce Top up | B101: Jerrican | C101: 20000 | D101: Liters | E101: Litres Per Jerican | F101: 5 | G101: =C101/F101 -> 4000
A102: Apples | B102: kg | C102: 3800 | D102: kg | E102: Kg Per kg | F102: 1 | G102: =C102/F102 -> 3800
A103: Oranges | B103: kg | C103: 8500 | D103: kg | E103: Kg Per kg | F103: 1 | G103: =C103/F103 -> 8500
A104: Red cabbage | B104: pcs | D104: Pcs | E104: Pcs Per Pc | F104: 1 | G104: =C104/F104 -> 0
A105: White Cabbage | B105: pcs | C105: 2400 | D105: Pcs | E105: Pcs Per Pc | F105: 1 | G105: =C105/F105 -> 2400
A106: Honey | B106: Litres | C106: 18000 | D106: Liters | E106: Litres Per Litres | F106: 1 | G106: =C106/F106 -> 18000
A107: Cilery leaves | B107: bundle | C107: 4000 | D107: bundles | E107: Bundles Per Bundle | F107: 1 | G107: =C107/F107 -> 4000
A108: Rosemary leaves | B108: bundle | C108: 3000 | D108: bundles | E108: Bundles Per Bundle | F108: 1 | G108: =C108/F108 -> 3000
A109: Rocket leaves | B109: bundle | C109: 4500 | D109: bundles | E109: Bundles Per Bundle | F109: 1 | G109: =C109/F109 -> 4500
A110: Bread Loaf | B110: loaf | C110: 3876 | D110: loaf | E110: Loaf Per Pc | F110: 1 | G110: =C110/F110 -> 3876
A111: Burger Buns | B111: pkts | C111: 465 | D111: Pcs | E111: Pcs Per Packet | F111: 1 | G111: =C111/F111 -> 465
A112: Slider Buns | B112: pkts | C112: 233 | D112: Pcs | E112: Pcs Per Packet | F112: 1 | G112: =C112/F112 -> 233
A113: Soup Buns | B113: pkts | C113: 97 | D113: Pcs | E113: Pcs Per Packet | F113: 1 | G113: =C113/F113 -> 97
A114: Baguette Bread | B114: pkts | C114: 781 | D114: Pcs | E114: Pcs Per Packet | F114: 1 | G114: =C114/F114 -> 781
A115: Foccacia Bread | B115: pkts | C115: 1715 | D115: Pcs | E115: Pcs Per Packet | F115: 1 | G115: =C115/F115 -> 1715
A116: Dry White Wine | B116: Bottles | C116: 38000 | D116: Liters | E116: Litres Per Bottle | F116: 0.75 | G116: =C116/F116 -> 50666.667
... A135: Aluminium foil | B135: Roll | C135: 30000 | D135: Kg | E135: Kg Per roll | F135: 2.5 | G135: =C135/F135 -> 12000
A136: Portioned Items: Meats & Others
A137: SEAFOOD
A138: Salmon | B138: Portions | C138: 44604 | D138: Pc | E138: Pieces Per Portion | F138: 1 | G138: =C138/F138 -> 44604
A139: Tilapia fillet | B139: Portions | C139: 10266 | D139: Pc | E139: Pieces Per Portion | F139: 2 | G139: =C139/F139 -> 5133
A140: Whole fish | B140: Portions | C140: 16000 | D140: Pc | E140: Pieces Per Portion | F140: 1 | G140: =C140/F140 -> 16000
A141: Fish stew | B141: Portions | C141: 9582 | D141: Ptn | E141: Portion Per Portion | F141: 1 | G141: =C141/F141 -> 9582
A142: Fish Fingers | B142: Portions | C142: 6160 | D142: Pc | E142: Pieces Per Portion | F142: 5 | G142: =C142/F142 -> 1232
A143: PORK | G143: =C143/F143 -> #DIV/0!
A144: Bacon | B144: Portions | C144: 5947 | D144: Pc | E144: Pieces Per Portion | F144: 4 | G144: =C144/F144 -> 1486.75
A145: Bacon wrap | B145: Portions | D145: Pc | E145: Pieces Per Portion | F145: 3 | G145: =C145/F145 -> 0
A146: Pork Ribs | B146: Portions | C146: 8295 | D146: Pc | E146: Pieces Per Portion | F146: 3 | G146: =C146/F146 -> 2765
A147: Pork Chops | B147: Portions | C147: 10042 | D147: Pc | E147: Pieces Per Portion | F147: 2 | G147: =C147/F147 -> 5021
A148: Sizzling pork | B148: Portions | C148: 6726 | D148: Pc | E148: Portion Per Portion | F148: 1 | G148: =C148/F148 -> 6726
A149: Pork pizza | B149: Portions | C149: 2242 | D149: Pc | E149: Portion Per Portion | F149: 1 | G149: =C149/F149 -> 2242
A150: CHICKEN | G150: =C150/F150 -> #DIV/0!
A151: Chicken breast | B151: Portions | C151: 5900 | D151: Pc | E151: Pieces Per Portion | F151: 1 | G151: =C151/F151 -> 5900
A152: Whole chicken | B152: Portions | C152: 14160 | D152: Pc | E152: Pieces Per Portion | F152: 1 | G152: =C152/F152 -> 14160
A153: Chicken curry | B153: Portions | D153: Pc | E153: Portion Per Portion | F153: 1 | G153: =C153/F153 -> 0
A154: Chicken pizza | B154: Portions | C154: 3068 | D154: Pc | E154: Portion Per Portion | F154: 1 | G154: =C154/F154 -> 3068
A155: Chicken skewers | B155: Portions | C155: 7080 | D155: Pc | E155: Portion Per Portion | F155: 1 | G155: =C155/F155 -> 7080
A156: Chicken Wings | B156: Portions | C156: 9027 | D156: Pc | E156: Pieces Per Portion | F156: 5 | G156: =C156/F156 -> 1805.4
A157: Chicken stroganoff | B157: Portions | C157: 4012 | D157: Pc | E157: Pieces Per Portion | F157: 1 | G157: =C157/F157 -> 4012
...

Sheet Report Format
A1: Kitchen Performance | G1: PORK RIBS.Normal | H1: 0.49 | I1: BBQ CHICKEN PIZZA.Normal | J1: 0.4
A2: Total Amount Collected | G2: Pan Fried Goat.Normal | H2: 0.45 | I2: Pan Fried Goat.Normal | J2: 0.45
A3: TOP 10 SELLERS | B3: Plates Sold | C3: Amount | D3: COGS% (Pre-Costed) | E3: % of Sales | G3: CARIBEAN JERK.Normal | H3: 0.6 | I3: CARIBEAN JERK.Normal | J3: 0.6
E4: =C4/$B$2 -> #DIV/0! | G4: BBQ CHICKEN PIZZA.Normal | H4: 0.4 | I4: PORK RIBS.Normal | J4: 0.49
E5: =C5/$B$2 -> #DIV/0! | G5: Whole Tilapia tracona.Normal | H5: 0.62 | I5: Whole Tilapia tracona.Normal | J5: 0.62
E6: =C6/$B$2 -> #DIV/0! | G6: Organic Beef Steak.Normal | H6: 0.48 | I6: Chicken Tenders.Normal | J6: 0.3
E7: =C7/$B$2 -> #DIV/0! | G7: Chicken Tikka Masala..Normal | H7: 0.53 | I7: BBQ Chicken Wings.Normal | J7: 0.31
E8: =C8/$B$2 -> #DIV/0! | G8: Classic chicken Burger.Normal | H8: 0.43 | I8: Chicken Tikka Masala..Normal | J8: 0.53
E9: =C9/$B$2 -> #DIV/0! | G9: Tilapia Fillet.Normal | H9: 0.65 | I9: Meaty Feast Pizza.Normal | J9: 0.42
E10: =C10/$B$2 -> #DIV/0! | G10: Balsamic Chicken wings.Normal | H10: 0.31 | I10: Fish Fingers.Normal | J10: 0.71
E11: =C11/$B$2 -> #DIV/0! | G11: EXTRA OVACADO.Normal | H11: 0.23 | I11: Samosas 2 pairs.chicken | J11: 0.43
E12: =C12/$B$2 -> #DIV/0! | G12: STEAMED IRISH / MASH.MASH | H12: 0.32 | I12: Spring Rolls.veg | J12: 0.28
E13: =C13/$B$2 -> #DIV/0! | G13: EXTRAS.mayonaise | H13: 0.27 | I13: KIDDY SAUSAGES WORLD.Normal | J13: 0.12
B14: Total | C14: =sum(C4:C13) -> 0 | E14: =C14/$B$2 -> #DIV/0! | G14: CHAPARTI (1).1 PC | H14: 0.1 | I14: Clear Chicken & Veg Soup.Normal | J14: 0.32
A15: Percentage of all items % | B15: =C14/B2 -> #DIV/0! | G15: GARLIC NAAN.1 PIECE | H15: 0.11 | I15: EXTRAS.ONION RINGS | J15: 0.09
G16: BUTTER NAAN.Normal | H16: 0.1 | I16: POTATO WEDGES.Normal | J16: 0.32
A17: Total Amount Collected | G17: EXTRA SAUCES.1000 island | H17: 0.15 | I17: PLANTAIN.Normal | J17: 0.3
A18: BOTTOM 10 SELLERS | B18: Plates Sold | C18: Amount | D18: COGS% (Pre-Costed) | E18: % of Sales | G18: EXTRA SAUCES.masala sauce | H18: 0.72 | I18: CHAPARTI (1).1 PC | J18: 0.1
E19: =C19/$B$17 -> #DIV/0! | G19: EXTRA SAUCES.Normal | H19: 0.15 | I19: EXTRA OVACADO.Normal | J19: 0.23
E20: =C20/$B$17 -> #DIV/0! | G20: EXTRAS.KACHUMBARI | H20: 0.2 | I20: COSLOW.Normal | J20: 0.27
E21: =C21/$B$17 -> #DIV/0! | G21: SPINACH.Normal | H21: 0.23
E22: =C22/$B$17 -> #DIV/0! | G22: STEAMED IRISH / MASH.STEAMED IRISH | H22: 0.32
E23: =C23/$B$17 -> #DIV/0! | G23: STEAMED IRISH / MASH.MASH | H23: 0.32
E24: =C24/$B$17 -> #DIV/0! | G24: RICE.Normal | H24: 0.16
E25: =C25/$B$17 -> #DIV/0! | G25: EXTRA SAUCES.masala sauce | H25: 0.2
E26: =C26/$B$17 -> #DIV/0! | G26: GARLIC NAAN.1 PIECE | H26: 0.11
E27: =C27/$B$17 -> #DIV/0! | G27: EXTRAS.TOASTED BREAD SLICE | H27: 0.21
E28: =C28/$B$17 -> #DIV/0! | G28: EXTRAS.mayonaise | H28: 0.1
B29: Total | C29: =SUM(C19:C28) -> 0 | E29: =C29/$B$17 -> #DIV/0! | G29: EXTRA OVACADO.Normal | H29: 0.23
A30: Percentage of all items % | B30: =C29/B17 -> #DIV/0! | G30: EXTRA SAUCES.Normal | H30: 0.15
G31: POTATO WEDGES.Normal | H31: 0.32
G32: EXTRA OVACADO.Normal | H32: 0.23
G33: CHAPARTI (1).1 PC | H33: 0.1
G34: EGGS A PAIR.2 EGGS | H34: 0.1
G35: Toast .Normal | H35: 0.2
A36: Item | B36: U.O.M | C36: Qty Used | D36: Cost | G36: EXTRA SAUCES.masala sauce | H36: 0.2
A37: =CogsReport!E3 -> Cooking oil 20L | B37: =CogsReport!F3 -> Liters | C37: =CogsReport!G3 -> 22.9 | D37: =CogsReport!H3 -> 180461.96 | G37: EXTRAS.KACHUMBARI | H37: 0.2
A38: =CogsReport!E4 -> Seseame Oil | B38: =CogsReport!F4 -> Kg | C38: =CogsReport!G4 -> 0.62 | D38: =CogsReport!H4 -> 122368.42 | G38: EXTRA SAUCES.MAYONNAISE | H38: 0.27
A39: =CogsReport!E5 -> Irish potatoes | B39: =CogsReport!F5 -> Kg | C39: =CogsReport!G5 -> 49.85 | D39: =CogsReport!H5 -> 114655 | G39: EXTRAS.mayonaise | H39: 0.27
A40: =CogsReport!E6 -> Mozzarella cheese | B40: =CogsReport!F6 -> Kg | C40: =CogsReport!G6 -> 4 | D40: =CogsReport!H6 -> 88000 | G40: COSLOW.Normal | H40: 0.27
A41: =CogsReport!E7 -> Plantain | B41: =CogsReport!F7 -> Cluster | C41: =CogsReport!G7 -> 9 | D41: =CogsReport!H7 -> 77142.857
A42: =CogsReport!E8 -> Patio Bella take away bags | B42: =CogsReport!F8 -> Pcs | C42: =CogsReport!G8 -> 60 | D42: =CogsReport!H8 -> 51000
A43: =CogsReport!E9 -> Basmati rice | B43: =CogsReport!F9 -> Kg | C43: =CogsReport!G9 -> 4.9 | D43: =CogsReport!H9 -> 49000
A44: =CogsReport!E10 -> Pilau masala | B44: =CogsReport!F10 -> Kg | C44: =CogsReport!G10 -> 0.462 | D44: =CogsReport!H10 -> 43890
A45: =CogsReport!E11 -> Aromat | B45: =CogsReport!F11 -> Kg | C45: =CogsReport!G11 -> 0.864 | D45: =CogsReport!H11 -> 38880
A46: =CogsReport!E12 -> Baking flour | B46: =CogsReport!F12 -> Kg | C46: =CogsReport!G12 -> 10.754 | D46: =CogsReport!H12 -> 35843.082
A48: Item | B48: U.O.M | C48: Qty Used | D48: Cost
A49: =CogsReport!N3 -> Panfried goat | B49: =CogsReport!O3 -> Ptns | C49: =CogsReport!P3 -> 8 | D49: =CogsReport!Q3 -> 67968
A50: =CogsReport!N4 -> Chicken wings | B50: =CogsReport!O4 -> Pcs | C50: =CogsReport!P4 -> 11 | D50: =CogsReport!Q4 -> 99297
A51: =CogsReport!N5 -> Chicken skewers | B51: =CogsReport!O5 -> Pcs | C51: =CogsReport!P5 -> 5.5 | D51: =CogsReport!Q5 -> 38940
A52: =CogsReport!N6 -> Goat ribs | B52: =CogsReport!O6 -> Ptns | C52: =CogsReport!P6 -> 4 | D52: =CogsReport!Q6 -> 42480
A53: =CogsReport!N7 -> Chicken stroganoff | B53: =CogsReport!O7 -> Ptns | C53: =CogsReport!P7 -> 13.5 | D53: =CogsReport!Q7 -> 54162
A54: =CogsReport!N8 -> Beef burger patty | B54: =CogsReport!O8 -> Ptns | C54: =CogsReport!P8 -> 4 | D54: =CogsReport!Q8 -> 19116
A55: =CogsReport!N9 -> Pork ribs | B55: =CogsReport!O9 -> Ptns | C55: =CogsReport!P9 -> 4 | D55: =CogsReport!Q9 -> 33180
A56: =CogsReport!N10 -> Tilapia fillet | B56: =CogsReport!O10 -> Pcs | C56: =CogsReport!P10 -> 3 | D56: =CogsReport!Q10 -> 30798
A57: =CogsReport!N11 -> Beef sausages | B57: =CogsReport!O11 -> Ptns | C57: =CogsReport!P11 -> 1.5 | D57: =CogsReport!Q11 -> 6555
A58: =CogsReport!N12 -> Beef fillet | B58: =CogsReport!O12 -> Ptns | C58: =CogsReport!P12 -> 1 | D58: =CogsReport!Q12 -> 9558
A59: =CogsReport!N13 -> Bacon | B59: =CogsReport!O13 -> Pcs | C59: =CogsReport!P13 -> 0 | D59: =CogsReport!Q13 -> 0
A62: Item | B62: U.O.M | C62: Qty | D62: Cost
B67: Total | D67: =sum(D63:D66) -> 0
A90: Peeled Irish Sample
A91: Count | B91: Quantity Peeled | C91: Peeling weight (KG)
A92: 1 | B92: 1kg | C92: 0.28
A93: 2 | B93: 1kg | C93: 0.285
A94: 3 | B94: 1kg | C94: 0.235
A95: 4 | B95: 1kg | C95: 0.24
A96: 5 | B96: 1kg | C96: 0.285

Sheet CogsReport
A1: 14thMAY | E1: Other common Items | H1: =SUM(H3:H1000) -> 1149613 | I1: Transfers | J1: =SUM(J3:J1000) -> 0 | K1: Damages | L1: =sum(L3:L1000) -> 0 | N1: Portioned items | Q1: =SUM(Q3:Q1000) -> 932486 | R1: Transfers | S1: =SUM(S3:S1000) -> 0 | T1: Damages | U1: =sum(U3:U1000) -> 0
E2: Item | F2: U.O.M | G2: Qty Used | H2: Cost | I2: Qty | J2: Cost | K2: Qty | L2: Cost | N2: Item | O2: U.O.M | P2: Qty Used | Q2: Cost | R2: Qty | S2: Cost | T2: Qty | U2: Cost
A3: COGS BREAKDOWN BY ACTUAL USAGE | E3: Cooking oil 20L | F3: Liters | G3: =VLOOKUP(E3, INDIRECT("'" & $A$1 & "'!A:O"), 13, FALSE) -> 22.9 | H3: =vlookup(E3, Prices!$A:$G,7,)*G3 -> 180461.96 | I3: {=VLOOKUP(E3, INDIRECT("'" & $A$1 & "'!A:O"), 14, FALSE)} | J3: =vlookup(E3, Prices!$A:$G,7,)*I3 -> 0 | K3: =VLOOKUP(E3, INDIRECT("'" & $A$1 & "'!A:O"), 15, FALSE) | L3: =vlookup(E3, Prices!$A:$G,7,)*K3 -> 0 | N3: Panfried goat | O3: Ptns | P3: {=VLOOKUP(N3, INDIRECT("'" & $A$1 & "'!A:O"), 13, FALSE)/ vlookup(N3,BACKEND2!$A$1:$F1000,5,)} -> 8 | Q3: =vlookup(N3, Prices!$A:$F,3,)*P3 -> 67968 | R3: {=VLOOKUP(N3, INDIRECT("'" & $A$1 & "'!A:O"), 14, FALSE)} | S3: =vlookup(N3, Prices!$A:$G,7,)*R3 -> 0 | T3: =VLOOKUP(N3, INDIRECT("'" & $A$1 & "'!A:O"), 15, FALSE) | U3: =vlookup(N3, Prices!$A:$G,7,)*T3 -> 0
A4: Portions Items Moved | B4: =Q1 -> 932486 | E4: Seseame Oil | F4: Kg | G4: =VLOOKUP(E4, INDIRECT("'" & $A$1 & "'!A:O"), 13, FALSE) -> 0.62 | H4: =vlookup(E4, Prices!$A:$G,7,)*G4 -> 122368.42 | J4: =vlookup(E4, Prices!$A:$G,7,)*I4 -> 0 | K4: =VLOOKUP(E4, INDIRECT("'" & $A$1 & "'!A:O"), 15, FALSE) | L4: =vlookup(E4, Prices!$A:$G,7,)*K4 -> 0 | N4: Chicken wings | O4: Pcs | P4: {=VLOOKUP(N4, INDIRECT("'" & $A$1 & "'!A:O"), 13, FALSE)/ vlookup(N4,BACKEND2!$A$1:$F1000,5,)} -> 11 | Q4: =vlookup(N4, Prices!$A:$F,3,)*P4 -> 99297 | S4: =vlookup(N4, Prices!$A:$G,7,)*R4 -> 0 | T4: =VLOOKUP(N4, INDIRECT("'" & $A$1 & "'!A:O"), 15, FALSE) | U4: =vlookup(N4, Prices!$A:$G,7,)*T4 -> 0 | V4: pork chops | W4: pork ribs | X4: Tilapia Fillet | Y4: chicken wings | Z4: chicken whole breast | AA4: 160 breast
A5: Other Common Items | B5: =H1 -> 1149613 | E5: Irish potatoes | F5: Kg | G5: =VLOOKUP(E5, INDIRECT("'" & $A$1 & "'!A:O"), 13, FALSE) -> 49.85 | H5: =vlookup(E5, Prices!$A:$G,7,)*G5 -> 114655 | I5: =VLOOKUP(E5, INDIRECT("'" & $A$1 & "'!A:O"), 14, FALSE) | J5: =vlookup(E5, Prices!$A:$G,7,)*I5 -> 0 | K5: =VLOOKUP(E5, INDIRECT("'" & $A$1 & "'!A:O"), 15, FALSE) | L5: =vlookup(E5, Prices!$A:$G,7,)*K5 -> 0 | N5: Chicken skewers | O5: Pcs | P5: {=VLOOKUP(N5, INDIRECT("'" & $A$1 & "'!A:O"), 13, FALSE)/ vlookup(N5,BACKEND2!$A$1:$F1000,5,)} -> 5.5 | Q5: =vlookup(N5, Prices!$A:$F,3,)*P5 -> 38940 | R5: =VLOOKUP(N5, INDIRECT("'" & $A$1 & "'!A:O"), 14, FALSE) | S5: =vlookup(N5, Prices!$A:$G,7,)*R5 -> 0 | T5: =VLOOKUP(N5, INDIRECT("'" & $A$1 & "'!A:O"), 15, FALSE) | U5: =vlookup(N5, Prices!$A:$G,7,)*T5 -> 0 | X5: fish fnger | Y5: chicken lollipop | Z5: chicken creole | AA5: chicken curry | AB5: 1
A6: Transfers | B6: =J1 -> 0 | E6: Mozzarella cheese | F6: Kg | G6: =VLOOKUP(E6, INDIRECT("'" & $A$1 & "'!A:O"), 13, FALSE) -> 4 | H6: =vlookup(E6, Prices!$A:$G,7,)*G6 -> 88000 | I6: =VLOOKUP(E6, INDIRECT("'" & $A$1 & "'!A:O"), 14, FALSE) | J6: =vlookup(E6, Prices!$A:$G,7,)*I6 -> 0 | K6: =VLOOKUP(E6, INDIRECT("'" & $A$1 & "'!A:O"), 15, FALSE) | L6: =vlookup(E6, Prices!$A:$G,7,)*K6 -> 0 | N6: Goat ribs | O6: Ptns | P6: {=VLOOKUP(N6, INDIRECT("'" & $A$1 & "'!A:O"), 13, FALSE)/ vlookup(N6,BACKEND2!$A$1:$F1000,5,)} -> 4 | Q6: =vlookup(N6, Prices!$A:$F,3,)*P6 -> 42480 | R6: =VLOOKUP(N6, INDIRECT("'" & $A$1 & "'!A:O"), 14, FALSE) | S6: =vlookup(N6, Prices!$A:$G,7,)*R6 -> 0 | T6: =VLOOKUP(N6, INDIRECT("'" & $A$1 & "'!A:O"), 15, FALSE) | U6: =vlookup(N6, Prices!$A:$G,7,)*T6 -> 0 | X6: ninj turtles | AA6: ceasar salad | AB6: 1
A7: Damages | B7: =L1 -> 0 | E7: Plantain | F7: Cluster | G7: =VLOOKUP(E7, INDIRECT("'" & $A$1 & "'!A:O"), 13, FALSE) -> 9 | H7: =vlookup(E7, Prices!$A:$G,7,)*G7 -> 77142.857 | I7: =VLOOKUP(E7, INDIRECT("'" & $A$1 & "'!A:O"), 14, FALSE) | J7: =vlookup(E7, Prices!$A:$G,7,)*I7 -> 0 | K7: =VLOOKUP(E7, INDIRECT("'" & $A$1 & "'!A:O"), 15, FALSE) | L7: =vlookup(E7, Prices!$A:$G,7,)*K7 -> 0 | N7: Chicken stroganoff | O7: Ptns | P7: {=VLOOKUP(N7, INDIRECT("'" & $A$1 & "'!A:O"), 13, FALSE)/ vlookup(N7,BACKEND2!$A$1:$F1000,5,)} -> 13.5 | Q7: =vlookup(N7, Prices!$A:$F,3,)*P7 -> 54162 | R7: =VLOOKUP(N7, INDIRECT("'" & $A$1 & "'!A:O"), 14, FALSE) | S7: =vlookup(N7, Prices!$A:$G,7,)*R7 -> 0 | T7: =VLOOKUP(N7, INDIRECT("'" & $A$1 & "'!A:O"), 15, FALSE) | U7: =vlookup(N7, Prices!$A:$G,7,)*T7 -> 0 | AA7: chicken sandwich | AB7: 1
A8: Total (Less Transfers) | B8: =sum(B4:B7) -> 2082099 | E8: Patio Bella take away bags | F8: Pcs | G8: =VLOOKUP(E8, INDIRECT("'" & $A$1 & "'!A:O"), 13, FALSE) -> 60 | H8: =vlookup(E8, Prices!$A:$G,7,)*G8 -> 51000 | I8: =VLOOKUP(E8, INDIRECT("'" & $A$1 & "'!A:O"), 14, FALSE) | J8: =vlookup(E8, Prices!$A:$G,7,)*I8 -> 0 | K8: =VLOOKUP(E8, INDIRECT("'" & $A$1 & "'!A:O"), 15, FALSE) | L8: =vlookup(E8, Prices!$A:$G,7,)*K8 -> 0 | N8: Beef burger patty | O8: Ptns | P8: {=VLOOKUP(N8, INDIRECT("'" & $A$1 & "'!A:O"), 13, FALSE)/ vlookup(N8,BACKEND2!$A$1:$F1000,5,)} -> 4 | Q8: =vlookup(N8, Prices!$A:$F,3,)*P8 -> 19116 | R8: =VLOOKUP(N8, INDIRECT("'" & $A$1 & "'!A:O"), 14, FALSE) | S8: =vlookup(N8, Prices!$A:$G,7,)*R8 -> 0 | T8: =VLOOKUP(N8, INDIRECT("'" & $A$1 & "'!A:O"), 15, FALSE) | U8: =vlookup(N8, Prices!$A:$G,7,)*T8 -> 0 | V8: 1kg = 2plates | AA8: maze fit | AB8: 1
E9: Basmati rice | F9: Kg | G9: =VLOOKUP(E9, INDIRECT("'" & $A$1 & "'!A:O"), 13, FALSE) -> 4.9 | H9: =vlookup(E9, Prices!$A:$G,7,)*G9 -> 49000 | I9: =VLOOKUP(E9, INDIRECT("'" & $A$1 & "'!A:O"), 14, FALSE) | J9: =vlookup(E9, Prices!$A:$G,7,)*I9 -> 0 | K9: =VLOOKUP(E9, INDIRECT("'" & $A$1 & "'!A:O"), 15, FALSE) | L9: =vlookup(E9, Prices!$A:$G,7,)*K9 -> 0 | N9: Pork ribs | O9: Ptns | P9: {=VLOOKUP(N9, INDIRECT("'" & $A$1 & "'!A:O"), 13, FALSE)/ vlookup(N9,BACKEND2!$A$1:$F1000,5,)} -> 4 | Q9: =vlookup(N9, Prices!$A:$F,3,)*P9 -> 33180 | R9: =VLOOKUP(N9, INDIRECT("'" & $A$1 & "'!A:O"), 14, FALSE) | S9: =vlookup(N9, Prices!$A:$G,7,)*R9 -> 0 | T9: =VLOOKUP(N9, INDIRECT("'" & $A$1 & "'!A:O"), 15, FALSE) | U9: =vlookup(N9, Prices!$A:$G,7,)*T9 -> 0 | AA9: chicken tender | AB9: 2portions
A10: Performance Summary: Gifts Included in Sales | E10: Pilau masala | F10: Kg | G10: =VLOOKUP(E10, INDIRECT("'" & $A$1 & "'!A:O"), 13, FALSE) -> 0.462 | H10: =vlookup(E10, Prices!$A:$G,7,)*G10 -> 43890 | I10: =VLOOKUP(E10, INDIRECT("'" & $A$1 & "'!A:O"), 14, FALSE) | J10: =vlookup(E10, Prices!$A:$G,7,)*I10 -> 0 | K10: =VLOOKUP(E10, INDIRECT("'" & $A$1 & "'!A:O"), 15, FALSE) | L10: =vlookup(E10, Prices!$A:$G,7,)*K10 -> 0 | N10: Tilapia fillet | O10: Pcs | P10: {=VLOOKUP(N10, INDIRECT("'" & $A$1 & "'!A:O"), 13, FALSE)/ vlookup(N10,BACKEND2!$A$1:$F1000,5,)} -> 3 | Q10: =vlookup(N10, Prices!$A:$F,3,)*P10 -> 30798 | R10: =VLOOKUP(N10, INDIRECT("'" & $A$1 & "'!A:O"), 14, FALSE) | S10: =vlookup(N10, Prices!$A:$G,7,)*R10 -> 0 | T10: =VLOOKUP(N10, INDIRECT("'" & $A$1 & "'!A:O"), 15, FALSE) | U10: =vlookup(N10, Prices!$A:$G,7,)*T10 -> 0 | V10: wings beef steak | AA10: chicken alfedo pasta | AB10: 1
A11: Sales (Gifts Included) | E11: Aromat | F11: Kg | G11: =VLOOKUP(E11, INDIRECT("'" & $A$1 & "'!A:O"), 13, FALSE) -> 0.864 | H11: =vlookup(E11, Prices!$A:$G,7,)*G11 -> 38880 | I11: =VLOOKUP(E11, INDIRECT("'" & $A$1 & "'!A:O"), 14, FALSE) | J11: =vlookup(E11, Prices!$A:$G,7,)*I11 -> 0 | K11: =VLOOKUP(E11, INDIRECT("'" & $A$1 & "'!A:O"), 15, FALSE) | L11: =vlookup(E11, Prices!$A:$G,7,)*K11 -> 0 | N11: Beef sausages | O11: Ptns | P11: {=VLOOKUP(N11, INDIRECT("'" & $A$1 & "'!A:O"), 13, FALSE)/ vlookup(N11,BACKEND2!$A$1:$F1000,5,)} -> 1.5 | Q11: =vlookup(N11, Prices!$A:$F,3,)*P11 -> 6555 | R11: =VLOOKUP(N11, INDIRECT("'" & $A$1 & "'!A:O"), 14, FALSE) | S11: =vlookup(N11, Prices!$A:$G,7,)*R11 -> 0 | T11: =VLOOKUP(N11, INDIRECT("'" & $A$1 & "'!A:O"), 15, FALSE) | U11: =vlookup(N11, Prices!$A:$G,7,)*T11 -> 0 | AA11: chicken alfedo pasta | AB11: 1
A12: Cost of Goods Sold | B12: =B8 -> 2082099 | E12: Baking flour | F12: Kg | G12: =VLOOKUP(E12, INDIRECT("'" & $A$1 & "'!A:O"), 13, FALSE) -> 10.754 | H12: =vlookup(E12, Prices!$A:$G,7,)*G12 -> 35843.082 | I12: =VLOOKUP(E12, INDIRECT("'" & $A$1 & "'!A:O"), 14, FALSE) | J12: =vlookup(E12, Prices!$A:$G,7,)*I12 -> 0 | K12: =VLOOKUP(E12, INDIRECT("'" & $A$1 & "'!A:O"), 15, FALSE) | L12: =vlookup(E12, Prices!$A:$G,7,)*K12 -> 0 | N12: Beef fillet | O12: Ptns | P12: {=VLOOKUP(N12, INDIRECT("'" & $A$1 & "'!A:O"), 13, FALSE)/ vlookup(N12,BACKEND2!$A$1:$F1000,5,)} -> 1 | Q12: =vlookup(N12, Prices!$A:$F,3,)*P12 -> 9558 | R12: =VLOOKUP(N12, INDIRECT("'" & $A$1 & "'!A:O"), 14, FALSE) | S12: =vlookup(N12, Prices!$A:$G,7,)*R12 -> 0 | T12: =VLOOKUP(N12, INDIRECT("'" & $A$1 & "'!A:O"), 15, FALSE) | U12: =vlookup(N12, Prices!$A:$G,7,)*T12 -> 0 | AA12: chicken burger | AB12: 1
A13: Gifts | E13: Tomatoes | F13: Kg | G13: =VLOOKUP(E13, INDIRECT("'" & $A$1 & "'!A:O"), 13, FALSE) -> 8.469 | H13: =vlookup(E13, Prices!$A:$G,7,)*G13 -> 23713.2 | I13: =VLOOKUP(E13, INDIRECT("'" & $A$1 & "'!A:O"), 14, FALSE) | J13: =vlookup(E13, Prices!$A:$G,7,)*I13 -> 0 | K13: =VLOOKUP(E13, INDIRECT("'" & $A$1 & "'!A:O"), 15, FALSE) | L13: =vlookup(E13, Prices!$A:$G,7,)*K13 -> 0 | N13: Bacon | O13: Pcs | P13: {=VLOOKUP(N13, INDIRECT("'" & $A$1 & "'!A:O"), 13, FALSE)/ vlookup(N13,BACKEND2!$A$1:$F1000,5,)} -> 0 | Q13: =vlookup(N13, Prices!$A:$F,3,)*P13 -> 0 | R13: =VLOOKUP(N13, INDIRECT("'" & $A$1 & "'!A:O"), 14, FALSE) | S13: =vlookup(N13, Prices!$A:$G,7,)*R13 -> 0 | T13: =VLOOKUP(N13, INDIRECT("'" & $A$1 & "'!A:O"), 15, FALSE) | U13: =vlookup(N13, Prices!$A:$G,7,)*T13 -> 0 | V13: Sausages | W13: bacon | X13: beef steak | Y13: minced meat | Z13: pork chops | AA13: tuscan pasta | AB13: 1
A14: Profit | B14: =B11-B12 -> -2082099 | E14: Mayonnaise big tin | F14: Kg | G14: =VLOOKUP(E14, INDIRECT("'" & $A$1 & "'!A:O"), 13, FALSE) -> 0.705 | H14: =vlookup(E14, Prices!$A:$G,7,)*G14 -> 22380.952 | I14: =VLOOKUP(E14, INDIRECT("'" & $A$1 & "'!A:O"), 14, FALSE) | J14: =vlookup(E14, Prices!$A:$G,7,)*I14 -> 0 | K14: =VLOOKUP(E14, INDIRECT("'" & $A$1 & "'!A:O"), 15, FALSE) | L14: =vlookup(E14, Prices!$A:$G,7,)*K14 -> 0 | N14: Sizzling pork | O14: Ptns | P14: {=VLOOKUP(N14, INDIRECT("'" & $A$1 & "'!A:O"), 13, FALSE)/ vlookup(N14,BACKEND2!$A$1:$F1000,5,)} -> 1 | Q14: =vlookup(N14, Prices!$A:$F,3,)*P14 -> 6726 | R14: =VLOOKUP(N14, INDIRECT("'" & $A$1 & "'!A:O"), 14, FALSE) | S14: =vlookup(N14, Prices!$A:$G,7,)*R14 -> 0 | T14: =VLOOKUP(N14, INDIRECT("'" & $A$1 & "'!A:O"), 15, FALSE) | U14: =vlookup(N14, Prices!$A:$G,7,)*T14 -> 0 | V14: meat feast (1pc) | W14: classic english | X14: cheese steak | Y14: beef pizza | AA14: classic hawain pizza | AB14: 1
A15: Cogs% | B15: =B12/B11 -> #DIV/0! | E15: Fish Sauce | F15: Liters | G15: =VLOOKUP(E15, INDIRECT("'" & $A$1 & "'!A:O"), 13, FALSE) -> 0.709 | H15: =vlookup(E15, Prices!$A:$G,7,)*G15 -> 21742.667 | I15: =VLOOKUP(E15, INDIRECT("'" & $A$1 & "'!A:O"), 14, FALSE) | J15: =vlookup(E15, Prices!$A:$G,7,)*I15 -> 0 | K15: =VLOOKUP(E15, INDIRECT("'" & $A$1 & "'!A:O"), 15, FALSE) | L15: =vlookup(E15, Prices!$A:$G,7,)*K15 -> 0 | N15: Carribean jerk | O15: Ptns | P15: {=VLOOKUP(N15, INDIRECT("'" & $A$1 & "'!A:O"), 13, FALSE)/ vlookup(N15,BACKEND2!$A$1:$F1000,5,)} -> 3 | Q15: =vlookup(N15, Prices!$A:$F,3,)*P15 -> 19116 | R15: =VLOOKUP(N15, INDIRECT("'" & $A$1 & "'!A:O"), 14, FALSE) | S15: =vlookup(N15, Prices!$A:$G,7,)*R15 -> 0 | T15: =VLOOKUP(N15, INDIRECT("'" & $A$1 & "'!A:O"), 15, FALSE) | U15: =vlookup(N15, Prices!$A:$G,7,)*T15 -> 0 | W15: penna cabonara | X15: teaxs steak slad | Y15: beef samosa | AA15: chiptole chicken bowl | AB15: 1
A16: Profit Margin | B16: =B14/B11 -> #DIV/0! | E16: Oyster sauce | F16: Liters | G16: =VLOOKUP(E16, INDIRECT("'" & $A$1 & "'!A:O"), 13, FALSE) -> 0.532 | H16: =vlookup(E16, Prices!$A:$G,7,)*G16 -> 20862.745 | I16: =VLOOKUP(E16, INDIRECT("'" & $A$1 & "'!A:O"), 14, FALSE) | J16: =vlookup(E16, Prices!$A:$G,7,)*I16 -> 0 | K16: =VLOOKUP(E16, INDIRECT("'" & $A$1 & "'!A:O"), 15, FALSE) | L16: =vlookup(E16, Prices!$A:$G,7,)*K16 -> 0 | N16: Chicken burger | O16: Ptns | P16: {=VLOOKUP(N16, INDIRECT("'" & $A$1 & "'!A:O"), 13, FALSE)/ vlookup(N16,BACKEND2!$A$1:$F1000,5,)} -> 8 | Q16: =vlookup(N16, Prices!$A:$F,3,)*P16 -> 24544 | S16: =vlookup(N16, Prices!$A:$G,7,)*R16 -> 0 | T16: =VLOOKUP(N16, INDIRECT("'" & $A$1 & "'!A:O"), 15, FALSE) | U16: =vlookup(N16, Prices!$A:$G,7,)*T16 -> 0 | Y16: pasta doronez | AA16: katogo | AB16: 3portions
E17: Parmesan cheese | F17: Kg | G17: =VLOOKUP(E17, INDIRECT("'" & $A$1 & "'!A:O"), 13, FALSE) -> 0.214 | H17: =vlookup(E17, Prices!$A:$G,7,)*G17 -> 16906 | I17: =VLOOKUP(E17, INDIRECT("'" & $A$1 & "'!A:O"), 14, FALSE) | J17: =vlookup(E17, Prices!$A:$G,7,)*I17 -> 0 | K17: =VLOOKUP(E17, INDIRECT("'" & $A$1 & "'!A:O"), 15, FALSE) | L17: =vlookup(E17, Prices!$A:$G,7,)*K17 -> 0 | N17: Chicken breast | O17: Pcs | P17: {=VLOOKUP(N17, INDIRECT("'" & $A$1 & "'!A:O"), 13, FALSE)/ vlookup(N17,BACKEND2!$A$1:$F1000,5,)} -> 0 | Q17: =vlookup(N17, Prices!$A:$F,3,)*P17 -> 0 | R17: =VLOOKUP(N17, INDIRECT("'" & $A$1 & "'!A:O"), 14, FALSE) | S17: =vlookup(N17, Prices!$A:$G,7,)*R17 -> 0 | T17: =VLOOKUP(N17, INDIRECT("'" & $A$1 & "'!A:O"), 15, FALSE) | U17: =vlookup(N17, Prices!$A:$G,7,)*T17 -> 0 | V17: Eggs | AA17: chicken and egg wrap
A18: Performance Summary: Gifts Excluded | E18: Square takeaway containers | F18: Pcs | G18: =VLOOKUP(E18, INDIRECT("'" & $A$1 & "'!A:O"), 13, FALSE) -> 35 | H18: =vlookup(E18, Prices!$A:$G,7,)*G18 -> 12460 | I18: =VLOOKUP(E18, INDIRECT("'" & $A$1 & "'!A:O"), 14, FALSE) | J18: =vlookup(E18, Prices!$A:$G,7,)*I18 -> 0 | K18: =VLOOKUP(E18, INDIRECT("'" & $A$1 & "'!A:O"), 15, FALSE) | L18: =vlookup(E18, Prices!$A:$G,7,)*K18 -> 0 | N18: Beef samosas | O18: Pcs | P18: {=VLOOKUP(N18, INDIRECT("'" & $A$1 & "'!A:O"), 13, FALSE)/ vlookup(N18,BACKEND2!$A$1:$F1000,5,)} -> 1 | Q18: =vlookup(N18, Prices!$A:$F,3,)*P18 -> 5756 | R18: =VLOOKUP(N18, INDIRECT("'" & $A$1 & "'!A:O"), 14, FALSE) | S18: =vlookup(N18, Prices!$A:$G,7,)*R18 -> 0 | T18: =VLOOKUP(N18, INDIRECT("'" & $A$1 & "'!A:O"), 15, FALSE) | U18: =vlookup(N18, Prices!$A:$G,7,)*T18 -> 0 | W18: Jerk chicken | X18: chicken pizzza | Y18: minced meat | Z18: Beef steak | AA18: Ham
A19: Sales (Gifts Removed) | B19: =B11 | E19: Ketchup 5L | F19: kg | G19: =VLOOKUP(E19, INDIRECT("'" & $A$1 & "'!A:O"), 13, FALSE) -> 0.953 | H19: =vlookup(E19, Prices!$A:$G,7,)*G19 -> 11436 | I19: =VLOOKUP(E19, INDIRECT("'" & $A$1 & "'!A:O"), 14, FALSE) | J19: =vlookup(E19, Prices!$A:$G,7,)*I19 -> 0 | K19: =VLOOKUP(E19, INDIRECT("'" & $A$1 & "'!A:O"), 15, FALSE) | L19: =vlookup(E19, Prices!$A:$G,7,)*K19 -> 0 | N19: Beef Stew | O19: Ptns | P19: {=VLOOKUP(N19, INDIRECT("'" & $A$1 & "'!A:O"), 13, FALSE)/ vlookup(N19,BACKEND2!$A$1:$F1000,5,)} -> 6 | Q19: =vlookup(N19, Prices!$A:$F,3,)*P19 -> 51612 | R19: =VLOOKUP(N19, INDIRECT("'" & $A$1 & "'!A:O"), 14, FALSE) | S19: =vlookup(N19, Prices!$A:$G,7,)*R19 -> 0 | T19: =VLOOKUP(N19, INDIRECT("'" & $A$1 & "'!A:O"), 15, FALSE) | U19: =vlookup(N19, Prices!$A:$G,7,)*T19 -> 0 | W19: sofia first3 = 2 | Y19: pasta | Z19: steak salad
A20: Cost of Goods Sold | B20: =B12 -> 2082099 | E20: Onions | F20: Kg | G20: =VLOOKUP(E20, INDIRECT("'" & $A$1 & "'!A:O"), 13, FALSE) -> 3.265 | H20: =vlookup(E20, Prices!$A:$G,7,)*G20 -> 11101 | I20: =VLOOKUP(E20, INDIRECT("'" & $A$1 & "'!A:O"), 14, FALSE) | J20: =vlookup(E20, Prices!$A:$G,7,)*I20 -> 0 | K20: =VLOOKUP(E20, INDIRECT("'" & $A$1 & "'!A:O"), 15, FALSE) | L20: =vlookup(E20, Prices!$A:$G,7,)*K20 -> 0 | N20: Beef pizza | O20: Ptns | P20: {=VLOOKUP(N20, INDIRECT("'" & $A$1 & "'!A:O"), 13, FALSE)/ vlookup(N20,BACKEND2!$A$1:$F1000,5,)} -> 1 | Q20: =vlookup(N20, Prices!$A:$F,3,)*P20 -> 4142 | R20: =VLOOKUP(N20, INDIRECT("'" & $A$1 & "'!A:O"), 14, FALSE) | S20: =vlookup(N20, Prices!$A:$G,7,)*R20 -> 0 | T20: =VLOOKUP(N20, INDIRECT("'" & $A$1 & "'!A:O"), 15, FALSE) | U20: =vlookup(N20, Prices!$A:$G,7,)*T20 -> 0 | W20: 1rder = 2 pc | Y20: beef pizza | Z20: beef pilau half portion
A21: Profit | B21: =B19-B20 -> -2082099 | E21: Fresh milk/Jesa | F21: Liters | G21: =VLOOKUP(E21, INDIRECT("'" & $A$1 & "'!A:O"), 13, FALSE) -> 4.5 | H21: =vlookup(E21, Prices!$A:$G,7,)*G21 -> 10800 | I21: =VLOOKUP(E21, INDIRECT("'" & $A$1 & "'!A:O"), 14, FALSE) | J21: =vlookup(E21, Prices!$A:$G,7,)*I21 -> 0 | K21: =VLOOKUP(E21, INDIRECT("'" & $A$1 & "'!A:O"), 15, FALSE) | L21: =vlookup(E21, Prices!$A:$G,7,)*K21 -> 0 | N21: Chicken lollipos | O21: Pcs | P21: {=VLOOKUP(N21, INDIRECT("'" & $A$1 & "'!A:O"), 13, FALSE)/ vlookup(N21,BACKEND2!$A$1:$F1000,5,)} -> 7 | Q21: =vlookup(N21, Prices!$A:$F,3,)*P21 -> 52038 | R21: =VLOOKUP(N21, INDIRECT("'" & $A$1 & "'!A:O"), 14, FALSE) | S21: =vlookup(N21, Prices!$A:$G,7,)*R21 -> 0 | T21: =VLOOKUP(N21, INDIRECT("'" & $A$1 & "'!A:O"), 15, FALSE) | U21: =vlookup(N21, Prices!$A:$G,7,)*T21 -> 0 | Z21: fillys finest half portion
A22: Cogs% | B22: =B20/B19 -> #DIV/0! | E22: Fresh Mushroom | F22: Kg | G22: =VLOOKUP(E22, INDIRECT("'" & $A$1 & "'!A:O"), 13, FALSE) -> 0.95 | H22: =vlookup(E22, Prices!$A:$G,7,)*G22 -> 9500 | I22: =VLOOKUP(E22, INDIRECT("'" & $A$1 & "'!A:O"), 14, FALSE) | J22: =vlookup(E22, Prices!$A:$G,7,)*I22 -> 0 | K22: =VLOOKUP(E22, INDIRECT("'" & $A$1 & "'!A:O"), 15, FALSE) | L22: =vlookup(E22, Prices!$A:$G,7,)*K22 -> 0 | N22: Bolognese | O22: Ptns | P22: {=VLOOKUP(N22, INDIRECT("'" & $A$1 & "'!A:O"), 13, FALSE)/ vlookup(N22,BACKEND2!$A$1:$F1000,5,)} -> 0 | Q22: =vlookup(N22, Prices!$A:$F,3,)*P22 -> 0 | R22: =VLOOKUP(N22, INDIRECT("'" & $A$1 & "'!A:O"), 14, FALSE) | S22: =vlookup(N22, Prices!$A:$G,7,)*R22 -> 0 | T22: =VLOOKUP(N22, INDIRECT("'" & $A$1 & "'!A:O"), 15, FALSE) | U22: =vlookup(N22, Prices!$A:$G,7,)*T22 -> 0 | W22: Sausages | X22: plantain 1cluster =
A23: Profit Margin | B23: =B21/B19 -> #DIV/0! | E23: Garlic | F23: Kg | G23: =VLOOKUP(E23, INDIRECT("'" & $A$1 & "'!A:O"), 13, FALSE) -> 0.694 | H23: =vlookup(E23, Prices!$A:$G,7,)*G23 -> 9369 | I23: =VLOOKUP(E23, INDIRECT("'" & $A$1 & "'!A:O"), 14, FALSE) | J23: =vlookup(E23, Prices!$A:$G,7,)*I23 -> 0 | K23: =VLOOKUP(E23, INDIRECT("'" & $A$1 & "'!A:O"), 15, FALSE) | L23: =vlookup(E23, Prices!$A:$G,7,)*K23 -> 0 | N23: Chicken Samosas | O23: Pcs | P23: {=VLOOKUP(N23, INDIRECT("'" & $A$1 & "'!A:O"), 13, FALSE)/ vlookup(N23,BACKEND2!$A$1:$F1000,5,)} -> 5 | Q23: =vlookup(N23, Prices!$A:$F,3,)*P23 -> 12980 | R23: =VLOOKUP(N23, INDIRECT("'" & $A$1 & "'!A:O"), 14, FALSE) | S23: =vlookup(N23, Prices!$A:$G,7,)*R23 -> 0 | T23: =VLOOKUP(N23, INDIRECT("'" & $A$1 & "'!A:O"), 15, FALSE) | U23: =vlookup(N23, Prices!$A:$G,7,)*T23 -> 0
E24: Yellow pepper | F24: Kg | G24: =VLOOKUP(E24, INDIRECT("'" & $A$1 & "'!A:O"), 13, FALSE) -> 1.035 | H24: =vlookup(E24, Prices!$A:$G,7,)*G24 -> 9315 | I24: =VLOOKUP(E24, INDIRECT("'" & $A$1 & "'!A:O"), 14, FALSE) | J24: =vlookup(E24, Prices!$A:$G,7,)*I24 -> 0 | K24: =VLOOKUP(E24, INDIRECT("'" & $A$1 & "'!A:O"), 15, FALSE) | L24: =vlookup(E24, Prices!$A:$G,7,)*K24 -> 0 | N24: Chicken spring rolls | O24: Pcs | P24: {=VLOOKUP(N24, INDIRECT("'" & $A$1 & "'!A:O"), 13, FALSE)/ vlookup(N24,BACKEND2!$A$1:$F1000,5,)} -> 5 | Q24: =vlookup(N24, Prices!$A:$F,3,)*P24 -> 23600 | R24: =VLOOKUP(N24, INDIRECT("'" & $A$1 & "'!A:O"), 14, FALSE) | S24: =vlookup(N24, Prices!$A:$G,7,)*R24 -> 0 | T24: =VLOOKUP(N24, INDIRECT("'" & $A$1 & "'!A:O"), 15, FALSE) | U24: =vlookup(N24, Prices!$A:$G,7,)*T24 -> 0
A25: TOP 10 SELLERS | B25: plates/portions | C25: Amount | E25: Ketchup sachets | F25: Pcs | G25: =VLOOKUP(E25, INDIRECT("'" & $A$1 & "'!A:O"), 13, FALSE) -> 45 | H25: =vlookup(E25, Prices!$A:$G,7,)*G25 -> 9000 | I25: =VLOOKUP(E25, INDIRECT("'" & $A$1 & "'!A:O"), 14, FALSE) | J25: =vlookup(E25, Prices!$A:$G,7,)*I25 -> 0 | K25: =VLOOKUP(E25, INDIRECT("'" & $A$1 & "'!A:O"), 15, FALSE) | L25: =vlookup(E25, Prices!$A:$G,7,)*K25 -> 0 | N25: Chicken pizza | O25: Ptns | P25: {=VLOOKUP(N25, INDIRECT("'" & $A$1 & "'!A:O"), 13, FALSE)/ vlookup(N25,BACKEND2!$A$1:$F1000,5,)} -> 11 | Q25: =vlookup(N25, Prices!$A:$F,3,)*P25 -> 33748 | R25: =VLOOKUP(N25, INDIRECT("'" & $A$1 & "'!A:O"), 14, FALSE) | S25: =vlookup(N25, Prices!$A:$G,7,)*R25 -> 0 | T25: =VLOOKUP(N25, INDIRECT("'" & $A$1 & "'!A:O"), 15, FALSE) | U25: =vlookup(N25, Prices!$A:$G,7,)*T25 -> 0
E26: Red pepper | F26: Kg | G26: =VLOOKUP(E26, INDIRECT("'" & $A$1 & "'!A:O"), 13, FALSE) -> 0.891 | H26: =vlookup(E26, Prices!$A:$G,7,)*G26 -> 8019 | I26: =VLOOKUP(E26, INDIRECT("'" & $A$1 & "'!A:O"), 14, FALSE) | J26: =vlookup(E26, Prices!$A:$G,7,)*I26 -> 0 | K26: =VLOOKUP(E26, INDIRECT("'" & $A$1 & "'!A:O"), 15, FALSE) | L26: =vlookup(E26, Prices!$A:$G,7,)*K26 -> 0 | N26: Veg Samosas | O26: Pcs | P26: {=VLOOKUP(N26, INDIRECT("'" & $A$1 & "'!A:O"), 13, FALSE)/ vlookup(N26,BACKEND2!$A$1:$F1000,5,)} -> 1 | Q26: =vlookup(N26, Prices!$A:$F,3,)*P26 -> 2000 | R26: =VLOOKUP(N26, INDIRECT("'" & $A$1 & "'!A:O"), 14, FALSE) | S26: =vlookup(N26, Prices!$A:$G,7,)*R26 -> 0 | T26: =VLOOKUP(N26, INDIRECT("'" & $A$1 & "'!A:O"), 15, FALSE) | U26: =vlookup(N26, Prices!$A:$G,7,)*T26 -> 0 | W26: Irish container
E27: Light soy sauce | F27: Liters | G27: =VLOOKUP(E27, INDIRECT("'" & $A$1 & "'!A:O"), 13, FALSE) -> 0.5 | H27: =vlookup(E27, Prices!$A:$G,7,)*G27 -> 8000 | J27: =vlookup(E27, Prices!$A:$G,7,)*I27 -> 0 | K27: =VLOOKUP(E27, INDIRECT("'" & $A$1 & "'!A:O"), 15, FALSE) | L27: =vlookup(E27, Prices!$A:$G,7,)*K27 -> 0 | N27: Whole fish | O27: Ptns | P27: {=VLOOKUP(N27, INDIRECT("'" & $A$1 & "'!A:O"), 13, FALSE)/ vlookup(N27,BACKEND2!$A$1:$F1000,5,)} -> 7 | Q27: =vlookup(N27, Prices!$A:$F,3,)*P27 -> 112000 | R27: =VLOOKUP(N27, INDIRECT("'" & $A$1 & "'!A:O"), 14, FALSE) | S27: =vlookup(N27, Prices!$A:$G,7,)*R27 -> 0 | T27: =VLOOKUP(N27, INDIRECT("'" & $A$1 & "'!A:O"), 15, FALSE) | U27: =vlookup(N27, Prices!$A:$G,7,)*T27 -> 0 | W27: 0.415
E28: Cherry Tomatoes | F28: Kg | G28: =VLOOKUP(E28, INDIRECT("'" & $A$1 & "'!A:O"), 13, FALSE) -> 0.384 | H28: =vlookup(E28, Prices!$A:$G,7,)*G28 -> 7822.2222 | I28: =VLOOKUP(E28, INDIRECT("'" & $A$1 & "'!A:O"), 14, FALSE) | J28: =vlookup(E28, Prices!$A:$G,7,)*I28 -> 0 | K28: =VLOOKUP(E28, INDIRECT("'" & $A$1 & "'!A:O"), 15, FALSE) | L28: =vlookup(E28, Prices!$A:$G,7,)*K28 -> 0 | N28: Pork chops | O28: Pcs | P28: {=VLOOKUP(N28, INDIRECT("'" & $A$1 & "'!A:O"), 13, FALSE)/ vlookup(N28,BACKEND2!$A$1:$F1000,5,)} -> 2 | Q28: =vlookup(N28, Prices!$A:$F,3,)*P28 -> 20084 | R28: =VLOOKUP(N28, INDIRECT("'" & $A$1 & "'!A:O"), 14, FALSE) | S28: =vlookup(N28, Prices!$A:$G,7,)*R28 -> 0 | T28: =VLOOKUP(N28, INDIRECT("'" & $A$1 & "'!A:O"), 15, FALSE) | U28: =vlookup(N28, Prices!$A:$G,7,)*T28 -> 0
E29: Eggs | F29: Pcs | G29: =VLOOKUP(E29, INDIRECT("'" & $A$1 & "'!A:O"), 13, FALSE) -> 19 | H29: =vlookup(E29, Prices!$A:$G,7,)*G29 -> 7600 | I29: =VLOOKUP(E29, INDIRECT("'" & $A$1 & "'!A:O"), 14, FALSE) | J29: =vlookup(E29, Prices!$A:$G,7,)*I29 -> 0 | K29: =VLOOKUP(E29, INDIRECT("'" & $A$1 & "'!A:O"), 15, FALSE) | L29: =vlookup(E29, Prices!$A:$G,7,)*K29 -> 0 | N29: Goat stew | O29: Ptns | P29: {=VLOOKUP(N29, INDIRECT("'" & $A$1 & "'!A:O"), 13, FALSE)/ vlookup(N29,BACKEND2!$A$1:$F1000,5,)} -> 1 | Q29: =vlookup(N29, Prices!$A:$F,3,)*P29 -> 6372 | R29: =VLOOKUP(N29, INDIRECT("'" & $A$1 & "'!A:O"), 14, FALSE) | S29: =vlookup(N29, Prices!$A:$G,7,)*R29 -> 0 | T29: =VLOOKUP(N29, INDIRECT("'" & $A$1 & "'!A:O"), 15, FALSE) | U29: =vlookup(N29, Prices!$A:$G,7,)*T29 -> 0 | W29: 7kgs = peelings 1.5
E30: Babby Marrow | F30: Pcs | G30: =VLOOKUP(E30, INDIRECT("'" & $A$1 & "'!A:O"), 13, FALSE) -> 2 | H30: =vlookup(E30, Prices!$A:$G,7,)*G30 -> 7000 | I30: =VLOOKUP(E30, INDIRECT("'" & $A$1 & "'!A:O"), 14, FALSE) | J30: =vlookup(E30, Prices!$A:$G,7,)*I30 -> 0 | K30: =VLOOKUP(E30, INDIRECT("'" & $A$1 & "'!A:O"), 15, FALSE) | L30: =vlookup(E30, Prices!$A:$G,7,)*K30 -> 0 | N30: Fish fingers | O30: Pcs | P30: {=VLOOKUP(N30, INDIRECT("'" & $A$1 & "'!A:O"), 13, FALSE)/ vlookup(N30,BACKEND2!$A$1:$F1000,5,)} -> 1 | Q30: =vlookup(N30, Prices!$A:$F,3,)*P30 -> 6160 | R30: =VLOOKUP(N30, INDIRECT("'" & $A$1 & "'!A:O"), 14, FALSE) | S30: =vlookup(N30, Prices!$A:$G,7,)*R30 -> 0 | T30: =VLOOKUP(N30, INDIRECT("'" & $A$1 & "'!A:O"), 15, FALSE) | U30: =vlookup(N30, Prices!$A:$G,7,)*T30 -> 0
E31: Baked Beans | F31: Kg | G31: =VLOOKUP(E31, INDIRECT("'" & $A$1 & "'!A:O"), 13, FALSE) -> 0.394 | H31: =vlookup(E31, Prices!$A:$G,7,)*G31 -> 6645.7831 | I31: =VLOOKUP(E31, INDIRECT("'" & $A$1 & "'!A:O"), 14, FALSE) | J31: =vlookup(E31, Prices!$A:$G,7,)*I31 -> 0 | K31: =VLOOKUP(E31, INDIRECT("'" & $A$1 & "'!A:O"), 15, FALSE) | L31: =vlookup(E31, Prices!$A:$G,7,)*K31 -> 0 | N31: Veg Springs rolls | O31: Pcs | P31: {=VLOOKUP(N31, INDIRECT("'" & $A$1 & "'!A:O"), 13, FALSE)/ vlookup(N31,BACKEND2!$A$1:$F1000,5,)} -> 0 | Q31: =vlookup(N31, Prices!$A:$F,3,)*P31 -> 0 | R31: =VLOOKUP(N31, INDIRECT("'" & $A$1 & "'!A:O"), 14, FALSE) | S31: =vlookup(N31, Prices!$A:$G,7,)*R31 -> 0 | T31: =VLOOKUP(N31, INDIRECT("'" & $A$1 & "'!A:O"), 15, FALSE) | U31: =vlookup(N31, Prices!$A:$G,7,)*T31 -> 0
E32: Burger Buns | F32: Pcs | G32: =VLOOKUP(E32, INDIRECT("'" & $A$1 & "'!A:O"), 13, FALSE) -> 14 | H32: =vlookup(E32, Prices!$A:$G,7,)*G32 -> 6510 | I32: =VLOOKUP(E32, INDIRECT("'" & $A$1 & "'!A:O"), 14, FALSE) | J32: =vlookup(E32, Prices!$A:$G,7,)*I32 -> 0 | K32: =VLOOKUP(E32, INDIRECT("'" & $A$1 & "'!A:O"), 15, FALSE) | L32: =vlookup(E32, Prices!$A:$G,7,)*K32 -> 0 | N32: Beef Minced Meat | O32: Ptns | P32: {=VLOOKUP(N32, INDIRECT("'" & $A$1 & "'!A:O"), 13, FALSE)/ vlookup(N32,BACKEND2!$A$1:$F1000,5,)} -> 6 | Q32: =vlookup(N32, Prices!$A:$F,3,)*P32 -> 13500 | R32: =VLOOKUP(N32, INDIRECT("'" & $A$1 & "'!A:O"), 14, FALSE) | S32: =vlookup(N32, Prices!$A:$G,7,)*R32 -> 0 | T32: =VLOOKUP(N32, INDIRECT("'" & $A$1 & "'!A:O"), 15, FALSE) | U32: =vlookup(N32, Prices!$A:$G,7,)*T32 -> 0
E33: Green pepper | F33: Kg | G33: =VLOOKUP(E33, INDIRECT("'" & $A$1 & "'!A:O"), 13, FALSE) -> 1.631 | H33: =vlookup(E33, Prices!$A:$G,7,)*G33 -> 6197.8 | I33: =VLOOKUP(E33, INDIRECT("'" & $A$1 & "'!A:O"), 14, FALSE) | J33: =vlookup(E33, Prices!$A:$G,7,)*I33 -> 0 | K33: =VLOOKUP(E33, INDIRECT("'" & $A$1 & "'!A:O"), 15, FALSE) | L33: =vlookup(E33, Prices!$A:$G,7,)*K33 -> 0 | N33: Pork pizza | O33: Ptns | P33: {=VLOOKUP(N33, INDIRECT("'" & $A$1 & "'!A:O"), 13, FALSE)/ vlookup(N33,BACKEND2!$A$1:$F1000,5,)} -> 1 | Q33: =vlookup(N33, Prices!$A:$F,3,)*P33 -> 2242 | R33: =VLOOKUP(N33, INDIRECT("'" & $A$1 & "'!A:O"), 14, FALSE) | S33: =vlookup(N33, Prices!$A:$G,7,)*R33 -> 0 | T33: =VLOOKUP(N33, INDIRECT("'" & $A$1 & "'!A:O"), 15, FALSE) | U33: =vlookup(N33, Prices!$A:$G,7,)*T33 -> 0
E34: Cauliflower | F34: Pcs | G34: =VLOOKUP(E34, INDIRECT("'" & $A$1 & "'!A:O"), 13, FALSE) -> 1.5 | H34: =vlookup(E34, Prices!$A:$G,7,)*G34 -> 5700 | I34: =VLOOKUP(E34, INDIRECT("'" & $A$1 & "'!A:O"), 14, FALSE) | J34: =vlookup(E34, Prices!$A:$G,7,)*I34 -> 0 | K34: =VLOOKUP(E34, INDIRECT("'" & $A$1 & "'!A:O"), 15, FALSE) | L34: =vlookup(E34, Prices!$A:$G,7,)*K34 -> 0 | N34: Salmon | O34: Ptns | P34: {=VLOOKUP(N34, INDIRECT("'" & $A$1 & "'!A:O"), 13, FALSE)/ vlookup(N34,BACKEND2!$A$1:$F1000,5,)} -> 3 | Q34: =vlookup(N34, Prices!$A:$F,3,)*P34 -> 133812 | R34: =VLOOKUP(N34, INDIRECT("'" & $A$1 & "'!A:O"), 14, FALSE) | S34: =vlookup(N34, Prices!$A:$G,7,)*R34 -> 0 | T34: =VLOOKUP(N34, INDIRECT("'" & $A$1 & "'!A:O"), 15, FALSE) | U34: =vlookup(N34, Prices!$A:$G,7,)*T34 -> 0
E35: Croma Butter | F35: Kg | G35: =VLOOKUP(E35, INDIRECT("'" & $A$1 & "'!A:O"), 13, FALSE) -> 0.58 | H35: =vlookup(E35, Prices!$A:$G,7,)*G35 -> 5510 | I35: =VLOOKUP(E35, INDIRECT("'" & $A$1 & "'!A:O"), 14, FALSE) | J35: =vlookup(E35, Prices!$A:$G,7,)*I35 -> 0 | K35: =VLOOKUP(E35, INDIRECT("'" & $A$1 & "'!A:O"), 15, FALSE) | L35: =vlookup(E35, Prices!$A:$G,7,)*K35 -> 0 | N35: Min Chicken burger | O35: Pcs | P35: {=VLOOKUP(N35, INDIRECT("'" & $A$1 & "'!A:O"), 13, FALSE)/ vlookup(N35,BACKEND2!$A$1:$F1000,5,)} -> 0 | Q35: =vlookup(N35, Prices!$A:$F,3,)*P35 -> 0 | S35: =vlookup(N35, Prices!$A:$G,7,)*R35 -> 0 | U35: =vlookup(N35, Prices!$A:$G,7,)*T35 -> 0
B36: Total | C36: =SUM(C26:C35) -> 0 | E36: Aluminium foil | F36: Kg | G36: =VLOOKUP(E36, INDIRECT("'" & $A$1 & "'!A:O"), 13, FALSE) -> 0.441 | H36: =vlookup(E36, Prices!$A:$G,7,)*G36 -> 5292 | I36: =VLOOKUP(E36, INDIRECT("'" & $A$1 & "'!A:O"), 14, FALSE) | J36: =vlookup(E36, Prices!$A:$G,7,)*I36 -> 0 | K36: =VLOOKUP(E36, INDIRECT("'" & $A$1 & "'!A:O"), 15, FALSE) | L36: =vlookup(E36, Prices!$A:$G,7,)*K36 -> 0 | N36: Chicken Tenders | O36: Ptns | P36: {=VLOOKUP(N36, INDIRECT("'" & $A$1 & "'!A:O"), 13, FALSE)/ vlookup(N36,BACKEND2!$A$1:$F1000,5,)} -> 0 | Q36: =vlookup(N36, Prices!$A:$F,3,)*P36 -> 0 | S36: =vlookup(N36, Prices!$A:$G,7,)*R36 -> 0 | U36: =vlookup(N36, Prices!$A:$G,7,)*T36 -> 0
A37: Percentage of all items % | B37: =C36/B19 -> #DIV/0! | E37: Cling film | F37: Kg | G37: =VLOOKUP(E37, INDIRECT("'" & $A$1 & "'!A:O"), 13, FALSE) -> 0.277 | H37: =vlookup(E37, Prices!$A:$G,7,)*G37 -> 5061.9289 | I37: =VLOOKUP(E37, INDIRECT("'" & $A$1 & "'!A:O"), 14, FALSE) | J37: =vlookup(E37, Prices!$A:$G,7,)*I37 -> 0 | K37: =VLOOKUP(E37, INDIRECT("'" & $A$1 & "'!A:O"), 15, FALSE) | L37: =vlookup(E37, Prices!$A:$G,7,)*K37 -> 0 | N37: Bacon Warp | O37: Pcs | P37: {=VLOOKUP(N37, INDIRECT("'" & $A$1 & "'!A:O"), 13, FALSE)/ vlookup(N37,BACKEND2!$A$1:$F1000,5,)} -> 0 | Q37: =vlookup(N37, Prices!$A:$F,3,)*P37 -> 0 | S37: =vlookup(N37, Prices!$A:$G,7,)*R37 -> 0 | U37: =vlookup(N37, Prices!$A:$G,7,)*T37 -> 0
E38: Tomato paste | F38: Kg | G38: =VLOOKUP(E38, INDIRECT("'" & $A$1 & "'!A:O"), 13, FALSE) -> 0.4 | H38: =vlookup(E38, Prices!$A:$G,7,)*G38 -> 5000 | I38: =VLOOKUP(E38, INDIRECT("'" & $A$1 & "'!A:O"), 14, FALSE) | J38: =vlookup(E38, Prices!$A:$G,7,)*I38 -> 0 | K38: =VLOOKUP(E38, INDIRECT("'" & $A$1 & "'!A:O"), 15, FALSE) | L38: =vlookup(E38, Prices!$A:$G,7,)*K38 -> 0 | N38: Beef stragnoff | O38: Ptns | P38: {=VLOOKUP(N38, INDIRECT("'" & $A$1 & "'!A:O"), 13, FALSE)/ vlookup(N38,BACKEND2!$A$1:$F1000,5,)} -> 0 | Q38: =vlookup(N38, Prices!$A:$F,3,)*P38 -> 0 | S38: =vlookup(N38, Prices!$A:$G,7,)*R38 -> 0 | U38: =vlookup(N38, Prices!$A:$G,7,)*T38 -> 0
E39: Chips bags | F39: Pcs | G39: =VLOOKUP(E39, INDIRECT("'" & $A$1 & "'!A:O"), 13, FALSE) -> 60 | H39: =vlookup(E39, Prices!$A:$G,7,)*G39 -> 4200 | I39: =VLOOKUP(E39, INDIRECT("'" & $A$1 & "'!A:O"), 14, FALSE) | J39: =vlookup(E39, Prices!$A:$G,7,)*I39 -> 0 | K39: =VLOOKUP(E39, INDIRECT("'" & $A$1 & "'!A:O"), 15, FALSE) | L39: =vlookup(E39, Prices!$A:$G,7,)*K39 -> 0 | N39: Beef mini burger | O39: Ptns | P39: {=VLOOKUP(N39, INDIRECT("'" & $A$1 & "'!A:O"), 13, FALSE)/ vlookup(N39,BACKEND2!$A$1:$F1000,5,)} -> 0 | Q39: =vlookup(N39, Prices!$A:$F,3,)*P39 -> 0 | S39: =vlookup(N39, Prices!$A:$G,7,)*R39 -> 0 | U39: =vlookup(N39, Prices!$A:$G,7,)*T39 -> 0
E40: Bread Loaf | F40: kg | G40: =VLOOKUP(E40, INDIRECT("'" & $A$1 & "'!A:O"), 13, FALSE) -> 1 | H40: =vlookup(E40, Prices!$A:$G,7,)*G40 -> 3876 | I40: =VLOOKUP(E40, INDIRECT("'" & $A$1 & "'!A:O"), 14, FALSE) | J40: =vlookup(E40, Prices!$A:$G,7,)*I40 -> 0 | K40: =VLOOKUP(E40, INDIRECT("'" & $A$1 & "'!A:O"), 15, FALSE) | L40: =vlookup(E40, Prices!$A:$G,7,)*K40 -> 0
E41: Cheddar cheese | F41: Kg | G41: =VLOOKUP(E41, INDIRECT("'" & $A$1 & "'!A:O"), 13, FALSE) -> 0.168 | H41: =vlookup(E41, Prices!$A:$G,7,)*G41 -> 3864 | I41: =VLOOKUP(E41, INDIRECT("'" & $A$1 & "'!A:O"), 14, FALSE) | J41: =vlookup(E41, Prices!$A:$G,7,)*I41 -> 0 | K41: =VLOOKUP(E41, INDIRECT("'" & $A$1 & "'!A:O"), 15, FALSE) | L41: =vlookup(E41, Prices!$A:$G,7,)*K41 -> 0
E42: Cooking cream | F42: Liters | G42: =VLOOKUP(E42, INDIRECT("'" & $A$1 & "'!A:O"), 13, FALSE) -> 0.219 | H42: =vlookup(E42, Prices!$A:$G,7,)*G42 -> 3832.5 | J42: =vlookup(E42, Prices!$A:$G,7,)*I42 -> 0 | K42: =VLOOKUP(E42, INDIRECT("'" & $A$1 & "'!A:O"), 15, FALSE) | L42: =vlookup(E42, Prices!$A:$G,7,)*K42 -> 0
E43: Takeaway spoons | F43: Pcs | G43: =VLOOKUP(E43, INDIRECT("'" & $A$1 & "'!A:O"), 13, FALSE) -> 46 | H43: =vlookup(E43, Prices!$A:$G,7,)*G43 -> 3680 | I43: =VLOOKUP(E43, INDIRECT("'" & $A$1 & "'!A:O"), 14, FALSE) | J43: =vlookup(E43, Prices!$A:$G,7,)*I43 -> 0 | K43: =VLOOKUP(E43, INDIRECT("'" & $A$1 & "'!A:O"), 15, FALSE) | L43: =vlookup(E43, Prices!$A:$G,7,)*K43 -> 0
E44: Avocado | F44: Pcs | G44: =VLOOKUP(E44, INDIRECT("'" & $A$1 & "'!A:O"), 13, FALSE) -> 3.5 | H44: =vlookup(E44, Prices!$A:$G,7,)*G44 -> 3500 | I44: =VLOOKUP(E44, INDIRECT("'" & $A$1 & "'!A:O"), 14, FALSE) | J44: =vlookup(E44, Prices!$A:$G,7,)*I44 -> 0 | K44: =VLOOKUP(E44, INDIRECT("'" & $A$1 & "'!A:O"), 15, FALSE) | L44: =vlookup(E44, Prices!$A:$G,7,)*K44 -> 0
E45: Broccoli | F45: Pcs | G45: =VLOOKUP(E45, INDIRECT("'" & $A$1 & "'!A:O"), 13, FALSE) -> 1 | H45: =vlookup(E45, Prices!$A:$G,7,)*G45 -> 3500 | I45: =VLOOKUP(E45, INDIRECT("'" & $A$1 & "'!A:O"), 14, FALSE) | J45: =vlookup(E45, Prices!$A:$G,7,)*I45 -> 0 | K45: =VLOOKUP(E45, INDIRECT("'" & $A$1 & "'!A:O"), 15, FALSE) | L45: =vlookup(E45, Prices!$A:$G,7,)*K45 -> 0
E46: Carrots | F46: Kg | G46: =VLOOKUP(E46, INDIRECT("'" & $A$1 & "'!A:O"), 13, FALSE) -> 1.148 | H46: =vlookup(E46, Prices!$A:$G,7,)*G46 -> 3444 | I46: =VLOOKUP(E46, INDIRECT("'" & $A$1 & "'!A:O"), 14, FALSE) | J46: =vlookup(E46, Prices!$A:$G,7,)*I46 -> 0 | K46: =VLOOKUP(E46, INDIRECT("'" & $A$1 & "'!A:O"), 15, FALSE) | L46: =vlookup(E46, Prices!$A:$G,7,)*K46 -> 0
E47: Mustard | F47: Kg | G47: =VLOOKUP(E47, INDIRECT("'" & $A$1 & "'!A:O"), 13, FALSE) -> 0.081 | H47: =vlookup(E47, Prices!$A:$G,7,)*G47 -> 3264.4836 | I47: =VLOOKUP(E47, INDIRECT("'" & $A$1 & "'!A:O"), 14, FALSE) | J47: =vlookup(E47, Prices!$A:$G,7,)*I47 -> 0 | K47: =VLOOKUP(E47, INDIRECT("'" & $A$1 & "'!A:O"), 15, FALSE) | L47: =vlookup(E47, Prices!$A:$G,7,)*K47 -> 0
E48: Dark soy sauce | F48: Liters | G48: =VLOOKUP(E48, INDIRECT("'" & $A$1 & "'!A:O"), 13, FALSE) -> 0.197 | H48: =vlookup(E48, Prices!$A:$G,7,)*G48 -> 3152 | I48: =VLOOKUP(E48, INDIRECT("'" & $A$1 & "'!A:O"), 14, FALSE) | J48: =vlookup(E48, Prices!$A:$G,7,)*I48 -> 0 | K48: =VLOOKUP(E48, INDIRECT("'" & $A$1 & "'!A:O"), 15, FALSE) | L48: =vlookup(E48, Prices!$A:$G,7,)*K48 -> 0
E49: Pickles | F49: Kg | G49: =VLOOKUP(E49, INDIRECT("'" & $A$1 & "'!A:O"), 13, FALSE) -> 0.087 | H49: =vlookup(E49, Prices!$A:$G,7,)*G49 -> 3056.7568 | I49: =VLOOKUP(E49, INDIRECT("'" & $A$1 & "'!A:O"), 14, FALSE) | J49: =vlookup(E49, Prices!$A:$G,7,)*I49 -> 0 | K49: =VLOOKUP(E49, INDIRECT("'" & $A$1 & "'!A:O"), 15, FALSE) | L49: =vlookup(E49, Prices!$A:$G,7,)*K49 -> 0
E50: Sweet chilli sauce | F50: Liters | G50: =VLOOKUP(E50, INDIRECT("'" & $A$1 & "'!A:O"), 13, FALSE) -> 0.16 | H50: =vlookup(E50, Prices!$A:$G,7,)*G50 -> 2962.963 | I50: =VLOOKUP(E50, INDIRECT("'" & $A$1 & "'!A:O"), 14, FALSE) | J50: =vlookup(E50, Prices!$A:$G,7,)*I50 -> 0 | K50: =VLOOKUP(E50, INDIRECT("'" & $A$1 & "'!A:O"), 15, FALSE) | L50: =vlookup(E50, Prices!$A:$G,7,)*K50 -> 0
E51: Yeast 500g | F51: Kg | G51: =VLOOKUP(E51, INDIRECT("'" & $A$1 & "'!A:O"), 13, FALSE) -> 0.094 | H51: =vlookup(E51, Prices!$A:$G,7,)*G51 -> 2820 | I51: =VLOOKUP(E51, INDIRECT("'" & $A$1 & "'!A:O"), 14, FALSE) | J51: =vlookup(E51, Prices!$A:$G,7,)*I51 -> 0 | K51: =VLOOKUP(E51, INDIRECT("'" & $A$1 & "'!A:O"), 15, FALSE) | L51: =vlookup(E51, Prices!$A:$G,7,)*K51 -> 0
E52: Patio Bella pizza boxes | F52: Pcs | G52: =VLOOKUP(E52, INDIRECT("'" & $A$1 & "'!A:O"), 13, FALSE) -> 2 | H52: =vlookup(E52, Prices!$A:$G,7,)*G52 -> 2800 | I52: =VLOOKUP(E52, INDIRECT("'" & $A$1 & "'!A:O"), 14, FALSE) | J52: =vlookup(E52, Prices!$A:$G,7,)*I52 -> 0 | K52: =VLOOKUP(E52, INDIRECT("'" & $A$1 & "'!A:O"), 15, FALSE) | L52: =vlookup(E52, Prices!$A:$G,7,)*K52 -> 0
E53: Round big takeaway containers | F53: Pcs | G53: =VLOOKUP(E53, INDIRECT("'" & $A$1 & "'!A:O"), 13, FALSE) -> 18 | H53: =vlookup(E53, Prices!$A:$G,7,)*G53 -> 2736 | I53: =VLOOKUP(E53, INDIRECT("'" & $A$1 & "'!A:O"), 14, FALSE) | J53: =vlookup(E53, Prices!$A:$G,7,)*I53 -> 0 | K53: =VLOOKUP(E53, INDIRECT("'" & $A$1 & "'!A:O"), 15, FALSE) | L53: =vlookup(E53, Prices!$A:$G,7,)*K53 -> 0
E54: White cabbage | F54: Pcs | G54: =VLOOKUP(E54, INDIRECT("'" & $A$1 & "'!A:O"), 13, FALSE) -> 1 | H54: =vlookup(E54, Prices!$A:$G,7,)*G54 -> 2400 | I54: =VLOOKUP(E54, INDIRECT("'" & $A$1 & "'!A:O"), 14, FALSE) | J54: =vlookup(E54, Prices!$A:$G,7,)*I54 -> 0 | K54: =VLOOKUP(E54, INDIRECT("'" & $A$1 & "'!A:O"), 15, FALSE) | L54: =vlookup(E54, Prices!$A:$G,7,)*K54 -> 0
... E61: Balsamic Vinegar | F61: Kg | G61: =VLOOKUP(E61, INDIRECT("'" & $A$1 & "'!A:O"), 13, FALSE) -> 0.044 | H61: =vlookup(E61, Prices!$A:$G,7,)*G61 -> 1144 | I61: =VLOOKUP(E61, INDIRECT("'" & $A$1 & "'!A:O"), 14, FALSE) | J61: =vlookup(E61, Prices!$A:$G,7,)*I61 -> 0 | K61: =VLOOKUP(E61, INDIRECT("'" & $A$1 & "'!A:O"), 15, FALSE) | L61: =vlookup(E61, Prices!$A:$G,7,)*K61 -> 0
E62: Sauce cups | F62: Pcs | G62: =VLOOKUP(E62, INDIRECT("'" & $A$1 & "'!A:O"), 13, FALSE) -> 12 | H62: =vlookup(E62, Prices!$A:$G,7,)*G62 -> 1140 | L62: =vlookup(E62, Prices!$A:$G,7,)*K62 -> 0
E63: Soft lettuce | F63: Pcs | G63: =VLOOKUP(E63, INDIRECT("'" & $A$1 & "'!A:O"), 13, FALSE) -> 0.25 | H63: =vlookup(E63, Prices!$A:$G,7,)*G63 -> 1125 | I63: =VLOOKUP(E63, INDIRECT("'" & $A$1 & "'!A:O"), 14, FALSE) | J63: =vlookup(E63, Prices!$A:$G,7,)*I63 -> 0 | K63: =VLOOKUP(E63, INDIRECT("'" & $A$1 & "'!A:O"), 15, FALSE) | L63: =vlookup(E63, Prices!$A:$G,7,)*K63 -> 0
E64: Zesta Jam | F64: Kg | G64: =VLOOKUP(E64, INDIRECT("'" & $A$1 & "'!A:O"), 13, FALSE) -> 0.056 | H64: =vlookup(E64, Prices!$A:$G,7,)*G64 -> 1120 | I64: =VLOOKUP(E64, INDIRECT("'" & $A$1 & "'!A:O"), 14, FALSE) | J64: =vlookup(E64, Prices!$A:$G,7,)*I64 -> 0 | K64: =VLOOKUP(E64, INDIRECT("'" & $A$1 & "'!A:O"), 15, FALSE) | L64: =vlookup(E64, Prices!$A:$G,7,)*K64 -> 0
E65: Icing sugar | F65: Kg | G65: =VLOOKUP(E65, INDIRECT("'" & $A$1 & "'!A:O"), 13, FALSE) -> 0.123 | H65: =vlookup(E65, Prices!$A:$G,7,)*G65 -> 1107 | I65: =VLOOKUP(E65, INDIRECT("'" & $A$1 & "'!A:O"), 14, FALSE) | J65: =vlookup(E65, Prices!$A:$G,7,)*I65 -> 0 | K65: =VLOOKUP(E65, INDIRECT("'" & $A$1 & "'!A:O"), 15, FALSE) | L65: =vlookup(E65, Prices!$A:$G,7,)*K65 -> 0
E66: Oranges | F66: Kg | G66: =VLOOKUP(E66, INDIRECT("'" & $A$1 & "'!A:O"), 13, FALSE) -> 0.1 | H66: =vlookup(E66, Prices!$A:$G,7,)*G66 -> 850 | I66: =VLOOKUP(E66, INDIRECT("'" & $A$1 & "'!A:O"), 14, FALSE) | J66: =vlookup(E66, Prices!$A:$G,7,)*I66 -> 0 | K66: =VLOOKUP(E66, INDIRECT("'" & $A$1 & "'!A:O"), 15, FALSE) | L66: =vlookup(E66, Prices!$A:$G,7,)*K66 -> 0
E67: Strawberry | F67: Kg | G67: =VLOOKUP(E67, INDIRECT("'" & $A$1 & "'!A:O"), 13, FALSE) -> 0.077 | H67: =vlookup(E67, Prices!$A:$G,7,)*G67 -> 847 | I67: =VLOOKUP(E67, INDIRECT("'" & $A$1 & "'!A:O"), 14, FALSE) | J67: =vlookup(E67, Prices!$A:$G,7,)*I67 -> 0 | K67: =VLOOKUP(E67, INDIRECT("'" & $A$1 & "'!A:O"), 15, FALSE) | L67: =vlookup(E67, Prices!$A:$G,7,)*K67 -> 0
E68: Cucumber | F68: Kg | G68: =VLOOKUP(E68, INDIRECT("'" & $A$1 & "'!A:O"), 13, FALSE) -> 0.338 | H68: =vlookup(E68, Prices!$A:$G,7,)*G68 -> 845 | I68: =VLOOKUP(E68, INDIRECT("'" & $A$1 & "'!A:O"), 14, FALSE) | J68: =vlookup(E68, Prices!$A:$G,7,)*I68 -> 0 | K68: =VLOOKUP(E68, INDIRECT("'" & $A$1 & "'!A:O"), 15, FALSE) | L68: =vlookup(E68, Prices!$A:$G,7,)*K68 -> 0
E69: Baguette Bread | F69: Pcs | G69: =VLOOKUP(E69, INDIRECT("'" & $A$1 & "'!A:O"), 13, FALSE) -> 1 | H69: =vlookup(E69, Prices!$A:$G,7,)*G69 -> 781 | I69: =VLOOKUP(E69, INDIRECT("'" & $A$1 & "'!A:O"), 14, FALSE) | J69: =vlookup(E69, Prices!$A:$G,7,)*I69 -> 0 | K69: =VLOOKUP(E69, INDIRECT("'" & $A$1 & "'!A:O"), 15, FALSE) | L69: =vlookup(E69, Prices!$A:$G,7,)*K69 -> 0
E70: Soup Buns | F70: Pcs | G70: =VLOOKUP(E70, INDIRECT("'" & $A$1 & "'!A:O"), 13, FALSE) -> 8 | H70: =vlookup(E70, Prices!$A:$G,7,)*G70 -> 776 | I70: =VLOOKUP(E70, INDIRECT("'" & $A$1 & "'!A:O"), 14, FALSE) | J70: =vlookup(E70, Prices!$A:$G,7,)*I70 -> 0 | K70: =VLOOKUP(E70, INDIRECT("'" & $A$1 & "'!A:O"), 15, FALSE) | L70: =vlookup(E70, Prices!$A:$G,7,)*K70 -> 0
E71: Pasely | F71: Bundles | G71: =VLOOKUP(E71, INDIRECT("'" & $A$1 & "'!A:O"), 13, FALSE) -> 0.25 | H71: =vlookup(E71, Prices!$A:$G,7,)*G71 -> 750 | I71: =VLOOKUP(E71, INDIRECT("'" & $A$1 & "'!A:O"), 14, FALSE) | J71: =vlookup(E71, Prices!$A:$G,7,)*I71 -> 0 | K71: =VLOOKUP(E71, INDIRECT("'" & $A$1 & "'!A:O"), 15, FALSE) | L71: =vlookup(E71, Prices!$A:$G,7,)*K71 -> 0
E72: Coriander Powder | F72: Kg | G72: =VLOOKUP(E72, INDIRECT("'" & $A$1 & "'!A:O"), 13, FALSE) -> 0.018 | H72: =vlookup(E72, Prices!$A:$G,7,)*G72 -> 720 | I72: =VLOOKUP(E72, INDIRECT("'" & $A$1 & "'!A:O"), 14, FALSE) | J72: =vlookup(E72, Prices!$A:$G,7,)*I72 -> 0 | K72: =VLOOKUP(E72, INDIRECT("'" & $A$1 & "'!A:O"), 15, FALSE) | L72: =vlookup(E72, Prices!$A:$G,7,)*K72 -> 0
E73: Temeric Powder | F73: Kg | G73: =VLOOKUP(E73, INDIRECT("'" & $A$1 & "'!A:O"), 13, FALSE) -> 0.016 | H73: =vlookup(E73, Prices!$A:$G,7,)*G73 -> 640 | I73: =VLOOKUP(E73, INDIRECT("'" & $A$1 & "'!A:O"), 14, FALSE) | J73: =vlookup(E73, Prices!$A:$G,7,)*I73 -> 0 | K73: =VLOOKUP(E73, INDIRECT("'" & $A$1 & "'!A:O"), 15, FALSE) | L73: =vlookup(E73, Prices!$A:$G,7,)*K73 -> 0
E74: Yellow Banana | F74: Pcs | G74: =VLOOKUP(E74, INDIRECT("'" & $A$1 & "'!A:O"), 13, FALSE) -> 1 | H74: =vlookup(E74, Prices!$A:$G,7,)*G74 -> 600 | I74: =VLOOKUP(E74, INDIRECT("'" & $A$1 & "'!A:O"), 14, FALSE) | J74: =vlookup(E74, Prices!$A:$G,7,)*I74 -> 0 | K74: =VLOOKUP(E74, INDIRECT("'" & $A$1 & "'!A:O"), 15, FALSE) | L74: =vlookup(E74, Prices!$A:$G,7,)*K74 -> 0
... E108: Bay leaves | F108: Bundles | G108: =VLOOKUP(E108, INDIRECT("'" & $A$1 & "'!A:O"), 13, FALSE) -> 0 | H108: =vlookup(E108, Prices!$A:$G,7,)*G108 -> 0 | I108: =VLOOKUP(E108, INDIRECT("'" & $A$1 & "'!A:O"), 14, FALSE) | J108: =vlookup(E108, Prices!$A:$G,7,)*I108 -> 0 | K108: =VLOOKUP(E108, INDIRECT("'" & $A$1 & "'!A:O"), 15, FALSE) | L108: =vlookup(E108, Prices!$A:$G,7,)*K108 -> 0
E109: White Pepper | F109: Kg | G109: =VLOOKUP(E109, INDIRECT("'" & $A$1 & "'!A:O"), 13, FALSE) -> 0 | H109: =vlookup(E109, Prices!$A:$G,7,)*G109 -> 0 | J109: =vlookup(E109, Prices!$A:$G,7,)*I109 -> 0 | K109: =VLOOKUP(E109, INDIRECT("'" & $A$1 & "'!A:O"), 15, FALSE) | L109: =vlookup(E109, Prices!$A:$G,7,)*K109 -> 0
E110: Black pepper powder | F110: Kg | G110: =VLOOKUP(E110, INDIRECT("'" & $A$1 & "'!A:O"), 13, FALSE) -> 0 | H110: =vlookup(E110, Prices!$A:$G,7,)*G110 -> 0 | I110: =VLOOKUP(E110, INDIRECT("'" & $A$1 & "'!A:O"), 14, FALSE) | J110: =vlookup(E110, Prices!$A:$G,7,)*I110 -> 0 | K110: =VLOOKUP(E110, INDIRECT("'" & $A$1 & "'!A:O"), 15, FALSE) | L110: =vlookup(E110, Prices!$A:$G,7,)*K110 -> 0
E111: Pineapple | F111: pcs | G111: =VLOOKUP(E111, INDIRECT("'" & $A$1 & "'!A:O"), 13, FALSE) -> 0 | H111: =vlookup(E111, Prices!$A:$G,7,)*G111 -> 0 | I111: =VLOOKUP(E111, INDIRECT("'" & $A$1 & "'!A:O"), 14, FALSE) | J111: =vlookup(E111, Prices!$A:$G,7,)*I111 -> 0 | K111: =VLOOKUP(E111, INDIRECT("'" & $A$1 & "'!A:O"), 15, FALSE) | L111: =vlookup(E111, Prices!$A:$G,7,)*K111 -> 0
E112: Muesli Frunt & Nut | F112: kg | G112: =VLOOKUP(E112, INDIRECT("'" & $A$1 & "'!A:O"), 13, FALSE) -> 0 | H112: =vlookup(E112, Prices!$A:$G,7,)*G112 -> 0 | I112: =VLOOKUP(E112, INDIRECT("'" & $A$1 & "'!A:O"), 14, FALSE) | J112: =vlookup(E112, Prices!$A:$G,7,)*I112 -> 0 | K112: =VLOOKUP(E112, INDIRECT("'" & $A$1 & "'!A:O"), 15, FALSE) | L112: =vlookup(E112, Prices!$A:$G,7,)*K112 -> 0
E113: Lemon | F113: Kg | G113: =VLOOKUP(E113, INDIRECT("'" & $A$1 & "'!A:O"), 13, FALSE) -> 0 | H113: =vlookup(E113, Prices!$A:$G,7,)*G113 -> 0 | I113: =VLOOKUP(E113, INDIRECT("'" & $A$1 & "'!A:O"), 14, FALSE) | J113: =vlookup(E113, Prices!$A:$G,7,)*I113 -> 0 | K113: =VLOOKUP(E113, INDIRECT("'" & $A$1 & "'!A:O"), 15, FALSE) | L113: =vlookup(E113, Prices!$A:$G,7,)*K113 -> 0
E114: Bok choy | F114: Kg | G114: =VLOOKUP(E114, INDIRECT("'" & $A$1 & "'!A:O"), 13, FALSE) -> 0 | H114: =vlookup(E114, Prices!$A:$G,7,)*G114 -> 0 | I114: =VLOOKUP(E114, INDIRECT("'" & $A$1 & "'!A:O"), 14, FALSE) | J114: =vlookup(E114, Prices!$A:$G,7,)*I114 -> 0 | K114: =VLOOKUP(E114, INDIRECT("'" & $A$1 & "'!A:O"), 15, FALSE) | L114: =vlookup(E114, Prices!$A:$G,7,)*K114 -> 0
E115: Celery leaves | F115: Bundles | G115: =VLOOKUP(E115, INDIRECT("'" & $A$1 & "'!A:O"), 13, FALSE) -> 0 | H115: =vlookup(E115, Prices!$A:$G,7,)*G115 -> 0 | I115: =VLOOKUP(E115, INDIRECT("'" & $A$1 & "'!A:O"), 14, FALSE) | J115: =vlookup(E115, Prices!$A:$G,7,)*I115 -> 0 | K115: =VLOOKUP(E115, INDIRECT("'" & $A$1 & "'!A:O"), 15, FALSE) | L115: =vlookup(E115, Prices!$A:$G,7,)*K115 -> 0
E116: Coriander | F116: Bundles | G116: =VLOOKUP(E116, INDIRECT("'" & $A$1 & "'!A:O"), 13, FALSE) -> 0 | H116: =vlookup(E116, Prices!$A:$G,7,)*G116 -> 0 | I116: =VLOOKUP(E116, INDIRECT("'" & $A$1 & "'!A:O"), 14, FALSE) | J116: =vlookup(E116, Prices!$A:$G,7,)*I116 -> 0 | K116: =VLOOKUP(E116, INDIRECT("'" & $A$1 & "'!A:O"), 15, FALSE) | L116: =vlookup(E116, Prices!$A:$G,7,)*K116 -> 0
E117: Sweet corn | F117: Kg | G117: =VLOOKUP(E117, INDIRECT("'" & $A$1 & "'!A:O"), 13, FALSE) -> 0 | H117: =vlookup(E117, Prices!$A:$G,7,)*G117 -> 0 | I117: =VLOOKUP(E117, INDIRECT("'" & $A$1 & "'!A:O"), 14, FALSE) | J117: =vlookup(E117, Prices!$A:$G,7,)*I117 -> 0 | K117: =VLOOKUP(E117, INDIRECT("'" & $A$1 & "'!A:O"), 15, FALSE) | L117: =vlookup(E117, Prices!$A:$G,7,)*K117 -> 0
E118: Foccacia Bread | F118: Pcs | G118: =VLOOKUP(E118, INDIRECT("'" & $A$1 & "'!A:O"), 13, FALSE) -> 0 | H118: =vlookup(E118, Prices!$A:$G,7,)*G118 -> 0 | I118: =VLOOKUP(E118, INDIRECT("'" & $A$1 & "'!A:O"), 14, FALSE) | J118: =vlookup(E118, Prices!$A:$G,7,)*I118 -> 0 | K118: =VLOOKUP(E118, INDIRECT("'" & $A$1 & "'!A:O"), 15, FALSE) | L118: =vlookup(E118, Prices!$A:$G,7,)*K118 -> 0
E119: Origano | F119: Kg | G119: =VLOOKUP(E119, INDIRECT("'" & $A$1 & "'!A:O"), 13, FALSE) -> 0 | H119: =vlookup(E119, Prices!$A:$G,7,)*G119 -> 0 | I119: =VLOOKUP(E119, INDIRECT("'" & $A$1 & "'!A:O"), 14, FALSE) | J119: =vlookup(E119, Prices!$A:$G,7,)*I119 -> 0 | K119: =VLOOKUP(E119, INDIRECT("'" & $A$1 & "'!A:O"), 15, FALSE) | L119: =vlookup(E119, Prices!$A:$G,7,)*K119 -> 0
E120: Plain yoghurt | F120: Kg | G120: =VLOOKUP(E120, INDIRECT("'" & $A$1 & "'!A:O"), 13, FALSE) -> 0 | H120: =vlookup(E120, Prices!$A:$G,7,)*G120 -> 0 | I120: =VLOOKUP(E120, INDIRECT("'" & $A$1 & "'!A:O"), 14, FALSE) | J120: =vlookup(E120, Prices!$A:$G,7,)*I120 -> 0 | K120: =VLOOKUP(E120, INDIRECT("'" & $A$1 & "'!A:O"), 15, FALSE) | L120: =vlookup(E120, Prices!$A:$G,7,)*K120 -> 0
E121: Simba mbili | F121: Kg | G121: =VLOOKUP(E121, INDIRECT("'" & $A$1 & "'!A:O"), 13, FALSE) -> 0 | H121: =vlookup(E121, Prices!$A:$G,7,)*G121 -> 0 | I121: =VLOOKUP(E121, INDIRECT("'" & $A$1 & "'!A:O"), 14, FALSE) | J121: =vlookup(E121, Prices!$A:$G,7,)*I121 -> 0 | K121: =VLOOKUP(E121, INDIRECT("'" & $A$1 & "'!A:O"), 15, FALSE) | L121: =vlookup(E121, Prices!$A:$G,7,)*K121 -> 0
... E152: Caramel syrup | F152: Ltr | G152: =VLOOKUP(E152, INDIRECT("'" & $A$1 & "'!A:O"), 13, FALSE) -> 0 | H152: =vlookup(E152, Prices!$A:$G,7,)*G152 -> 0 | I152: =VLOOKUP(E152, INDIRECT("'" & $A$1 & "'!A:O"), 14, FALSE) | J152: =vlookup(E152, Prices!$A:$G,7,)*I152 -> 0 | K152: =VLOOKUP(E152, INDIRECT("'" & $A$1 & "'!A:O"), 15, FALSE) | L152: =vlookup(E152, Prices!$A:$G,7,)*K152 -> 0
E153: Dry Foods | G153: =VLOOKUP(E153, INDIRECT("'" & $A$1 & "'!A:O"), 13, FALSE) -> 0 | H153: =vlookup(E153, Prices!$A:$G,7,)*G153 -> 0 | I153: =VLOOKUP(E153, INDIRECT("'" & $A$1 & "'!A:O"), 14, FALSE) | J153: =vlookup(E153, Prices!$A:$G,7,)*I153 -> 0 | K153: =VLOOKUP(E153, INDIRECT("'" & $A$1 & "'!A:O"), 15, FALSE) | L153: =vlookup(E153, Prices!$A:$G,7,)*K153 -> 0
E154: Coconut Oil | F154: Kg | G154: =VLOOKUP(E154, INDIRECT("'" & $A$1 & "'!A:O"), 13, FALSE) -> 0 | H154: =vlookup(E154, Prices!$A:$G,7,)*G154 -> 0 | I154: =VLOOKUP(E154, INDIRECT("'" & $A$1 & "'!A:O"), 14, FALSE) | J154: =vlookup(E154, Prices!$A:$G,7,)*I154 -> 0 | K154: =VLOOKUP(E154, INDIRECT("'" & $A$1 & "'!A:O"), 15, FALSE) | L154: =vlookup(E154, Prices!$A:$G,7,)*K154 -> 0
E155: Cocoa powder | F155: Kg | G155: =VLOOKUP(E155, INDIRECT("'" & $A$1 & "'!A:O"), 13, FALSE) -> 0 | H155: =vlookup(E155, Prices!$A:$G,7,)*G155 -> 0 | I155: =VLOOKUP(E155, INDIRECT("'" & $A$1 & "'!A:O"), 14, FALSE) | J155: =vlookup(E155, Prices!$A:$G,7,)*I155 -> 0 | K155: =VLOOKUP(E155, INDIRECT("'" & $A$1 & "'!A:O"), 15, FALSE) | L155: =vlookup(E155, Prices!$A:$G,7,)*K155 -> 0
E156: Raisins | F156: Kg | G156: =VLOOKUP(E156, INDIRECT("'" & $A$1 & "'!A:O"), 13, FALSE) -> 0 | H156: =vlookup(E156, Prices!$A:$G,7,)*G156 -> 0 | I156: =VLOOKUP(E156, INDIRECT("'" & $A$1 & "'!A:O"), 14, FALSE) | J156: =vlookup(E156, Prices!$A:$G,7,)*I156 -> 0 | K156: =VLOOKUP(E156, INDIRECT("'" & $A$1 & "'!A:O"), 15, FALSE) | L156: =vlookup(E156, Prices!$A:$G,7,)*K156 -> 0
E157: Ginger Powder | F157: Kg | G157: =VLOOKUP(E157, INDIRECT("'" & $A$1 & "'!A:O"), 13, FALSE) -> 0 | H157: =vlookup(E157, Prices!$A:$G,7,)*G157 -> 0 | I157: =VLOOKUP(E157, INDIRECT("'" & $A$1 & "'!A:O"), 14, FALSE) | J157: =vlookup(E157, Prices!$A:$G,7,)*I157 -> 0 | K157: =VLOOKUP(E157, INDIRECT("'" & $A$1 & "'!A:O"), 15, FALSE) | L157: =vlookup(E157, Prices!$A:$G,7,)*K157 -> 0
E158: Ellebi Rose Powder | F158: Kg | G158: =VLOOKUP(E158, INDIRECT("'" & $A$1 & "'!A:O"), 13, FALSE) -> 0 | H158: =vlookup(E158, Prices!$A:$G,7,)*G158 -> 0 | I158: =VLOOKUP(E158, INDIRECT("'" & $A$1 & "'!A:O"), 14, FALSE) | J158: =vlookup(E158, Prices!$A:$G,7,)*I158 -> 0 | K158: =VLOOKUP(E158, INDIRECT("'" & $A$1 & "'!A:O"), 15, FALSE) | L158: =vlookup(E158, Prices!$A:$G,7,)*K158 -> 0
E159: Coriander Seeds | F159: Kg | G159: =VLOOKUP(E159, INDIRECT("'" & $A$1 & "'!A:O"), 13, FALSE) -> 0 | H159: =vlookup(E159, Prices!$A:$G,7,)*G159 -> 0 | I159: =VLOOKUP(E159, INDIRECT("'" & $A$1 & "'!A:O"), 14, FALSE) | J159: =vlookup(E159, Prices!$A:$G,7,)*I159 -> 0 | K159: =VLOOKUP(E159, INDIRECT("'" & $A$1 & "'!A:O"), 15, FALSE) | L159: =vlookup(E159, Prices!$A:$G,7,)*K159 -> 0
E160: Meat Tenderizer 100g | F160: Kg | G160: =VLOOKUP(E160, INDIRECT("'" & $A$1 & "'!A:O"), 13, FALSE) -> 0 | H160: =vlookup(E160, Prices!$A:$G,7,)*G160 -> 0 | I160: =VLOOKUP(E160, INDIRECT("'" & $A$1 & "'!A:O"), 14, FALSE) | J160: =vlookup(E160, Prices!$A:$G,7,)*I160 -> 0 | K160: =VLOOKUP(E160, INDIRECT("'" & $A$1 & "'!A:O"), 15, FALSE) | L160: =vlookup(E160, Prices!$A:$G,7,)*K160 -> 0
E161: Sweeteners | G161: =VLOOKUP(E161, INDIRECT("'" & $A$1 & "'!A:O"), 13, FALSE) -> 0 | H161: =vlookup(E161, Prices!$A:$G,7,)*G161 -> 0 | I161: =VLOOKUP(E161, INDIRECT("'" & $A$1 & "'!A:O"), 14, FALSE) | J161: =vlookup(E161, Prices!$A:$G,7,)*I161 -> 0 | K161: =VLOOKUP(E161, INDIRECT("'" & $A$1 & "'!A:O"), 15, FALSE) | L161: =vlookup(E161, Prices!$A:$G,7,)*K161 -> 0
E162: Bbq sauce | F162: Liters | G162: =VLOOKUP(E162, INDIRECT("'" & $A$1 & "'!A:O"), 13, FALSE) -> 0 | H162: =vlookup(E162, Prices!$A:$G,7,)*G162 -> 0 | I162: =VLOOKUP(E162, INDIRECT("'" & $A$1 & "'!A:O"), 14, FALSE) | J162: =vlookup(E162, Prices!$A:$G,7,)*I162 -> 0 | K162: =VLOOKUP(E162, INDIRECT("'" & $A$1 & "'!A:O"), 15, FALSE) | L162: =vlookup(E162, Prices!$A:$G,7,)*K162 -> 0
E163: Canned goods | G163: =VLOOKUP(E163, INDIRECT("'" & $A$1 & "'!A:O"), 13, FALSE) -> 0 | H163: =vlookup(E163, Prices!$A:$G,7,)*G163 -> 0 | I163: =VLOOKUP(E163, INDIRECT("'" & $A$1 & "'!A:O"), 14, FALSE) | J163: =vlookup(E163, Prices!$A:$G,7,)*I163 -> 0 | K163: =VLOOKUP(E163, INDIRECT("'" & $A$1 & "'!A:O"), 15, FALSE) | L163: =vlookup(E163, Prices!$A:$G,7,)*K163 -> 0
E164: Peanut butter | F164: Kg | G164: =VLOOKUP(E164, INDIRECT("'" & $A$1 & "'!A:O"), 13, FALSE) -> 0 | H164: =vlookup(E164, Prices!$A:$G,7,)*G164 -> 0 | I164: =VLOOKUP(E164, INDIRECT("'" & $A$1 & "'!A:O"), 14, FALSE) | J164: =vlookup(E164, Prices!$A:$G,7,)*I164 -> 0 | K164: =VLOOKUP(E164, INDIRECT("'" & $A$1 & "'!A:O"), 15, FALSE) | L164: =vlookup(E164, Prices!$A:$G,7,)*K164 -> 0
E165: Dates | F165: Kg | G165: =VLOOKUP(E165, INDIRECT("'" & $A$1 & "'!A:O"), 13, FALSE) -> 0 | H165: =vlookup(E165, Prices!$A:$G,7,)*G165 -> 0 | I165: =VLOOKUP(E165, INDIRECT("'" & $A$1 & "'!A:O"), 14, FALSE) | J165: =vlookup(E165, Prices!$A:$G,7,)*I165 -> 0 | K165: =VLOOKUP(E165, INDIRECT("'" & $A$1 & "'!A:O"), 15, FALSE) | L165: =vlookup(E165, Prices!$A:$G,7,)*K165 -> 0
E166: Red Cherries | F166: Kg | G166: =VLOOKUP(E166, INDIRECT("'" & $A$1 & "'!A:O"), 13, FALSE) -> 0 | H166: =vlookup(E166, Prices!$A:$G,7,)*G166 -> 0 | I166: =VLOOKUP(E166, INDIRECT("'" & $A$1 & "'!A:O"), 14, FALSE) | J166: =vlookup(E166, Prices!$A:$G,7,)*I166 -> 0 | K166: =VLOOKUP(E166, INDIRECT("'" & $A$1 & "'!A:O"), 15, FALSE) | L166: =vlookup(E166, Prices!$A:$G,7,)*K166 -> 0
E167: Gren Cherries | F167: Kg | G167: =VLOOKUP(E167, INDIRECT("'" & $A$1 & "'!A:O"), 13, FALSE) -> 0 | H167: =vlookup(E167, Prices!$A:$G,7,)*G167 -> 0 | I167: =VLOOKUP(E167, INDIRECT("'" & $A$1 & "'!A:O"), 14, FALSE) | J167: =vlookup(E167, Prices!$A:$G,7,)*I167 -> 0 | K167: =VLOOKUP(E167, INDIRECT("'" & $A$1 & "'!A:O"), 15, FALSE) | L167: =vlookup(E167, Prices!$A:$G,7,)*K167 -> 0
E168: Dairy | G168: =VLOOKUP(E168, INDIRECT("'" & $A$1 & "'!A:O"), 13, FALSE) -> 0 | H168: =vlookup(E168, Prices!$A:$G,7,)*G168 -> 0 | I168: =VLOOKUP(E168, INDIRECT("'" & $A$1 & "'!A:O"), 14, FALSE) | J168: =vlookup(E168, Prices!$A:$G,7,)*I168 -> 0 | K168: =VLOOKUP(E168, INDIRECT("'" & $A$1 & "'!A:O"), 15, FALSE)
E169: Lato ghee | F169: kg | G169: =VLOOKUP(E169, INDIRECT("'" & $A$1 & "'!A:O"), 13, FALSE) -> 0 | H169: =vlookup(E169, Prices!$A:$G,7,)*G169 -> 0 | I169: =VLOOKUP(E169, INDIRECT("'" & $A$1 & "'!A:O"), 14, FALSE) | J169: =vlookup(E169, Prices!$A:$G,7,)*I169 -> 0 | K169: =VLOOKUP(E169, INDIRECT("'" & $A$1 & "'!A:O"), 15, FALSE) | L169: =vlookup(E169, Prices!$A:$G,7,)*K169 -> 0
...

Sheet Temp1
B2: WHOLE | F2: REMAINDER | L2: ACCOUNTABILITY
A3: Type | B3: U.O.M | C3: Opening | D3: Added | E3: Closing | F3: U.O.M | G3: Added | H3: Opening | I3: Units | J3: Closing | K3: Units | L3: U.O.M | M3: Used | N3: Transfer | O3: Damage
A4: Portioned Items: Meats & Others
A5: Carribean jerk | B5: Ptns | F5: Pcs | L5: Pcs | M5: =IF(AND(H5<>"", J5<>""), H5-J5, IF(H5<>"", H5-I5*VLOOKUP(A5, BACKEND2!$A:$G,6,FALSE), IF(J5<>"", -J5+K5*VLOOKUP(A5, BACKEND2!$A:$G,6,FALSE),0)))+ (C5+D5-E5)*VLOOKUP(A5, BACKEND2!$A:$G,5,FALSE)+G5 -> 0
A6: Chicken breast | B6: Ptns | F6: Pcs | L6: Pcs | M6: =IF(AND(H6<>"", J6<>""), H6-J6, IF(H6<>"", H6-I6*VLOOKUP(A6, BACKEND2!$A:$G,6,FALSE), IF(J6<>"", -J6+K6*VLOOKUP(A6, BACKEND2!$A:$G,6,FALSE),0)))+ (C6+D6-E6)*VLOOKUP(A6, BACKEND2!$A:$G,5,FALSE)+G6 -> 0
A7: Chicken wings | B7: Ptns | F7: Pcs | L7: Pcs | M7: =IF(AND(H7<>"", J7<>""), H7-J7, IF(H7<>"", H7-I7*VLOOKUP(A7, BACKEND2!$A:$G,6,FALSE), IF(J7<>"", -J7+K7*VLOOKUP(A7, BACKEND2!$A:$G,6,FALSE),0)))+ (C7+D7-E7)*VLOOKUP(A7, BACKEND2!$A:$G,5,FALSE)+G7 -> 0
A8: Chicken burger | B8: Ptns | F8: Ptns | L8: Ptns | M8: =IF(AND(H8<>"", J8<>""), H8-J8, IF(H8<>"", H8-I8*VLOOKUP(A8, BACKEND2!$A:$G,6,FALSE), IF(J8<>"", -J8+K8*VLOOKUP(A8, BACKEND2!$A:$G,6,FALSE),0)))+ (C8+D8-E8)*VLOOKUP(A8, BACKEND2!$A:$G,5,FALSE)+G8 -> 0
A9: Min Chicken burger | B9: Ptns | F9: Pcs | L9: Pcs | M9: =IF(AND(H9<>"", J9<>""), H9-J9, IF(H9<>"", H9-I9*VLOOKUP(A9, BACKEND2!$A:$G,6,FALSE), IF(J9<>"", -J9+K9*VLOOKUP(A9, BACKEND2!$A:$G,6,FALSE),0)))+ (C9+D9-E9)*VLOOKUP(A9, BACKEND2!$A:$G,5,FALSE)+G9 -> 0
A10: Chicken lollipos | B10: Ptns | F10: Pcs | L10: Pcs | M10: =IF(AND(H10<>"", J10<>""), H10-J10, IF(H10<>"", H10-I10*VLOOKUP(A10, BACKEND2!$A:$G,6,FALSE), IF(J10<>"", -J10+K10*VLOOKUP(A10, BACKEND2!$A:$G,6,FALSE),0)))+ (C10+D10-E10)*VLOOKUP(A10, BACKEND2!$A:$G,5,FALSE)+G10 -> 0
A11: Chicken pizza | B11: Ptns | F11: Ptns | L11: Ptns | M11: =IF(AND(H11<>"", J11<>""), H11-J11, IF(H11<>"", H11-I11*VLOOKUP(A11, BACKEND2!$A:$G,6,FALSE), IF(J11<>"", -J11+K11*VLOOKUP(A11, BACKEND2!$A:$G,6,FALSE),0)))+ (C11+D11-E11)*VLOOKUP(A11, BACKEND2!$A:$G,5,FALSE)+G11 -> 0
A12: Chicken Tenders | B12: Ptns | F12: Ptns | L12: Ptns | M12: =IF(AND(H12<>"", J12<>""), H12-J12, IF(H12<>"", H12-I12*VLOOKUP(A12, BACKEND2!$A:$G,6,FALSE), IF(J12<>"", -J12+K12*VLOOKUP(A12, BACKEND2!$A:$G,6,FALSE),0)))+ (C12+D12-E12)*VLOOKUP(A12, BACKEND2!$A:$G,5,FALSE)+G12 -> 0
A13: Chicken skewers | B13: Ptns | F13: Pcs | L13: Pcs | M13: =IF(AND(H13<>"", J13<>""), H13-J13, IF(H13<>"", H13-I13*VLOOKUP(A13, BACKEND2!$A:$G,6,FALSE), IF(J13<>"", -J13+K13*VLOOKUP(A13, BACKEND2!$A:$G,6,FALSE),0)))+ (C13+D13-E13)*VLOOKUP(A13, BACKEND2!$A:$G,5,FALSE)+G13 -> 0
A14: Chicken stroganoff | B14: Ptns | F14: Ptns | L14: Ptns | M14: =IF(AND(H14<>"", J14<>""), H14-J14, IF(H14<>"", H14-I14*VLOOKUP(A14, BACKEND2!$A:$G,6,FALSE), IF(J14<>"", -J14+K14*VLOOKUP(A14, BACKEND2!$A:$G,6,FALSE),0)))+ (C14+D14-E14)*VLOOKUP(A14, BACKEND2!$A:$G,5,FALSE)+G14 -> 0
A15: Chicken spring rolls | B15: Ptns | F15: Pcs | L15: Pcs | M15: =IF(AND(H15<>"", J15<>""), H15-J15, IF(H15<>"", H15-I15*VLOOKUP(A15, BACKEND2!$A:$G,6,FALSE), IF(J15<>"", -J15+K15*VLOOKUP(A15, BACKEND2!$A:$G,6,FALSE),0)))+ (C15+D15-E15)*VLOOKUP(A15, BACKEND2!$A:$G,5,FALSE)+G15 -> 0
A16: Chicken Samosas | B16: Ptns | F16: Pcs | L16: Pcs | M16: =IF(AND(H16<>"", J16<>""), H16-J16, IF(H16<>"", H16-I16*VLOOKUP(A16, BACKEND2!$A:$G,6,FALSE), IF(J16<>"", -J16+K16*VLOOKUP(A16, BACKEND2!$A:$G,6,FALSE),0)))+ (C16+D16-E16)*VLOOKUP(A16, BACKEND2!$A:$G,5,FALSE)+G16 -> 0
... A41: Beef Minced Meat | B41: Ptns | F41: Pcs | L41: Pcs | M41: =IF(AND(H41<>"", J41<>""), H41-J41, IF(H41<>"", H41-I41*VLOOKUP(A41, BACKEND2!$A:$G,6,FALSE), IF(J41<>"", -J41+K41*VLOOKUP(A41, BACKEND2!$A:$G,6,FALSE),0)))+ (C41+D41-E41)*VLOOKUP(A41, BACKEND2!$A:$G,5,FALSE)+G41 -> 0
A42: Other Kitchen & Food Supplies
A43: Condiments
A44: Bread Loaf | B44: Loaf | F44: kg | L44: kg | M44: =IF(AND(H44<>"", J44<>""), H44-J44, IF(H44<>"", H44-I44*VLOOKUP(A44, BACKEND1!$A:$G,6,FALSE), IF(J44<>"", -J44+K44*VLOOKUP(A44, BACKEND1!$A:$G,6,FALSE),0)))+ (C44+D44-E44)*VLOOKUP(A44, BACKEND1!$A:$G,5,FALSE)+G44 -> 0
A45: Burger Buns | B45: Pcs | F45: Pcs | L45: Pcs | M45: =IF(AND(H45<>"", J45<>""), H45-J45, IF(H45<>"", H45-I45*VLOOKUP(A45, BACKEND1!$A:$G,6,FALSE), IF(J45<>"", -J45+K45*VLOOKUP(A45, BACKEND1!$A:$G,6,FALSE),0)))+ (C45+D45-E45)*VLOOKUP(A45, BACKEND1!$A:$G,5,FALSE)+G45 -> 0
A46: Slider Buns | B46: Pcs | F46: Pcs | L46: Pcs | M46: =IF(AND(H46<>"", J46<>""), H46-J46, IF(H46<>"", H46-I46*VLOOKUP(A46, BACKEND1!$A:$G,6,FALSE), IF(J46<>"", -J46+K46*VLOOKUP(A46, BACKEND1!$A:$G,6,FALSE),0)))+ (C46+D46-E46)*VLOOKUP(A46, BACKEND1!$A:$G,5,FALSE)+G46 -> 0
A47: Soup Buns | B47: Pcs | F47: Pcs | L47: Pcs | M47: =IF(AND(H47<>"", J47<>""), H47-J47, IF(H47<>"", H47-I47*VLOOKUP(A47, BACKEND1!$A:$G,6,FALSE), IF(J47<>"", -J47+K47*VLOOKUP(A47, BACKEND1!$A:$G,6,FALSE),0)))+ (C47+D47-E47)*VLOOKUP(A47, BACKEND1!$A:$G,5,FALSE)+G47 -> 0
A48: Baguette Bread | B48: Pcs | F48: Pcs | L48: Pcs | M48: =IF(AND(H48<>"", J48<>""), H48-J48, IF(H48<>"", H48-I48*VLOOKUP(A48, BACKEND1!$A:$G,6,FALSE), IF(J48<>"", -J48+K48*VLOOKUP(A48, BACKEND1!$A:$G,6,FALSE),0)))+ (C48+D48-E48)*VLOOKUP(A48, BACKEND1!$A:$G,5,FALSE)+G48 -> 0
A49: Foccacia Bread | B49: Pcs | F49: Pcs | L49: Pcs | M49: =IF(AND(H49<>"", J49<>""), H49-J49, IF(H49<>"", H49-I49*VLOOKUP(A49, BACKEND1!$A:$G,6,FALSE), IF(J49<>"", -J49+K49*VLOOKUP(A49, BACKEND1!$A:$G,6,FALSE),0)))+ (C49+D49-E49)*VLOOKUP(A49, BACKEND1!$A:$G,5,FALSE)+G49 -> 0
A50: White vinegar | B50: Bottles | F50: Liters | L50: Liters | M50: =IF(AND(H50<>"", J50<>""), H50-J50, IF(H50<>"", H50-I50*VLOOKUP(A50, BACKEND1!$A:$G,6,FALSE), IF(J50<>"", -J50+K50*VLOOKUP(A50, BACKEND1!$A:$G,6,FALSE),0)))+ (C50+D50-E50)*VLOOKUP(A50, BACKEND1!$A:$G,5,FALSE)+G50 -> 0
A51: Heinz ketchup bottles | B51: Bottles | F51: Bottles | L51: Bottles | M51: =IF(AND(H51<>"", J51<>""), H51-J51, IF(H51<>"", H51-I51*VLOOKUP(A51, BACKEND1!$A:$G,6,FALSE), IF(J51<>"", -J51+K51*VLOOKUP(A51, BACKEND1!$A:$G,6,FALSE),0)))+ (C51+D51-E51)*VLOOKUP(A51, BACKEND1!$A:$G,5,FALSE)+G51 -> 0
A52: Apple cider vinegar | B52: Pcs | F52: kg | L52: kg | M52: =IF(AND(H52<>"", J52<>""), H52-J52, IF(H52<>"", H52-I52*VLOOKUP(A52, BACKEND1!$A:$G,6,FALSE), IF(J52<>"", -J52+K52*VLOOKUP(A52, BACKEND1!$A:$G,6,FALSE),0)))+ (C52+D52-E52)*VLOOKUP(A52, BACKEND1!$A:$G,5,FALSE)+G52 -> 0
A53: Balsamic Vinegar | B53: Bottles | F53: Kg | L53: Kg | M53: =IF(AND(H53<>"", J53<>""), H53-J53, IF(H53<>"", H53-I53*VLOOKUP(A53, BACKEND1!$A:$G,6,FALSE), IF(J53<>"", -J53+K53*VLOOKUP(A53, BACKEND1!$A:$G,6,FALSE),0)))+ (C53+D53-E53)*VLOOKUP(A53, BACKEND1!$A:$G,5,FALSE)+G53 -> 0
A54: Tomato paste | B54: Tins | F54: Kg | L54: Kg | M54: =IF(AND(H54<>"", J54<>""), H54-J54, IF(H54<>"", H54-I54*VLOOKUP(A54, BACKEND1!$A:$G,6,FALSE), IF(J54<>"", -J54+K54*VLOOKUP(A54, BACKEND1!$A:$G,6,FALSE),0)))+ (C54+D54-E54)*VLOOKUP(A54, BACKEND1!$A:$G,5,FALSE)+G54 -> 0
A55: Tabasco | B55: Pcs | F55: Kgs | L55: Kgs | M55: =IF(AND(H55<>"", J55<>""), H55-J55, IF(H55<>"", H55-I55*VLOOKUP(A55, BACKEND1!$A:$G,6,FALSE), IF(J55<>"", -J55+K55*VLOOKUP(A55, BACKEND1!$A:$G,6,FALSE),0)))+ (C55+D55-E55)*VLOOKUP(A55, BACKEND1!$A:$G,5,FALSE)+G55 -> 0
... A64: Ketchup 5L | B64: Jerrycan | F64: kg | L64: kg | M64: =IF(AND(H64<>"", J64<>""), H64-J64, IF(H64<>"", H64-I64*VLOOKUP(A64, BACKEND1!$A:$G,6,FALSE), IF(J64<>"", -J64+K64*VLOOKUP(A64, BACKEND1!$A:$G,6,FALSE),0)))+ (C64+D64-E64)*VLOOKUP(A64, BACKEND1!$A:$G,5,FALSE)+G64 -> 0
A65: Dry Foods | M65: =IF(AND(H65<>"", J65<>""), H65-J65, IF(H65<>"", H65-I65*VLOOKUP(A65, BACKEND1!$A:$G,6,FALSE), IF(J65<>"", -J65+K65*VLOOKUP(A65, BACKEND1!$A:$G,6,FALSE),0)))+ (C65+D65-E65)*VLOOKUP(A65, BACKEND1!$A:$G,5,FALSE)+G65 -> 0
A66: Baking flour | B66: Pkts | F66: Kg | L66: Kg | M66: =IF(AND(H66<>"", J66<>""), H66-J66, IF(H66<>"", H66-I66*VLOOKUP(A66, BACKEND1!$A:$G,6,FALSE), IF(J66<>"", -J66+K66*VLOOKUP(A66, BACKEND1!$A:$G,6,FALSE),0)))+ (C66+D66-E66)*VLOOKUP(A66, BACKEND1!$A:$G,5,FALSE)+G66 -> 0
A67: Baking Powder | B67: Pkts | F67: Kg | L67: Kg | M67: =IF(AND(H67<>"", J67<>""), H67-J67, IF(H67<>"", H67-I67*VLOOKUP(A67, BACKEND1!$A:$G,6,FALSE), IF(J67<>"", -J67+K67*VLOOKUP(A67, BACKEND1!$A:$G,6,FALSE),0)))+ (C67+D67-E67)*VLOOKUP(A67, BACKEND1!$A:$G,5,FALSE)+G67 -> 0
A68: Basmati rice | B68: Kg | F68: Kg | L68: Kg | M68: =IF(AND(H68<>"", J68<>""), H68-J68, IF(H68<>"", H68-I68*VLOOKUP(A68, BACKEND1!$A:$G,6,FALSE), IF(J68<>"", -J68+K68*VLOOKUP(A68, BACKEND1!$A:$G,6,FALSE),0)))+ (C68+D68-E68)*VLOOKUP(A68, BACKEND1!$A:$G,5,FALSE)+G68 -> 0
A69: Corn flour | B69: Pkts | F69: Kg | L69: Kg | M69: =IF(AND(H69<>"", J69<>""), H69-J69, IF(H69<>"", H69-I69*VLOOKUP(A69, BACKEND1!$A:$G,6,FALSE), IF(J69<>"", -J69+K69*VLOOKUP(A69, BACKEND1!$A:$G,6,FALSE),0)))+ (C69+D69-E69)*VLOOKUP(A69, BACKEND1!$A:$G,5,FALSE)+G69 -> 0
A70: Oils, Fats & Creams | M70: =IF(AND(H70<>"", J70<>""), H70-J70, IF(H70<>"", H70-I70*VLOOKUP(A70, BACKEND1!$A:$G,6,FALSE), IF(J70<>"", -J70+K70*VLOOKUP(A70, BACKEND1!$A:$G,6,FALSE),0)))+ (C70+D70-E70)*VLOOKUP(A70, BACKEND1!$A:$G,5,FALSE)+G70 -> 0
A71: Cooking oil 20L | B71: Jerrycan | F71: Liters | L71: Liters | M71: =IF(AND(H71<>"", J71<>""), H71-J71, IF(H71<>"", H71-I71*VLOOKUP(A71, BACKEND1!$A:$G,6,FALSE), IF(J71<>"", -J71+K71*VLOOKUP(A71, BACKEND1!$A:$G,6,FALSE),0)))+ (C71+D71-E71)*VLOOKUP(A71, BACKEND1!$A:$G,5,FALSE)+G71 -> 0
A72: Croma Butter | B72: Kg | F72: Kg | L72: Kg | M72: =IF(AND(H72<>"", J72<>""), H72-J72, IF(H72<>"", H72-I72*VLOOKUP(A72, BACKEND1!$A:$G,6,FALSE), IF(J72<>"", -J72+K72*VLOOKUP(A72, BACKEND1!$A:$G,6,FALSE),0)))+ (C72+D72-E72)*VLOOKUP(A72, BACKEND1!$A:$G,5,FALSE)+G72 -> 0
A73: Prestige | B73: Kg | F73: Kg | L73: Kg | M73: =IF(AND(H73<>"", J73<>""), H73-J73, IF(H73<>"", H73-I73*VLOOKUP(A73, BACKEND1!$A:$G,6,FALSE), IF(J73<>"", -J73+K73*VLOOKUP(A73, BACKEND1!$A:$G,6,FALSE),0)))+ (C73+D73-E73)*VLOOKUP(A73, BACKEND1!$A:$G,5,FALSE)+G73 -> 0
A74: Cooking cream | B74: Packs | F74: Liters | L74: Liters | M74: =IF(AND(H74<>"", J74<>""), H74-J74, IF(H74<>"", H74-I74*VLOOKUP(A74, BACKEND1!$A:$G,6,FALSE), IF(J74<>"", -J74+K74*VLOOKUP(A74, BACKEND1!$A:$G,6,FALSE),0)))+ (C74+D74-E74)*VLOOKUP(A74, BACKEND1!$A:$G,5,FALSE)+G74 -> 0
A75: Sunseed Oil 5L | B75: Pcs | F75: Liters | L75: Liters | M75: =IF(AND(H75<>"", J75<>""), H75-J75, IF(H75<>"", H75-I75*VLOOKUP(A75, BACKEND1!$A:$G,6,FALSE), IF(J75<>"", -J75+K75*VLOOKUP(A75, BACKEND1!$A:$G,6,FALSE),0)))+ (C75+D75-E75)*VLOOKUP(A75, BACKEND1!$A:$G,5,FALSE)+G75 -> 0
A76: Whipping cream | B76: Packs | F76: Kg | L76: Kg | M76: =IF(AND(H76<>"", J76<>""), H76-J76, IF(H76<>"", H76-I76*VLOOKUP(A76, BACKEND1!$A:$G,6,FALSE), IF(J76<>"", -J76+K76*VLOOKUP(A76, BACKEND1!$A:$G,6,FALSE),0)))+ (C76+D76-E76)*VLOOKUP(A76, BACKEND1!$A:$G,5,FALSE)+G76 -> 0
A77: Olive Oil | B77: Can | F77: Liters | L77: Liters | M77: =IF(AND(H77<>"", J77<>""), H77-J77, IF(H77<>"", H77-I77*VLOOKUP(A77, BACKEND1!$A:$G,6,FALSE), IF(J77<>"", -J77+K77*VLOOKUP(A77, BACKEND1!$A:$G,6,FALSE),0)))+ (C77+D77-E77)*VLOOKUP(A77, BACKEND1!$A:$G,5,FALSE)+G77 -> 0
A78: Coconut Oil | B78: Jerrycan | F78: Kg | L78: Kg | M78: =IF(AND(H78<>"", J78<>""), H78-J78, IF(H78<>"", H78-I78*VLOOKUP(A78, BACKEND1!$A:$G,6,FALSE), IF(J78<>"", -J78+K78*VLOOKUP(A78, BACKEND1!$A:$G,6,FALSE),0)))+ (C78+D78-E78)*VLOOKUP(A78, BACKEND1!$A:$G,5,FALSE)+G78 -> 0
A79: Seseame Oil | B79: Bottle | F79: Kg | L79: Kg | M79: =IF(AND(H79<>"", J79<>""), H79-J79, IF(H79<>"", H79-I79*VLOOKUP(A79, BACKEND1!$A:$G,6,FALSE), IF(J79<>"", -J79+K79*VLOOKUP(A79, BACKEND1!$A:$G,6,FALSE),0)))+ (C79+D79-E79)*VLOOKUP(A79, BACKEND1!$A:$G,5,FALSE)+G79 -> 0
A80: Sauces | M80: =IF(AND(H80<>"", J80<>""), H80-J80, IF(H80<>"", H80-I80*VLOOKUP(A80, BACKEND1!$A:$G,6,FALSE), IF(J80<>"", -J80+K80*VLOOKUP(A80, BACKEND1!$A:$G,6,FALSE),0)))+ (C80+D80-E80)*VLOOKUP(A80, BACKEND1!$A:$G,5,FALSE)+G80 -> 0
A81: Light soy sauce | B81: Bottle | F81: Liters | L81: Liters | M81: =IF(AND(H81<>"", J81<>""), H81-J81, IF(H81<>"", H81-I81*VLOOKUP(A81, BACKEND1!$A:$G,6,FALSE), IF(J81<>"", -J81+K81*VLOOKUP(A81, BACKEND1!$A:$G,6,FALSE),0)))+ (C81+D81-E81)*VLOOKUP(A81, BACKEND1!$A:$G,5,FALSE)+G81 -> 0
A82: Dark soy sauce | B82: Bottle | F82: Liters | L82: Liters | M82: =IF(AND(H82<>"", J82<>""), H82-J82, IF(H82<>"", H82-I82*VLOOKUP(A82, BACKEND1!$A:$G,6,FALSE), IF(J82<>"", -J82+K82*VLOOKUP(A82, BACKEND1!$A:$G,6,FALSE),0)))+ (C82+D82-E82)*VLOOKUP(A82, BACKEND1!$A:$G,5,FALSE)+G82 -> 0
A83: Sweet chilli sauce | B83: Bottle | F83: Liters | L83: Liters | M83: =IF(AND(H83<>"", J83<>""), H83-J83, IF(H83<>"", H83-I83*VLOOKUP(A83, BACKEND1!$A:$G,6,FALSE), IF(J83<>"", -J83+K83*VLOOKUP(A83, BACKEND1!$A:$G,6,FALSE),0)))+ (C83+D83-E83)*VLOOKUP(A83, BACKEND1!$A:$G,5,FALSE)+G83 -> 0
A84: Oyster sauce | B84: Bottle | F84: Liters | L84: Liters | M84: =IF(AND(H84<>"", J84<>""), H84-J84, IF(H84<>"", H84-I84*VLOOKUP(A84, BACKEND1!$A:$G,6,FALSE), IF(J84<>"", -J84+K84*VLOOKUP(A84, BACKEND1!$A:$G,6,FALSE),0)))+ (C84+D84-E84)*VLOOKUP(A84, BACKEND1!$A:$G,5,FALSE)+G84 -> 0
A85: Worcestershire sauce | B85: Bottles | F85: Liters | L85: Liters | M85: =IF(AND(H85<>"", J85<>""), H85-J85, IF(H85<>"", H85-I85*VLOOKUP(A85, BACKEND1!$A:$G,6,FALSE), IF(J85<>"", -J85+K85*VLOOKUP(A85, BACKEND1!$A:$G,6,FALSE),0)))+ (C85+D85-E85)*VLOOKUP(A85, BACKEND1!$A:$G,5,FALSE)+G85 -> 0
A86: Top up sauce | B86: Jerrycan | F86: Liters | L86: Liters | M86: =IF(AND(H86<>"", J86<>""), H86-J86, IF(H86<>"", H86-I86*VLOOKUP(A86, BACKEND1!$A:$G,6,FALSE), IF(J86<>"", -J86+K86*VLOOKUP(A86, BACKEND1!$A:$G,6,FALSE),0)))+ (C86+D86-E86)*VLOOKUP(A86, BACKEND1!$A:$G,5,FALSE)+G86 -> 0
A87: Fish Sauce | B87: Bottle | F87: Liters | L87: Liters | M87: =IF(AND(H87<>"", J87<>""), H87-J87, IF(H87<>"", H87-I87*VLOOKUP(A87, BACKEND1!$A:$G,6,FALSE), IF(J87<>"", -J87+K87*VLOOKUP(A87, BACKEND1!$A:$G,6,FALSE),0)))+ (C87+D87-E87)*VLOOKUP(A87, BACKEND1!$A:$G,5,FALSE)+G87 -> 0
A88: Red Wine | B88: Bottle | F88: Liters | L88: Liters | M88: =IF(AND(H88<>"", J88<>""), H88-J88, IF(H88<>"", H88-I88*VLOOKUP(A88, BACKEND1!$A:$G,6,FALSE), IF(J88<>"", -J88+K88*VLOOKUP(A88, BACKEND1!$A:$G,6,FALSE),0)))+ (C88+D88-E88)*VLOOKUP(A88, BACKEND1!$A:$G,5,FALSE)+G88 -> 0
A89: White Wine | B89: Bottle | F89: Liters | L89: Liters | M89: =IF(AND(H89<>"", J89<>""), H89-J89, IF(H89<>"", H89-I89*VLOOKUP(A89, BACKEND1!$A:$G,6,FALSE), IF(J89<>"", -J89+K89*VLOOKUP(A89, BACKEND1!$A:$G,6,FALSE),0)))+ (C89+D89-E89)*VLOOKUP(A89, BACKEND1!$A:$G,5,FALSE)+G89 -> 0
A90: Spices | M90: =IF(AND(H90<>"", J90<>""), H90-J90, IF(H90<>"", H90-I90*VLOOKUP(A90, BACKEND1!$A:$G,6,FALSE), IF(J90<>"", -J90+K90*VLOOKUP(A90, BACKEND1!$A:$G,6,FALSE),0)))+ (C90+D90-E90)*VLOOKUP(A90, BACKEND1!$A:$G,5,FALSE)+G90 -> 0
A91: Turmeric | B91: Packet | F91: Kg | L91: Kg | M91: =IF(AND(H91<>"", J91<>""), H91-J91, IF(H91<>"", H91-I91*VLOOKUP(A91, BACKEND1!$A:$G,6,FALSE), IF(J91<>"", -J91+K91*VLOOKUP(A91, BACKEND1!$A:$G,6,FALSE),0)))+ (C91+D91-E91)*VLOOKUP(A91, BACKEND1!$A:$G,5,FALSE)+G91 -> 0
A92: Paprika | B92: Packet | F92: Kg | L92: Kg | M92: =IF(AND(H92<>"", J92<>""), H92-J92, IF(H92<>"", H92-I92*VLOOKUP(A92, BACKEND1!$A:$G,6,FALSE), IF(J92<>"", -J92+K92*VLOOKUP(A92, BACKEND1!$A:$G,6,FALSE),0)))+ (C92+D92-E92)*VLOOKUP(A92, BACKEND1!$A:$G,5,FALSE)+G92 -> 0
A93: Origano | B93: Packet | F93: Kg | L93: Kg | M93: =IF(AND(H93<>"", J93<>""), H93-J93, IF(H93<>"", H93-I93*VLOOKUP(A93, BACKEND1!$A:$G,6,FALSE), IF(J93<>"", -J93+K93*VLOOKUP(A93, BACKEND1!$A:$G,6,FALSE),0)))+ (C93+D93-E93)*VLOOKUP(A93, BACKEND1!$A:$G,5,FALSE)+G93 -> 0
A94: Curry powder | B94: Packet | F94: Kg | L94: Kg | M94: =IF(AND(H94<>"", J94<>""), H94-J94, IF(H94<>"", H94-I94*VLOOKUP(A94, BACKEND1!$A:$G,6,FALSE), IF(J94<>"", -J94+K94*VLOOKUP(A94, BACKEND1!$A:$G,6,FALSE),0)))+ (C94+D94-E94)*VLOOKUP(A94, BACKEND1!$A:$G,5,FALSE)+G94 -> 0
A95: Black pepper powder | B95: Packet | F95: Kg | L95: Kg | M95: =IF(AND(H95<>"", J95<>""), H95-J95, IF(H95<>"", H95-I95*VLOOKUP(A95, BACKEND1!$A:$G,6,FALSE), IF(J95<>"", -J95+K95*VLOOKUP(A95, BACKEND1!$A:$G,6,FALSE),0)))+ (C95+D95-E95)*VLOOKUP(A95, BACKEND1!$A:$G,5,FALSE)+G95 -> 0
A96: Black pepper Seeds | B96: Packet | F96: Kg | L96: Kg | M96: =IF(AND(H96<>"", J96<>""), H96-J96, IF(H96<>"", H96-I96*VLOOKUP(A96, BACKEND1!$A:$G,6,FALSE), IF(J96<>"", -J96+K96*VLOOKUP(A96, BACKEND1!$A:$G,6,FALSE),0)))+ (C96+D96-E96)*VLOOKUP(A96, BACKEND1!$A:$G,5,FALSE)+G96 -> 0
A97: Cumin seeds | B97: Packet | F97: Kg | L97: Kg | M97: =IF(AND(H97<>"", J97<>""), H97-J97, IF(H97<>"", H97-I97*VLOOKUP(A97, BACKEND1!$A:$G,6,FALSE), IF(J97<>"", -J97+K97*VLOOKUP(A97, BACKEND1!$A:$G,6,FALSE),0)))+ (C97+D97-E97)*VLOOKUP(A97, BACKEND1!$A:$G,5,FALSE)+G97 -> 0
A98: Simba mbili | B98: Tin | F98: Kg | L98: Kg | M98: =IF(AND(H98<>"", J98<>""), H98-J98, IF(H98<>"", H98-I98*VLOOKUP(A98, BACKEND1!$A:$G,6,FALSE), IF(J98<>"", -J98+K98*VLOOKUP(A98, BACKEND1!$A:$G,6,FALSE),0)))+ (C98+D98-E98)*VLOOKUP(A98, BACKEND1!$A:$G,5,FALSE)+G98 -> 0
A99: Cinnamon powder | B99: Packet | F99: Kg | L99: Kg | M99: =IF(AND(H99<>"", J99<>""), H99-J99, IF(H99<>"", H99-I99*VLOOKUP(A99, BACKEND1!$A:$G,6,FALSE), IF(J99<>"", -J99+K99*VLOOKUP(A99, BACKEND1!$A:$G,6,FALSE),0)))+ (C99+D99-E99)*VLOOKUP(A99, BACKEND1!$A:$G,5,FALSE)+G99 -> 0
A100: Ground cloves | B100: Packet | F100: Kg | L100: Kg | M100: =IF(AND(H100<>"", J100<>""), H100-J100, IF(H100<>"", H100-I100*VLOOKUP(A100, BACKEND1!$A:$G,6,FALSE), IF(J100<>"", -J100+K100*VLOOKUP(A100, BACKEND1!$A:$G,6,FALSE),0)))+ (C100+D100-E100)*VLOOKUP(A100, BACKEND1!$A:$G,5,FALSE)+G100 -> 0
A101: Pilau masala | B101: Packet | F101: Kg | L101: Kg | M101: =IF(AND(H101<>"", J101<>""), H101-J101, IF(H101<>"", H101-I101*VLOOKUP(A101, BACKEND1!$A:$G,6,FALSE), IF(J101<>"", -J101+K101*VLOOKUP(A101, BACKEND1!$A:$G,6,FALSE),0)))+ (C101+D101-E101)*VLOOKUP(A101, BACKEND1!$A:$G,5,FALSE)+G101 -> 0
A102: Cocoa powder | B102: Packet | F102: Kg | L102: Kg | M102: =IF(AND(H102<>"", J102<>""), H102-J102, IF(H102<>"", H102-I102*VLOOKUP(A102, BACKEND1!$A:$G,6,FALSE), IF(J102<>"", -J102+K102*VLOOKUP(A102, BACKEND1!$A:$G,6,FALSE),0)))+ (C102+D102-E102)*VLOOKUP(A102, BACKEND1!$A:$G,5,FALSE)+G102 -> 0
... A126: Chilli Powder | B126: Packet | F126: Kg | L126: Kg | M126: =IF(AND(H126<>"", J126<>""), H126-J126, IF(H126<>"", H126-I126*VLOOKUP(A126, BACKEND1!$A:$G,6,FALSE), IF(J126<>"", -J126+K126*VLOOKUP(A126, BACKEND1!$A:$G,6,FALSE),0)))+ (C126+D126-E126)*VLOOKUP(A126, BACKEND1!$A:$G,5,FALSE)+G126 -> 0
A127: Sweeteners | M127: =IF(AND(H127<>"", J127<>""), H127-J127, IF(H127<>"", H127-I127*VLOOKUP(A127, BACKEND1!$A:$G,6,FALSE), IF(J127<>"", -J127+K127*VLOOKUP(A127, BACKEND1!$A:$G,6,FALSE),0)))+ (C127+D127-E127)*VLOOKUP(A127, BACKEND1!$A:$G,5,FALSE)+G127 -> 0
A128: Brown sugar | B128: Packet | F128: Kg | L128: Kg | M128: =IF(AND(H128<>"", J128<>""), H128-J128, IF(H128<>"", H128-I128*VLOOKUP(A128, BACKEND1!$A:$G,6,FALSE), IF(J128<>"", -J128+K128*VLOOKUP(A128, BACKEND1!$A:$G,6,FALSE),0)))+ (C128+D128-E128)*VLOOKUP(A128, BACKEND1!$A:$G,5,FALSE)+G128 -> 0
A129: Sugar | B129: Kg | F129: Kg | L129: Kg | M129: =IF(AND(H129<>"", J129<>""), H129-J129, IF(H129<>"", H129-I129*VLOOKUP(A129, BACKEND1!$A:$G,6,FALSE), IF(J129<>"", -J129+K129*VLOOKUP(A129, BACKEND1!$A:$G,6,FALSE),0)))+ (C129+D129-E129)*VLOOKUP(A129, BACKEND1!$A:$G,5,FALSE)+G129 -> 0
A130: Icing sugar | B130: Packet | F130: Kg | L130: Kg | M130: =IF(AND(H130<>"", J130<>""), H130-J130, IF(H130<>"", H130-I130*VLOOKUP(A130, BACKEND1!$A:$G,6,FALSE), IF(J130<>"", -J130+K130*VLOOKUP(A130, BACKEND1!$A:$G,6,FALSE),0)))+ (C130+D130-E130)*VLOOKUP(A130, BACKEND1!$A:$G,5,FALSE)+G130 -> 0
A131: Bbq sauce | B131: Bottles | F131: Liters | L131: Liters | M131: =IF(AND(H131<>"", J131<>""), H131-J131, IF(H131<>"", H131-I131*VLOOKUP(A131, BACKEND1!$A:$G,6,FALSE), IF(J131<>"", -J131+K131*VLOOKUP(A131, BACKEND1!$A:$G,6,FALSE),0)))+ (C131+D131-E131)*VLOOKUP(A131, BACKEND1!$A:$G,5,FALSE)+G131 -> 0
A132: Canned goods | M132: =IF(AND(H132<>"", J132<>""), H132-J132, IF(H132<>"", H132-I132*VLOOKUP(A132, BACKEND1!$A:$G,6,FALSE), IF(J132<>"", -J132+K132*VLOOKUP(A132, BACKEND1!$A:$G,6,FALSE),0)))+ (C132+D132-E132)*VLOOKUP(A132, BACKEND1!$A:$G,5,FALSE)+G132 -> 0
A133: Aromat | B133: Tin | F133: Kg | L133: Kg | M133: =IF(AND(H133<>"", J133<>""), H133-J133, IF(H133<>"", H133-I133*VLOOKUP(A133, BACKEND1!$A:$G,6,FALSE), IF(J133<>"", -J133+K133*VLOOKUP(A133, BACKEND1!$A:$G,6,FALSE),0)))+ (C133+D133-E133)*VLOOKUP(A133, BACKEND1!$A:$G,5,FALSE)+G133 -> 0
A134: Salt | B134: Pkt | F134: Kg | L134: Kg | M134: =IF(AND(H134<>"", J134<>""), H134-J134, IF(H134<>"", H134-I134*VLOOKUP(A134, BACKEND1!$A:$G,6,FALSE), IF(J134<>"", -J134+K134*VLOOKUP(A134, BACKEND1!$A:$G,6,FALSE),0)))+ (C134+D134-E134)*VLOOKUP(A134, BACKEND1!$A:$G,5,FALSE)+G134 -> 0
A135: Sweet corn | B135: Tins | F135: Kg | L135: Kg | M135: =IF(AND(H135<>"", J135<>""), H135-J135, IF(H135<>"", H135-I135*VLOOKUP(A135, BACKEND1!$A:$G,6,FALSE), IF(J135<>"", -J135+K135*VLOOKUP(A135, BACKEND1!$A:$G,6,FALSE),0)))+ (C135+D135-E135)*VLOOKUP(A135, BACKEND1!$A:$G,5,FALSE)+G135 -> 0
A136: Coconut Milk | B136: Tins | F136: Kg | L136: Kg | M136: =IF(AND(H136<>"", J136<>""), H136-J136, IF(H136<>"", H136-I136*VLOOKUP(A136, BACKEND1!$A:$G,6,FALSE), IF(J136<>"", -J136+K136*VLOOKUP(A136, BACKEND1!$A:$G,6,FALSE),0)))+ (C136+D136-E136)*VLOOKUP(A136, BACKEND1!$A:$G,5,FALSE)+G136 -> 0
A137: Peanut butter | B137: Tins | F137: Kg | L137: Kg | M137: =IF(AND(H137<>"", J137<>""), H137-J137, IF(H137<>"", H137-I137*VLOOKUP(A137, BACKEND1!$A:$G,6,FALSE), IF(J137<>"", -J137+K137*VLOOKUP(A137, BACKEND1!$A:$G,6,FALSE),0)))+ (C137+D137-E137)*VLOOKUP(A137, BACKEND1!$A:$G,5,FALSE)+G137 -> 0
A138: Black olives | B138: Tins | F138: Kg | L138: Kg | M138: =IF(AND(H138<>"", J138<>""), H138-J138, IF(H138<>"", H138-I138*VLOOKUP(A138, BACKEND1!$A:$G,6,FALSE), IF(J138<>"", -J138+K138*VLOOKUP(A138, BACKEND1!$A:$G,6,FALSE),0)))+ (C138+D138-E138)*VLOOKUP(A138, BACKEND1!$A:$G,5,FALSE)+G138 -> 0
A139: Green olives | B139: Tins | F139: Kg | L139: Kg | M139: =IF(AND(H139<>"", J139<>""), H139-J139, IF(H139<>"", H139-I139*VLOOKUP(A139, BACKEND1!$A:$G,6,FALSE), IF(J139<>"", -J139+K139*VLOOKUP(A139, BACKEND1!$A:$G,6,FALSE),0)))+ (C139+D139-E139)*VLOOKUP(A139, BACKEND1!$A:$G,5,FALSE)+G139 -> 0
A140: Mushroom Tin | B140: Tins | F140: Kg | L140: Kg | M140: =IF(AND(H140<>"", J140<>""), H140-J140, IF(H140<>"", H140-I140*VLOOKUP(A140, BACKEND1!$A:$G,6,FALSE), IF(J140<>"", -J140+K140*VLOOKUP(A140, BACKEND1!$A:$G,6,FALSE),0)))+ (C140+D140-E140)*VLOOKUP(A140, BACKEND1!$A:$G,5,FALSE)+G140 -> 0
A141: Pickles | B141: Tins | F141: Kg | L141: Kg | M141: =IF(AND(H141<>"", J141<>""), H141-J141, IF(H141<>"", H141-I141*VLOOKUP(A141, BACKEND1!$A:$G,6,FALSE), IF(J141<>"", -J141+K141*VLOOKUP(A141, BACKEND1!$A:$G,6,FALSE),0)))+ (C141+D141-E141)*VLOOKUP(A141, BACKEND1!$A:$G,5,FALSE)+G141 -> 0
A142: Grapes | B142: Pkt | F142: Kg | L142: Kg | M142: =IF(AND(H142<>"", J142<>""), H142-J142, IF(H142<>"", H142-I142*VLOOKUP(A142, BACKEND1!$A:$G,6,FALSE), IF(J142<>"", -J142+K142*VLOOKUP(A142, BACKEND1!$A:$G,6,FALSE),0)))+ (C142+D142-E142)*VLOOKUP(A142, BACKEND1!$A:$G,5,FALSE)+G142 -> 0
A143: Dates | B143: Pkt | F143: Kg | L143: Kg | M143: =IF(AND(H143<>"", J143<>""), H143-J143, IF(H143<>"", H143-I143*VLOOKUP(A143, BACKEND1!$A:$G,6,FALSE), IF(J143<>"", -J143+K143*VLOOKUP(A143, BACKEND1!$A:$G,6,FALSE),0)))+ (C143+D143-E143)*VLOOKUP(A143, BACKEND1!$A:$G,5,FALSE)+G143 -> 0
A144: Mayonnaise big tin | B144: Tin | F144: Kg | L144: Kg | M144: =IF(AND(H144<>"", J144<>""), H144-J144, IF(H144<>"", H144-I144*VLOOKUP(A144, BACKEND1!$A:$G,6,FALSE), IF(J144<>"", -J144+K144*VLOOKUP(A144, BACKEND1!$A:$G,6,FALSE),0)))+ (C144+D144-E144)*VLOOKUP(A144, BACKEND1!$A:$G,5,FALSE)+G144 -> 0
... A151: Sprinkles | B151: Tin | F151: kg | L151: kg | M151: =IF(AND(H151<>"", J151<>""), H151-J151, IF(H151<>"", H151-I151*VLOOKUP(A151, BACKEND1!$A:$G,6,FALSE), IF(J151<>"", -J151+K151*VLOOKUP(A151, BACKEND1!$A:$G,6,FALSE),0)))+ (C151+D151-E151)*VLOOKUP(A151, BACKEND1!$A:$G,5,FALSE)+G151 -> 0
A152: Dairy | M152: =IF(AND(H152<>"", J152<>""), H152-J152, IF(H152<>"", H152-I152*VLOOKUP(A152, BACKEND1!$A:$G,6,FALSE), IF(J152<>"", -J152+K152*VLOOKUP(A152, BACKEND1!$A:$G,6,FALSE),0)))+ (C152+D152-E152)*VLOOKUP(A152, BACKEND1!$A:$G,5,FALSE)+G152 -> 0
A153: Fresh milk/Jesa | B153: Liters | F153: Liters | L153: Liters | M153: =IF(AND(H153<>"", J153<>""), H153-J153, IF(H153<>"", H153-I153*VLOOKUP(A153, BACKEND1!$A:$G,6,FALSE), IF(J153<>"", -J153+K153*VLOOKUP(A153, BACKEND1!$A:$G,6,FALSE),0)))+ (C153+D153-E153)*VLOOKUP(A153, BACKEND1!$A:$G,5,FALSE)+G153 -> 0
A154: Mozzarella cheese | B154: Kg | F154: Kg | L154: Kg | M154: =IF(AND(H154<>"", J154<>""), H154-J154, IF(H154<>"", H154-I154*VLOOKUP(A154, BACKEND1!$A:$G,6,FALSE), IF(J154<>"", -J154+K154*VLOOKUP(A154, BACKEND1!$A:$G,6,FALSE),0)))+ (C154+D154-E154)*VLOOKUP(A154, BACKEND1!$A:$G,5,FALSE)+G154 -> 0
A155: Parmesan cheese | B155: Kg | F155: Kg | L155: Kg | M155: =IF(AND(H155<>"", J155<>""), H155-J155, IF(H155<>"", H155-I155*VLOOKUP(A155, BACKEND1!$A:$G,6,FALSE), IF(J155<>"", -J155+K155*VLOOKUP(A155, BACKEND1!$A:$G,6,FALSE),0)))+ (C155+D155-E155)*VLOOKUP(A155, BACKEND1!$A:$G,5,FALSE)+G155 -> 0
A156: Cheddar cheese | B156: Kg | F156: Kg | L156: Kg | M156: =IF(AND(H156<>"", J156<>""), H156-J156, IF(H156<>"", H156-I156*VLOOKUP(A156, BACKEND1!$A:$G,6,FALSE), IF(J156<>"", -J156+K156*VLOOKUP(A156, BACKEND1!$A:$G,6,FALSE),0)))+ (C156+D156-E156)*VLOOKUP(A156, BACKEND1!$A:$G,5,FALSE)+G156 -> 0
A157: Plain yoghurt | B157: Kg | F157: Kg | L157: Kg | M157: =IF(AND(H157<>"", J157<>""), H157-J157, IF(H157<>"", H157-I157*VLOOKUP(A157, BACKEND1!$A:$G,6,FALSE), IF(J157<>"", -J157+K157*VLOOKUP(A157, BACKEND1!$A:$G,6,FALSE),0)))+ (C157+D157-E157)*VLOOKUP(A157, BACKEND1!$A:$G,5,FALSE)+G157 -> 0
A158: Lato ghee | B158: Kg | F158: kg | L158: kg | M158: =IF(AND(H158<>"", J158<>""), H158-J158, IF(H158<>"", H158-I158*VLOOKUP(A158, BACKEND1!$A:$G,6,FALSE), IF(J158<>"", -J158+K158*VLOOKUP(A158, BACKEND1!$A:$G,6,FALSE),0)))+ (C158+D158-E158)*VLOOKUP(A158, BACKEND1!$A:$G,5,FALSE)+G158 -> 0
A159: Fruits & Vegetables | M159: =IF(AND(H159<>"", J159<>""), H159-J159, IF(H159<>"", H159-I159*VLOOKUP(A159, BACKEND1!$A:$G,6,FALSE), IF(J159<>"", -J159+K159*VLOOKUP(A159, BACKEND1!$A:$G,6,FALSE),0)))+ (C159+D159-E159)*VLOOKUP(A159, BACKEND1!$A:$G,5,FALSE)+G159 -> 0
A160: Hard lettuce | B160: Pcs | F160: Pcs | L160: Pcs | M160: =IF(AND(H160<>"", J160<>""), H160-J160, IF(H160<>"", H160-I160*VLOOKUP(A160, BACKEND1!$A:$G,6,FALSE), IF(J160<>"", -J160+K160*VLOOKUP(A160, BACKEND1!$A:$G,6,FALSE),0)))+ (C160+D160-E160)*VLOOKUP(A160, BACKEND1!$A:$G,5,FALSE)+G160 -> 0
A161: Soft lettuce | B161: Pcs | F161: Pcs | L161: Pcs | M161: =IF(AND(H161<>"", J161<>""), H161-J161, IF(H161<>"", H161-I161*VLOOKUP(A161, BACKEND1!$A:$G,6,FALSE), IF(J161<>"", -J161+K161*VLOOKUP(A161, BACKEND1!$A:$G,6,FALSE),0)))+ (C161+D161-E161)*VLOOKUP(A161, BACKEND1!$A:$G,5,FALSE)+G161 -> 0
A162: Onions | B162: Kg | F162: Kg | L162: Kg | M162: =IF(AND(H162<>"", J162<>""), H162-J162, IF(H162<>"", H162-I162*VLOOKUP(A162, BACKEND1!$A:$G,6,FALSE), IF(J162<>"", -J162+K162*VLOOKUP(A162, BACKEND1!$A:$G,6,FALSE),0)))+ (C162+D162-E162)*VLOOKUP(A162, BACKEND1!$A:$G,5,FALSE)+G162 -> 0
...

Sheet 23rd-24thMAY
B2: WHOLE | F2: REMAINDER | L2: ACCOUNTABILITY
A3: Type | B3: U.O.M | C3: Opening | D3: Added | E3: Closing | F3: U.O.M | G3: Added | H3: Opening | I3: Units | J3: Closing | K3: Units | L3: U.O.M | M3: Used | N3: Transfer | O3: Damage
A4: Portioned Items: Meats & Others
A5: Carribean jerk | B5: Ptns | C5: ='22ndMAY'!E5 -> 38.02 | F5: Pcs | L5: Pcs | M5: =IF(AND(H5<>"", J5<>""), H5-J5, IF(H5<>"", H5-I5*VLOOKUP(A5, BACKEND2!$A:$G,6,FALSE), IF(J5<>"", -J5+K5*VLOOKUP(A5, BACKEND2!$A:$G,6,FALSE),0)))+ (C5+D5-E5)*VLOOKUP(A5, BACKEND2!$A:$G,5,FALSE)+G5 -> 114.06
A6: Chicken breast | B6: Ptns | C6: ='22ndMAY'!E6 -> 6 | F6: Pcs | L6: Pcs | M6: =IF(AND(H6<>"", J6<>""), H6-J6, IF(H6<>"", H6-I6*VLOOKUP(A6, BACKEND2!$A:$G,6,FALSE), IF(J6<>"", -J6+K6*VLOOKUP(A6, BACKEND2!$A:$G,6,FALSE),0)))+ (C6+D6-E6)*VLOOKUP(A6, BACKEND2!$A:$G,5,FALSE)+G6 -> 12
A7: Chicken wings | B7: Ptns | C7: ='22ndMAY'!E7 -> 6 | F7: Pcs | L7: Pcs | M7: =IF(AND(H7<>"", J7<>""), H7-J7, IF(H7<>"", H7-I7*VLOOKUP(A7, BACKEND2!$A:$G,6,FALSE), IF(J7<>"", -J7+K7*VLOOKUP(A7, BACKEND2!$A:$G,6,FALSE),0)))+ (C7+D7-E7)*VLOOKUP(A7, BACKEND2!$A:$G,5,FALSE)+G7 -> 30
A8: Chicken burger | B8: Ptns | C8: ='22ndMAY'!E8 -> 18 | F8: Ptns | L8: Ptns | M8: =IF(AND(H8<>"", J8<>""), H8-J8, IF(H8<>"", H8-I8*VLOOKUP(A8, BACKEND2!$A:$G,6,FALSE), IF(J8<>"", -J8+K8*VLOOKUP(A8, BACKEND2!$A:$G,6,FALSE),0)))+ (C8+D8-E8)*VLOOKUP(A8, BACKEND2!$A:$G,5,FALSE)+G8 -> 18
A9: Min Chicken burger | B9: Ptns | C9: ='22ndMAY'!E9 | F9: Pcs | L9: Pcs | M9: =IF(AND(H9<>"", J9<>""), H9-J9, IF(H9<>"", H9-I9*VLOOKUP(A9, BACKEND2!$A:$G,6,FALSE), IF(J9<>"", -J9+K9*VLOOKUP(A9, BACKEND2!$A:$G,6,FALSE),0)))+ (C9+D9-E9)*VLOOKUP(A9, BACKEND2!$A:$G,5,FALSE)+G9 -> 0
A10: Chicken lollipos | B10: Ptns | C10: ='22ndMAY'!E10 -> 3 | F10: Pcs | L10: Pcs | M10: =IF(AND(H10<>"", J10<>""), H10-J10, IF(H10<>"", H10-I10*VLOOKUP(A10, BACKEND2!$A:$G,6,FALSE), IF(J10<>"", -J10+K10*VLOOKUP(A10, BACKEND2!$A:$G,6,FALSE),0)))+ (C10+D10-E10)*VLOOKUP(A10, BACKEND2!$A:$G,5,FALSE)+G10 -> 24
A11: Chicken pizza | B11: Ptns | C11: ='22ndMAY'!E11 -> 13 | F11: Ptns | L11: Ptns | M11: =IF(AND(H11<>"", J11<>""), H11-J11, IF(H11<>"", H11-I11*VLOOKUP(A11, BACKEND2!$A:$G,6,FALSE), IF(J11<>"", -J11+K11*VLOOKUP(A11, BACKEND2!$A:$G,6,FALSE),0)))+ (C11+D11-E11)*VLOOKUP(A11, BACKEND2!$A:$G,5,FALSE)+G11 -> 13
A12: Chicken Tenders | B12: Ptns | C12: ='22ndMAY'!E12 | F12: Ptns | L12: Ptns | M12: =IF(AND(H12<>"", J12<>""), H12-J12, IF(H12<>"", H12-I12*VLOOKUP(A12, BACKEND2!$A:$G,6,FALSE), IF(J12<>"", -J12+K12*VLOOKUP(A12, BACKEND2!$A:$G,6,FALSE),0)))+ (C12+D12-E12)*VLOOKUP(A12, BACKEND2!$A:$G,5,FALSE)+G12 -> 0
A13: Chicken skewers | B13: Ptns | C13: ='22ndMAY'!E13 -> 8.5 | F13: Pcs | L13: Pcs | M13: =IF(AND(H13<>"", J13<>""), H13-J13, IF(H13<>"", H13-I13*VLOOKUP(A13, BACKEND2!$A:$G,6,FALSE), IF(J13<>"", -J13+K13*VLOOKUP(A13, BACKEND2!$A:$G,6,FALSE),0)))+ (C13+D13-E13)*VLOOKUP(A13, BACKEND2!$A:$G,5,FALSE)+G13 -> 76.5
A14: Chicken stroganoff | B14: Ptns | C14: ='22ndMAY'!E14 -> 20.5 | F14: Ptns | L14: Ptns | M14: =IF(AND(H14<>"", J14<>""), H14-J14, IF(H14<>"", H14-I14*VLOOKUP(A14, BACKEND2!$A:$G,6,FALSE), IF(J14<>"", -J14+K14*VLOOKUP(A14, BACKEND2!$A:$G,6,FALSE),0)))+ (C14+D14-E14)*VLOOKUP(A14, BACKEND2!$A:$G,5,FALSE)+G14 -> 20.5
A15: Chicken spring rolls | B15: Ptns | C15: ='22ndMAY'!E15 -> 5 | F15: Pcs | L15: Pcs | M15: =IF(AND(H15<>"", J15<>""), H15-J15, IF(H15<>"", H15-I15*VLOOKUP(A15, BACKEND2!$A:$G,6,FALSE), IF(J15<>"", -J15+K15*VLOOKUP(A15, BACKEND2!$A:$G,6,FALSE),0)))+ (C15+D15-E15)*VLOOKUP(A15, BACKEND2!$A:$G,5,FALSE)+G15 -> 20
A16: Chicken Samosas | B16: Ptns | C16: ='22ndMAY'!E16 -> 6 | F16: Pcs | L16: Pcs | M16: =IF(AND(H16<>"", J16<>""), H16-J16, IF(H16<>"", H16-I16*VLOOKUP(A16, BACKEND2!$A:$G,6,FALSE), IF(J16<>"", -J16+K16*VLOOKUP(A16, BACKEND2!$A:$G,6,FALSE),0)))+ (C16+D16-E16)*VLOOKUP(A16, BACKEND2!$A:$G,5,FALSE)+G16 -> 24
... A31: Bolognese | B31: Ptns | C31: ='22ndMAY'!E31 -> 13 | F31: Ptns | L31: Ptns | M31: =IF(AND(H31<>"", J31<>""), H31-J31, IF(H31<>"", H31-I31*VLOOKUP(A31, BACKEND2!$A:$G,6,FALSE), IF(J31<>"", -J31+K31*VLOOKUP(A31, BACKEND2!$A:$G,6,FALSE),0)))+ (C31+D31-E31)*VLOOKUP(A31, BACKEND2!$A:$G,5,FALSE)+G31 -> 13
A32: Beef samosas | B32: Ptns | C32: ='22ndMAY'!E32 -> 2 | D32: 5 | F32: Pcs | L32: Pcs | M32: =IF(AND(H32<>"", J32<>""), H32-J32, IF(H32<>"", H32-I32*VLOOKUP(A32, BACKEND2!$A:$G,6,FALSE), IF(J32<>"", -J32+K32*VLOOKUP(A32, BACKEND2!$A:$G,6,FALSE),0)))+ (C32+D32-E32)*VLOOKUP(A32, BACKEND2!$A:$G,5,FALSE)+G32 -> 28
A33: Beef mini burger | B33: Ptns | C33: ='22ndMAY'!E33 | F33: Ptns | L33: Ptns | M33: =IF(AND(H33<>"", J33<>""), H33-J33, IF(H33<>"", H33-I33*VLOOKUP(A33, BACKEND2!$A:$G,6,FALSE), IF(J33<>"", -J33+K33*VLOOKUP(A33, BACKEND2!$A:$G,6,FALSE),0)))+ (C33+D33-E33)*VLOOKUP(A33, BACKEND2!$A:$G,5,FALSE)+G33 -> 0
A34: Whole fish | B34: Ptns | C34: ='22ndMAY'!E34 -> 7 | F34: Ptns | L34: Ptns | M34: =IF(AND(H34<>"", J34<>""), H34-J34, IF(H34<>"", H34-I34*VLOOKUP(A34, BACKEND2!$A:$G,6,FALSE), IF(J34<>"", -J34+K34*VLOOKUP(A34, BACKEND2!$A:$G,6,FALSE),0)))+ (C34+D34-E34)*VLOOKUP(A34, BACKEND2!$A:$G,5,FALSE)+G34 -> 7
A35: Salmon | B35: Ptns | C35: ='22ndMAY'!E35 -> 5 | F35: Ptns | L35: Ptns | M35: =IF(AND(H35<>"", J35<>""), H35-J35, IF(H35<>"", H35-I35*VLOOKUP(A35, BACKEND2!$A:$G,6,FALSE), IF(J35<>"", -J35+K35*VLOOKUP(A35, BACKEND2!$A:$G,6,FALSE),0)))+ (C35+D35-E35)*VLOOKUP(A35, BACKEND2!$A:$G,5,FALSE)+G35 -> 5
A36: Tilapia fillet | B36: Ptns | C36: ='22ndMAY'!E36 -> 4 | F36: Pcs | L36: Pcs | M36: =IF(AND(H36<>"", J36<>""), H36-J36, IF(H36<>"", H36-I36*VLOOKUP(A36, BACKEND2!$A:$G,6,FALSE), IF(J36<>"", -J36+K36*VLOOKUP(A36, BACKEND2!$A:$G,6,FALSE),0)))+ (C36+D36-E36)*VLOOKUP(A36, BACKEND2!$A:$G,5,FALSE)+G36 -> 8
A37: Fish fingers | B37: Ptns | C37: ='22ndMAY'!E37 -> 14 | F37: Pcs | L37: Pcs | M37: =IF(AND(H37<>"", J37<>""), H37-J37, IF(H37<>"", H37-I37*VLOOKUP(A37, BACKEND2!$A:$G,6,FALSE), IF(J37<>"", -J37+K37*VLOOKUP(A37, BACKEND2!$A:$G,6,FALSE),0)))+ (C37+D37-E37)*VLOOKUP(A37, BACKEND2!$A:$G,5,FALSE)+G37 -> 56
A38: Veg Springs rolls | B38: Ptns | C38: ='22ndMAY'!E38 -> 1 | D38: 4 | F38: Pcs | L38: Pcs | M38: =IF(AND(H38<>"", J38<>""), H38-J38, IF(H38<>"", H38-I38*VLOOKUP(A38, BACKEND2!$A:$G,6,FALSE), IF(J38<>"", -J38+K38*VLOOKUP(A38, BACKEND2!$A:$G,6,FALSE),0)))+ (C38+D38-E38)*VLOOKUP(A38, BACKEND2!$A:$G,5,FALSE)+G38 -> 20
A39: Veg Samosas | B39: Ptns | C39: ='22ndMAY'!E39 -> 4 | F39: Pcs | L39: Pcs | M39: =IF(AND(H39<>"", J39<>""), H39-J39, IF(H39<>"", H39-I39*VLOOKUP(A39, BACKEND2!$A:$G,6,FALSE), IF(J39<>"", -J39+K39*VLOOKUP(A39, BACKEND2!$A:$G,6,FALSE),0)))+ (C39+D39-E39)*VLOOKUP(A39, BACKEND2!$A:$G,5,FALSE)+G39 -> 16
A40: Beef Stew | B40: Ptns | C40: ='22ndMAY'!E40 -> 4 | F40: Pcs | L40: Pcs | M40: =IF(AND(H40<>"", J40<>""), H40-J40, IF(H40<>"", H40-I40*VLOOKUP(A40, BACKEND2!$A:$G,6,FALSE), IF(J40<>"", -J40+K40*VLOOKUP(A40, BACKEND2!$A:$G,6,FALSE),0)))+ (C40+D40-E40)*VLOOKUP(A40, BACKEND2!$A:$G,5,FALSE)+G40 -> 4
A41: Beef Minced Meat | B41: Ptns | C41: ='22ndMAY'!E41 | F41: Pcs | L41: Pcs | M41: =IF(AND(H41<>"", J41<>""), H41-J41, IF(H41<>"", H41-I41*VLOOKUP(A41, BACKEND2!$A:$G,6,FALSE), IF(J41<>"", -J41+K41*VLOOKUP(A41, BACKEND2!$A:$G,6,FALSE),0)))+ (C41+D41-E41)*VLOOKUP(A41, BACKEND2!$A:$G,5,FALSE)+G41 -> 0
A42: Other Kitchen & Food Supplies | C42: ='22ndMAY'!E42
A43: Condiments | C43: ='22ndMAY'!E43
A44: Bread Loaf | B44: Loaf | C44: ='22ndMAY'!E44 | F44: kg | H44: ='22ndMAY'!J44 -> 1.5 | I44: 1 | L44: kg | M44: =IF(AND(H44<>"", J44<>""), H44-J44, IF(H44<>"", H44-I44*VLOOKUP(A44, BACKEND1!$A:$G,6,FALSE), IF(J44<>"", -J44+K44*VLOOKUP(A44, BACKEND1!$A:$G,6,FALSE),0)))+ (C44+D44-E44)*VLOOKUP(A44, BACKEND1!$A:$G,5,FALSE)+G44 -> 1.5
A45: Burger Buns | B45: Pcs | C45: ='22ndMAY'!E45 | F45: Pcs | H45: ='22ndMAY'!J45 -> 15 | I45: 1 | L45: Pcs | M45: =IF(AND(H45<>"", J45<>""), H45-J45, IF(H45<>"", H45-I45*VLOOKUP(A45, BACKEND1!$A:$G,6,FALSE), IF(J45<>"", -J45+K45*VLOOKUP(A45, BACKEND1!$A:$G,6,FALSE),0)))+ (C45+D45-E45)*VLOOKUP(A45, BACKEND1!$A:$G,5,FALSE)+G45 -> 15
A46: Slider Buns | B46: Pcs | C46: ='22ndMAY'!E46 | F46: Pcs | H46: ='22ndMAY'!J46 -> 11 | I46: 1 | L46: Pcs | M46: =IF(AND(H46<>"", J46<>""), H46-J46, IF(H46<>"", H46-I46*VLOOKUP(A46, BACKEND1!$A:$G,6,FALSE), IF(J46<>"", -J46+K46*VLOOKUP(A46, BACKEND1!$A:$G,6,FALSE),0)))+ (C46+D46-E46)*VLOOKUP(A46, BACKEND1!$A:$G,5,FALSE)+G46 -> 11
A47: Soup Buns | B47: Pcs | C47: ='22ndMAY'!E47 | F47: Pcs | H47: ='22ndMAY'!J47 -> 6 | I47: 1 | L47: Pcs | M47: =IF(AND(H47<>"", J47<>""), H47-J47, IF(H47<>"", H47-I47*VLOOKUP(A47, BACKEND1!$A:$G,6,FALSE), IF(J47<>"", -J47+K47*VLOOKUP(A47, BACKEND1!$A:$G,6,FALSE),0)))+ (C47+D47-E47)*VLOOKUP(A47, BACKEND1!$A:$G,5,FALSE)+G47 -> 6
A48: Baguette Bread | B48: Pcs | C48: ='22ndMAY'!E48 | F48: Pcs | H48: ='22ndMAY'!J48 -> 4 | I48: 1 | L48: Pcs | M48: =IF(AND(H48<>"", J48<>""), H48-J48, IF(H48<>"", H48-I48*VLOOKUP(A48, BACKEND1!$A:$G,6,FALSE), IF(J48<>"", -J48+K48*VLOOKUP(A48, BACKEND1!$A:$G,6,FALSE),0)))+ (C48+D48-E48)*VLOOKUP(A48, BACKEND1!$A:$G,5,FALSE)+G48 -> 4
A49: Foccacia Bread | B49: Pcs | C49: ='22ndMAY'!E49 | F49: Pcs | H49: ='22ndMAY'!J49 | I49: 1 | L49: Pcs | M49: =IF(AND(H49<>"", J49<>""), H49-J49, IF(H49<>"", H49-I49*VLOOKUP(A49, BACKEND1!$A:$G,6,FALSE), IF(J49<>"", -J49+K49*VLOOKUP(A49, BACKEND1!$A:$G,6,FALSE),0)))+ (C49+D49-E49)*VLOOKUP(A49, BACKEND1!$A:$G,5,FALSE)+G49 -> 0
A50: White vinegar | B50: Bottles | C50: ='22ndMAY'!E50 | F50: Liters | H50: ='22ndMAY'!J50 -> 0.51 | I50: 1 | L50: Liters | M50: =IF(AND(H50<>"", J50<>""), H50-J50, IF(H50<>"", H50-I50*VLOOKUP(A50, BACKEND1!$A:$G,6,FALSE), IF(J50<>"", -J50+K50*VLOOKUP(A50, BACKEND1!$A:$G,6,FALSE),0)))+ (C50+D50-E50)*VLOOKUP(A50, BACKEND1!$A:$G,5,FALSE)+G50 -> 0.504
A51: Heinz ketchup bottles | B51: Bottles | C51: ='22ndMAY'!E51 | F51: Bottles | H51: ='22ndMAY'!J51 | I51: 1 | L51: Bottles | M51: =IF(AND(H51<>"", J51<>""), H51-J51, IF(H51<>"", H51-I51*VLOOKUP(A51, BACKEND1!$A:$G,6,FALSE), IF(J51<>"", -J51+K51*VLOOKUP(A51, BACKEND1!$A:$G,6,FALSE),0)))+ (C51+D51-E51)*VLOOKUP(A51, BACKEND1!$A:$G,5,FALSE)+G51 -> 0
A52: Apple cider vinegar | B52: Pcs | C52: ='22ndMAY'!E52 | F52: kg | H52: ='22ndMAY'!J52 -> 0.485 | I52: 1 | L52: kg | M52: =IF(AND(H52<>"", J52<>""), H52-J52, IF(H52<>"", H52-I52*VLOOKUP(A52, BACKEND1!$A:$G,6,FALSE), IF(J52<>"", -J52+K52*VLOOKUP(A52, BACKEND1!$A:$G,6,FALSE),0)))+ (C52+D52-E52)*VLOOKUP(A52, BACKEND1!$A:$G,5,FALSE)+G52 -> 0.448
A53: Balsamic Vinegar | B53: Bottles | C53: ='22ndMAY'!E53 | F53: Kg | H53: ='22ndMAY'!J53 -> 0.713 | I53: 1 | L53: Kg | M53: =IF(AND(H53<>"", J53<>""), H53-J53, IF(H53<>"", H53-I53*VLOOKUP(A53, BACKEND1!$A:$G,6,FALSE), IF(J53<>"", -J53+K53*VLOOKUP(A53, BACKEND1!$A:$G,6,FALSE),0)))+ (C53+D53-E53)*VLOOKUP(A53, BACKEND1!$A:$G,5,FALSE)+G53 -> 0.313
A54: Tomato paste | B54: Tins | C54: ='22ndMAY'!E54 | F54: Kg | H54: ='22ndMAY'!J54 -> 0.278 | I54: 1 | L54: Kg | M54: =IF(AND(H54<>"", J54<>""), H54-J54, IF(H54<>"", H54-I54*VLOOKUP(A54, BACKEND1!$A:$G,6,FALSE), IF(J54<>"", -J54+K54*VLOOKUP(A54, BACKEND1!$A:$G,6,FALSE),0)))+ (C54+D54-E54)*VLOOKUP(A54, BACKEND1!$A:$G,5,FALSE)+G54 -> 0.215
A55: Tabasco | B55: Pcs | C55: ='22ndMAY'!E55 | F55: Kgs | H55: ='22ndMAY'!J55 | I55: 1 | L55: Kgs | M55: =IF(AND(H55<>"", J55<>""), H55-J55, IF(H55<>"", H55-I55*VLOOKUP(A55, BACKEND1!$A:$G,6,FALSE), IF(J55<>"", -J55+K55*VLOOKUP(A55, BACKEND1!$A:$G,6,FALSE),0)))+ (C55+D55-E55)*VLOOKUP(A55, BACKEND1!$A:$G,5,FALSE)+G55 -> 0
... A64: Ketchup 5L | B64: Jerrycan | C64: ='22ndMAY'!E64 | F64: kg | H64: ='22ndMAY'!J64 -> 3.771 | I64: 1 | L64: kg | M64: =IF(AND(H64<>"", J64<>""), H64-J64, IF(H64<>"", H64-I64*VLOOKUP(A64, BACKEND1!$A:$G,6,FALSE), IF(J64<>"", -J64+K64*VLOOKUP(A64, BACKEND1!$A:$G,6,FALSE),0)))+ (C64+D64-E64)*VLOOKUP(A64, BACKEND1!$A:$G,5,FALSE)+G64 -> 3.471
A65: Dry Foods | C65: ='22ndMAY'!E65 | H65: ='22ndMAY'!J65 | I65: 1 | M65: =IF(AND(H65<>"", J65<>""), H65-J65, IF(H65<>"", H65-I65*VLOOKUP(A65, BACKEND1!$A:$G,6,FALSE), IF(J65<>"", -J65+K65*VLOOKUP(A65, BACKEND1!$A:$G,6,FALSE),0)))+ (C65+D65-E65)*VLOOKUP(A65, BACKEND1!$A:$G,5,FALSE)+G65 -> 0
A66: Baking flour | B66: Pkts | C66: ='22ndMAY'!E66 -> 1 | F66: Kg | H66: ='22ndMAY'!J66 | I66: 1 | L66: Kg | M66: =IF(AND(H66<>"", J66<>""), H66-J66, IF(H66<>"", H66-I66*VLOOKUP(A66, BACKEND1!$A:$G,6,FALSE), IF(J66<>"", -J66+K66*VLOOKUP(A66, BACKEND1!$A:$G,6,FALSE),0)))+ (C66+D66-E66)*VLOOKUP(A66, BACKEND1!$A:$G,5,FALSE)+G66 -> 2
A67: Baking Powder | B67: Pkts | C67: ='22ndMAY'!E67 -> 1 | F67: Kg | H67: ='22ndMAY'!J67 -> 0.093 | I67: 1 | L67: Kg | M67: =IF(AND(H67<>"", J67<>""), H67-J67, IF(H67<>"", H67-I67*VLOOKUP(A67, BACKEND1!$A:$G,6,FALSE), IF(J67<>"", -J67+K67*VLOOKUP(A67, BACKEND1!$A:$G,6,FALSE),0)))+ (C67+D67-E67)*VLOOKUP(A67, BACKEND1!$A:$G,5,FALSE)+G67 -> 0.183
A68: Basmati rice | B68: Kg | C68: ='22ndMAY'!E68 | F68: Kg | H68: ='22ndMAY'!J68 | I68: 1 | L68: Kg | M68: =IF(AND(H68<>"", J68<>""), H68-J68, IF(H68<>"", H68-I68*VLOOKUP(A68, BACKEND1!$A:$G,6,FALSE), IF(J68<>"", -J68+K68*VLOOKUP(A68, BACKEND1!$A:$G,6,FALSE),0)))+ (C68+D68-E68)*VLOOKUP(A68, BACKEND1!$A:$G,5,FALSE)+G68 -> 0
A69: Corn flour | B69: Pkts | C69: ='22ndMAY'!E69 | F69: Kg | H69: ='22ndMAY'!J69 -> 0.23 | I69: 1 | L69: Kg | M69: =IF(AND(H69<>"", J69<>""), H69-J69, IF(H69<>"", H69-I69*VLOOKUP(A69, BACKEND1!$A:$G,6,FALSE), IF(J69<>"", -J69+K69*VLOOKUP(A69, BACKEND1!$A:$G,6,FALSE),0)))+ (C69+D69-E69)*VLOOKUP(A69, BACKEND1!$A:$G,5,FALSE)+G69 -> 0.18
A70: Oils, Fats & Creams | C70: ='22ndMAY'!E70 | H70: ='22ndMAY'!J70 | I70: 1 | M70: =IF(AND(H70<>"", J70<>""), H70-J70, IF(H70<>"", H70-I70*VLOOKUP(A70, BACKEND1!$A:$G,6,FALSE), IF(J70<>"", -J70+K70*VLOOKUP(A70, BACKEND1!$A:$G,6,FALSE),0)))+ (C70+D70-E70)*VLOOKUP(A70, BACKEND1!$A:$G,5,FALSE)+G70 -> 0
A71: Cooking oil 20L | B71: Jerrycan | C71: ='22ndMAY'!E71 | F71: Liters | H71: ='22ndMAY'!J71 -> 0.311 | I71: 1 | L71: Liters | M71: =IF(AND(H71<>"", J71<>""), H71-J71, IF(H71<>"", H71-I71*VLOOKUP(A71, BACKEND1!$A:$G,6,FALSE), IF(J71<>"", -J71+K71*VLOOKUP(A71, BACKEND1!$A:$G,6,FALSE),0)))+ (C71+D71-E71)*VLOOKUP(A71, BACKEND1!$A:$G,5,FALSE)+G71 -> -0.499
A72: Croma Butter | B72: Kg | C72: ='22ndMAY'!E72 | F72: Kg | H72: ='22ndMAY'!J72 -> 0.56 | I72: 1 | L72: Kg | M72: =IF(AND(H72<>"", J72<>""), H72-J72, IF(H72<>"", H72-I72*VLOOKUP(A72, BACKEND1!$A:$G,6,FALSE), IF(J72<>"", -J72+K72*VLOOKUP(A72, BACKEND1!$A:$G,6,FALSE),0)))+ (C72+D72-E72)*VLOOKUP(A72, BACKEND1!$A:$G,5,FALSE)+G72 -> 0.56
A73: Prestige | B73: Kg | C73: ='22ndMAY'!E73 | F73: Kg | H73: ='22ndMAY'!J73 -> 0.56 | I73: 1 | L73: Kg | M73: =IF(AND(H73<>"", J73<>""), H73-J73, IF(H73<>"", H73-I73*VLOOKUP(A73, BACKEND1!$A:$G,6,FALSE), IF(J73<>"", -J73+K73*VLOOKUP(A73, BACKEND1!$A:$G,6,FALSE),0)))+ (C73+D73-E73)*VLOOKUP(A73, BACKEND1!$A:$G,5,FALSE)+G73 -> 0.56
A74: Cooking cream | B74: Packs | C74: ='22ndMAY'!E74 | F74: Liters | H74: ='22ndMAY'!J74 | I74: 1 | L74: Liters | M74: =IF(AND(H74<>"", J74<>""), H74-J74, IF(H74<>"", H74-I74*VLOOKUP(A74, BACKEND1!$A:$G,6,FALSE), IF(J74<>"", -J74+K74*VLOOKUP(A74, BACKEND1!$A:$G,6,FALSE),0)))+ (C74+D74-E74)*VLOOKUP(A74, BACKEND1!$A:$G,5,FALSE)+G74 -> 0
A75: Sunseed Oil 5L | B75: Pcs | C75: ='22ndMAY'!E75 | F75: Liters | H75: ='22ndMAY'!J75 -> 0.781 | I75: 1 | L75: Liters | M75: =IF(AND(H75<>"", J75<>""), H75-J75, IF(H75<>"", H75-I75*VLOOKUP(A75, BACKEND1!$A:$G,6,FALSE), IF(J75<>"", -J75+K75*VLOOKUP(A75, BACKEND1!$A:$G,6,FALSE),0)))+ (C75+D75-E75)*VLOOKUP(A75, BACKEND1!$A:$G,5,FALSE)+G75 -> 0.601
A76: Whipping cream | B76: Packs | C76: ='22ndMAY'!E76 | F76: Kg | H76: ='22ndMAY'!J76 -> 1 | I76: 1 | L76: Kg | M76: =IF(AND(H76<>"", J76<>""), H76-J76, IF(H76<>"", H76-I76*VLOOKUP(A76, BACKEND1!$A:$G,6,FALSE), IF(J76<>"", -J76+K76*VLOOKUP(A76, BACKEND1!$A:$G,6,FALSE),0)))+ (C76+D76-E76)*VLOOKUP(A76, BACKEND1!$A:$G,5,FALSE)+G76 -> 0.938
A77: Olive Oil | B77: Can | C77: ='22ndMAY'!E77 | F77: Liters | H77: ='22ndMAY'!J77 -> 0.742 | I77: 1 | L77: Liters | M77: =IF(AND(H77<>"", J77<>""), H77-J77, IF(H77<>"", H77-I77*VLOOKUP(A77, BACKEND1!$A:$G,6,FALSE), IF(J77<>"", -J77+K77*VLOOKUP(A77, BACKEND1!$A:$G,6,FALSE),0)))+ (C77+D77-E77)*VLOOKUP(A77, BACKEND1!$A:$G,5,FALSE)+G77 -> 0.662
A78: Coconut Oil | B78: Jerrycan | C78: ='22ndMAY'!E78 | F78: Kg | H78: ='22ndMAY'!J78 | I78: 1 | L78: Kg | M78: =IF(AND(H78<>"", J78<>""), H78-J78, IF(H78<>"", H78-I78*VLOOKUP(A78, BACKEND1!$A:$G,6,FALSE), IF(J78<>"", -J78+K78*VLOOKUP(A78, BACKEND1!$A:$G,6,FALSE),0)))+ (C78+D78-E78)*VLOOKUP(A78, BACKEND1!$A:$G,5,FALSE)+G78 -> 0
A79: Seseame Oil | B79: Bottle | C79: ='22ndMAY'!E79 | F79: Kg | H79: ='22ndMAY'!J79 -> 1 | I79: 1 | L79: Kg | M79: =IF(AND(H79<>"", J79<>""), H79-J79, IF(H79<>"", H79-I79*VLOOKUP(A79, BACKEND1!$A:$G,6,FALSE), IF(J79<>"", -J79+K79*VLOOKUP(A79, BACKEND1!$A:$G,6,FALSE),0)))+ (C79+D79-E79)*VLOOKUP(A79, BACKEND1!$A:$G,5,FALSE)+G79 -> 0.82
A80: Sauces | C80: ='22ndMAY'!E80 | H80: ='22ndMAY'!J80 | I80: 1 | M80: =IF(AND(H80<>"", J80<>""), H80-J80, IF(H80<>"", H80-I80*VLOOKUP(A80, BACKEND1!$A:$G,6,FALSE), IF(J80<>"", -J80+K80*VLOOKUP(A80, BACKEND1!$A:$G,6,FALSE),0)))+ (C80+D80-E80)*VLOOKUP(A80, BACKEND1!$A:$G,5,FALSE)+G80 -> 0
A81: Light soy sauce | B81: Bottle | C81: ='22ndMAY'!E81 | F81: Liters | H81: ='22ndMAY'!J81 | I81: 1 | L81: Liters | M81: =IF(AND(H81<>"", J81<>""), H81-J81, IF(H81<>"", H81-I81*VLOOKUP(A81, BACKEND1!$A:$G,6,FALSE), IF(J81<>"", -J81+K81*VLOOKUP(A81, BACKEND1!$A:$G,6,FALSE),0)))+ (C81+D81-E81)*VLOOKUP(A81, BACKEND1!$A:$G,5,FALSE)+G81 -> 0
A82: Dark soy sauce | B82: Bottle | C82: ='22ndMAY'!E82 -> 1 | F82: Liters | H82: ='22ndMAY'!J82 -> 0.143 | I82: 1 | L82: Liters | M82: =IF(AND(H82<>"", J82<>""), H82-J82, IF(H82<>"", H82-I82*VLOOKUP(A82, BACKEND1!$A:$G,6,FALSE), IF(J82<>"", -J82+K82*VLOOKUP(A82, BACKEND1!$A:$G,6,FALSE),0)))+ (C82+D82-E82)*VLOOKUP(A82, BACKEND1!$A:$G,5,FALSE)+G82 -> 0.166
A83: Sweet chilli sauce | B83: Bottle | C83: ='22ndMAY'!E83 | F83: Liters | H83: ='22ndMAY'!J83 -> 0.734 | I83: 1 | L83: Liters | M83: =IF(AND(H83<>"", J83<>""), H83-J83, IF(H83<>"", H83-I83*VLOOKUP(A83, BACKEND1!$A:$G,6,FALSE), IF(J83<>"", -J83+K83*VLOOKUP(A83, BACKEND1!$A:$G,6,FALSE),0)))+ (C83+D83-E83)*VLOOKUP(A83, BACKEND1!$A:$G,5,FALSE)+G83 -> 0.234
A84: Oyster sauce | B84: Bottle | C84: ='22ndMAY'!E84 | F84: Liters | H84: ='22ndMAY'!J84 -> 0.667 | I84: 1 | L84: Liters | M84: =IF(AND(H84<>"", J84<>""), H84-J84, IF(H84<>"", H84-I84*VLOOKUP(A84, BACKEND1!$A:$G,6,FALSE), IF(J84<>"", -J84+K84*VLOOKUP(A84, BACKEND1!$A:$G,6,FALSE),0)))+ (C84+D84-E84)*VLOOKUP(A84, BACKEND1!$A:$G,5,FALSE)+G84 -> 0.374
A85: Worcestershire sauce | B85: Bottles | C85: ='22ndMAY'!E85 | F85: Liters | H85: ='22ndMAY'!J85 -> 0.288 | I85: 1 | L85: Liters | M85: =IF(AND(H85<>"", J85<>""), H85-J85, IF(H85<>"", H85-I85*VLOOKUP(A85, BACKEND1!$A:$G,6,FALSE), IF(J85<>"", -J85+K85*VLOOKUP(A85, BACKEND1!$A:$G,6,FALSE),0)))+ (C85+D85-E85)*VLOOKUP(A85, BACKEND1!$A:$G,5,FALSE)+G85 -> 0.226
A86: Top up sauce | B86: Jerrycan | C86: ='22ndMAY'!E86 | F86: Liters | H86: ='22ndMAY'!J86 -> 2.824 | I86: 1 | L86: Liters | M86: =IF(AND(H86<>"", J86<>""), H86-J86, IF(H86<>"", H86-I86*VLOOKUP(A86, BACKEND1!$A:$G,6,FALSE), IF(J86<>"", -J86+K86*VLOOKUP(A86, BACKEND1!$A:$G,6,FALSE),0)))+ (C86+D86-E86)*VLOOKUP(A86, BACKEND1!$A:$G,5,FALSE)+G86 -> 2.704
A87: Fish Sauce | B87: Bottle | C87: ='22ndMAY'!E87 | F87: Liters | H87: ='22ndMAY'!J87 -> 0.751 | I87: 1 | L87: Liters | M87: =IF(AND(H87<>"", J87<>""), H87-J87, IF(H87<>"", H87-I87*VLOOKUP(A87, BACKEND1!$A:$G,6,FALSE), IF(J87<>"", -J87+K87*VLOOKUP(A87, BACKEND1!$A:$G,6,FALSE),0)))+ (C87+D87-E87)*VLOOKUP(A87, BACKEND1!$A:$G,5,FALSE)+G87 -> 0.051
A88: Red Wine | B88: Bottle | C88: ='22ndMAY'!E88 | F88: Liters | H88: ='22ndMAY'!J88 -> 0.661 | I88: 1 | L88: Liters | M88: =IF(AND(H88<>"", J88<>""), H88-J88, IF(H88<>"", H88-I88*VLOOKUP(A88, BACKEND1!$A:$G,6,FALSE), IF(J88<>"", -J88+K88*VLOOKUP(A88, BACKEND1!$A:$G,6,FALSE),0)))+ (C88+D88-E88)*VLOOKUP(A88, BACKEND1!$A:$G,5,FALSE)+G88 -> 0.241
A89: White Wine | B89: Bottle | C89: ='22ndMAY'!E89 | F89: Liters | H89: ='22ndMAY'!J89 -> 0.974 | I89: 1 | L89: Liters | M89: =IF(AND(H89<>"", J89<>""), H89-J89, IF(H89<>"", H89-I89*VLOOKUP(A89, BACKEND1!$A:$G,6,FALSE), IF(J89<>"", -J89+K89*VLOOKUP(A89, BACKEND1!$A:$G,6,FALSE),0)))+ (C89+D89-E89)*VLOOKUP(A89, BACKEND1!$A:$G,5,FALSE)+G89 -> 0.554
A90: Spices | C90: ='22ndMAY'!E90 | H90: ='22ndMAY'!J90 | I90: 1 | M90: =IF(AND(H90<>"", J90<>""), H90-J90, IF(H90<>"", H90-I90*VLOOKUP(A90, BACKEND1!$A:$G,6,FALSE), IF(J90<>"", -J90+K90*VLOOKUP(A90, BACKEND1!$A:$G,6,FALSE),0)))+ (C90+D90-E90)*VLOOKUP(A90, BACKEND1!$A:$G,5,FALSE)+G90 -> 0
A91: Turmeric | B91: Packet | C91: ='22ndMAY'!E91 | F91: Kg | H91: ='22ndMAY'!J91 | I91: 1 | L91: Kg | M91: =IF(AND(H91<>"", J91<>""), H91-J91, IF(H91<>"", H91-I91*VLOOKUP(A91, BACKEND1!$A:$G,6,FALSE), IF(J91<>"", -J91+K91*VLOOKUP(A91, BACKEND1!$A:$G,6,FALSE),0)))+ (C91+D91-E91)*VLOOKUP(A91, BACKEND1!$A:$G,5,FALSE)+G91 -> 0
A92: Paprika | B92: Packet | C92: ='22ndMAY'!E92 | F92: Kg | H92: ='22ndMAY'!J92 -> 0.698 | I92: 1 | L92: Kg | M92: =IF(AND(H92<>"", J92<>""), H92-J92, IF(H92<>"", H92-I92*VLOOKUP(A92, BACKEND1!$A:$G,6,FALSE), IF(J92<>"", -J92+K92*VLOOKUP(A92, BACKEND1!$A:$G,6,FALSE),0)))+ (C92+D92-E92)*VLOOKUP(A92, BACKEND1!$A:$G,5,FALSE)+G92 -> 0.692
A93: Origano | B93: Packet | C93: ='22ndMAY'!E93 | F93: Kg | H93: ='22ndMAY'!J93 -> 0.125 | I93: 1 | L93: Kg | M93: =IF(AND(H93<>"", J93<>""), H93-J93, IF(H93<>"", H93-I93*VLOOKUP(A93, BACKEND1!$A:$G,6,FALSE), IF(J93<>"", -J93+K93*VLOOKUP(A93, BACKEND1!$A:$G,6,FALSE),0)))+ (C93+D93-E93)*VLOOKUP(A93, BACKEND1!$A:$G,5,FALSE)+G93 -> 0.108
A94: Curry powder | B94: Packet | C94: ='22ndMAY'!E94 | F94: Kg | H94: ='22ndMAY'!J94 | I94: 1 | L94: Kg | M94: =IF(AND(H94<>"", J94<>""), H94-J94, IF(H94<>"", H94-I94*VLOOKUP(A94, BACKEND1!$A:$G,6,FALSE), IF(J94<>"", -J94+K94*VLOOKUP(A94, BACKEND1!$A:$G,6,FALSE),0)))+ (C94+D94-E94)*VLOOKUP(A94, BACKEND1!$A:$G,5,FALSE)+G94 -> 0
A95: Black pepper powder | B95: Packet | C95: ='22ndMAY'!E95 | F95: Kg | H95: ='22ndMAY'!J95 | I95: 1 | L95: Kg | M95: =IF(AND(H95<>"", J95<>""), H95-J95, IF(H95<>"", H95-I95*VLOOKUP(A95, BACKEND1!$A:$G,6,FALSE), IF(J95<>"", -J95+K95*VLOOKUP(A95, BACKEND1!$A:$G,6,FALSE),0)))+ (C95+D95-E95)*VLOOKUP(A95, BACKEND1!$A:$G,5,FALSE)+G95 -> 0
A96: Black pepper Seeds | B96: Packet | C96: ='22ndMAY'!E96 | F96: Kg | H96: ='22ndMAY'!J96 -> 0.303 | I96: 1 | L96: Kg | M96: =IF(AND(H96<>"", J96<>""), H96-J96, IF(H96<>"", H96-I96*VLOOKUP(A96, BACKEND1!$A:$G,6,FALSE), IF(J96<>"", -J96+K96*VLOOKUP(A96, BACKEND1!$A:$G,6,FALSE),0)))+ (C96+D96-E96)*VLOOKUP(A96, BACKEND1!$A:$G,5,FALSE)+G96 -> 0.299
A97: Cumin seeds | B97: Packet | C97: ='22ndMAY'!E97 | F97: Kg | H97: ='22ndMAY'!J97 | I97: 1 | L97: Kg | M97: =IF(AND(H97<>"", J97<>""), H97-J97, IF(H97<>"", H97-I97*VLOOKUP(A97, BACKEND1!$A:$G,6,FALSE), IF(J97<>"", -J97+K97*VLOOKUP(A97, BACKEND1!$A:$G,6,FALSE),0)))+ (C97+D97-E97)*VLOOKUP(A97, BACKEND1!$A:$G,5,FALSE)+G97 -> 0
A98: Simba mbili | B98: Tin | C98: ='22ndMAY'!E98 | F98: Kg | H98: ='22ndMAY'!J98 -> 0.273 | I98: 1 | L98: Kg | M98: =IF(AND(H98<>"", J98<>""), H98-J98, IF(H98<>"", H98-I98*VLOOKUP(A98, BACKEND1!$A:$G,6,FALSE), IF(J98<>"", -J98+K98*VLOOKUP(A98, BACKEND1!$A:$G,6,FALSE),0)))+ (C98+D98-E98)*VLOOKUP(A98, BACKEND1!$A:$G,5,FALSE)+G98 -> 0.166
A99: Cinnamon powder | B99: Packet | C99: ='22ndMAY'!E99 | F99: Kg | H99: ='22ndMAY'!J99 -> 0.218 | I99: 1 | L99: Kg | M99: =IF(AND(H99<>"", J99<>""), H99-J99, IF(H99<>"", H99-I99*VLOOKUP(A99, BACKEND1!$A:$G,6,FALSE), IF(J99<>"", -J99+K99*VLOOKUP(A99, BACKEND1!$A:$G,6,FALSE),0)))+ (C99+D99-E99)*VLOOKUP(A99, BACKEND1!$A:$G,5,FALSE)+G99 -> 0.214
A100: Ground cloves | B100: Packet | C100: ='22ndMAY'!E100 | F100: Kg | H100: ='22ndMAY'!J100 -> 0.233 | I100: 1 | L100: Kg | M100: =IF(AND(H100<>"", J100<>""), H100-J100, IF(H100<>"", H100-I100*VLOOKUP(A100, BACKEND1!$A:$G,6,FALSE), IF(J100<>"", -J100+K100*VLOOKUP(A100, BACKEND1!$A:$G,6,FALSE),0)))+ (C100+D100-E100)*VLOOKUP(A100, BACKEND1!$A:$G,5,FALSE)+G100 -> 0.222
A101: Pilau masala | B101: Packet | C101: ='22ndMAY'!E101 | F101: Kg | H101: ='22ndMAY'!J101 -> 0.505 | I101: 1 | L101: Kg | M101: =IF(AND(H101<>"", J101<>""), H101-J101, IF(H101<>"", H101-I101*VLOOKUP(A101, BACKEND1!$A:$G,6,FALSE), IF(J101<>"", -J101+K101*VLOOKUP(A101, BACKEND1!$A:$G,6,FALSE),0)))+ (C101+D101-E101)*VLOOKUP(A101, BACKEND1!$A:$G,5,FALSE)+G101 -> 0.499
A102: Cocoa powder | B102: Packet | C102: ='22ndMAY'!E102 | F102: Kg | H102: ='22ndMAY'!J102 | I102: 1 | L102: Kg | M102: =IF(AND(H102<>"", J102<>""), H102-J102, IF(H102<>"", H102-I102*VLOOKUP(A102, BACKEND1!$A:$G,6,FALSE), IF(J102<>"", -J102+K102*VLOOKUP(A102, BACKEND1!$A:$G,6,FALSE),0)))+ (C102+D102-E102)*VLOOKUP(A102, BACKEND1!$A:$G,5,FALSE)+G102 -> 0
... A126: Chilli Powder | B126: Packet | C126: ='22ndMAY'!E126 | F126: Kg | H126: ='22ndMAY'!J126 -> 0.222 | I126: 1 | L126: Kg | M126: =IF(AND(H126<>"", J126<>""), H126-J126, IF(H126<>"", H126-I126*VLOOKUP(A126, BACKEND1!$A:$G,6,FALSE), IF(J126<>"", -J126+K126*VLOOKUP(A126, BACKEND1!$A:$G,6,FALSE),0)))+ (C126+D126-E126)*VLOOKUP(A126, BACKEND1!$A:$G,5,FALSE)+G126 -> 0.202
A127: Sweeteners | C127: ='22ndMAY'!E127 | H127: ='22ndMAY'!J127 | I127: 1 | M127: =IF(AND(H127<>"", J127<>""), H127-J127, IF(H127<>"", H127-I127*VLOOKUP(A127, BACKEND1!$A:$G,6,FALSE), IF(J127<>"", -J127+K127*VLOOKUP(A127, BACKEND1!$A:$G,6,FALSE),0)))+ (C127+D127-E127)*VLOOKUP(A127, BACKEND1!$A:$G,5,FALSE)+G127 -> 0
A128: Brown sugar | B128: Packet | C128: ='22ndMAY'!E128 | F128: Kg | H128: ='22ndMAY'!J128 | I128: 1 | L128: Kg | M128: =IF(AND(H128<>"", J128<>""), H128-J128, IF(H128<>"", H128-I128*VLOOKUP(A128, BACKEND1!$A:$G,6,FALSE), IF(J128<>"", -J128+K128*VLOOKUP(A128, BACKEND1!$A:$G,6,FALSE),0)))+ (C128+D128-E128)*VLOOKUP(A128, BACKEND1!$A:$G,5,FALSE)+G128 -> 0
A129: Sugar | B129: Kg | C129: ='22ndMAY'!E129 | F129: Kg | H129: ='22ndMAY'!J129 -> 1.143 | I129: 1 | L129: Kg | M129: =IF(AND(H129<>"", J129<>""), H129-J129, IF(H129<>"", H129-I129*VLOOKUP(A129, BACKEND1!$A:$G,6,FALSE), IF(J129<>"", -J129+K129*VLOOKUP(A129, BACKEND1!$A:$G,6,FALSE),0)))+ (C129+D129-E129)*VLOOKUP(A129, BACKEND1!$A:$G,5,FALSE)+G129 -> 1.143
A130: Icing sugar | B130: Packet | C130: ='22ndMAY'!E130 | F130: Kg | H130: ='22ndMAY'!J130 -> 0.232 | I130: 1 | L130: Kg | M130: =IF(AND(H130<>"", J130<>""), H130-J130, IF(H130<>"", H130-I130*VLOOKUP(A130, BACKEND1!$A:$G,6,FALSE), IF(J130<>"", -J130+K130*VLOOKUP(A130, BACKEND1!$A:$G,6,FALSE),0)))+ (C130+D130-E130)*VLOOKUP(A130, BACKEND1!$A:$G,5,FALSE)+G130 -> 0.132
A131: Bbq sauce | B131: Bottles | C131: ='22ndMAY'!E131 | F131: Liters | H131: ='22ndMAY'!J131 | I131: 1 | L131: Liters | M131: =IF(AND(H131<>"", J131<>""), H131-J131, IF(H131<>"", H131-I131*VLOOKUP(A131, BACKEND1!$A:$G,6,FALSE), IF(J131<>"", -J131+K131*VLOOKUP(A131, BACKEND1!$A:$G,6,FALSE),0)))+ (C131+D131-E131)*VLOOKUP(A131, BACKEND1!$A:$G,5,FALSE)+G131 -> 0
A132: Canned goods | C132: ='22ndMAY'!E132 | H132: ='22ndMAY'!J132 | I132: 1 | M132: =IF(AND(H132<>"", J132<>""), H132-J132, IF(H132<>"", H132-I132*VLOOKUP(A132, BACKEND1!$A:$G,6,FALSE), IF(J132<>"", -J132+K132*VLOOKUP(A132, BACKEND1!$A:$G,6,FALSE),0)))+ (C132+D132-E132)*VLOOKUP(A132, BACKEND1!$A:$G,5,FALSE)+G132 -> 0
A133: Aromat | B133: Tin | C133: ='22ndMAY'!E133 | F133: Kg | H133: ='22ndMAY'!J133 -> 0.096 | I133: 1 | L133: Kg | M133: =IF(AND(H133<>"", J133<>""), H133-J133, IF(H133<>"", H133-I133*VLOOKUP(A133, BACKEND1!$A:$G,6,FALSE), IF(J133<>"", -J133+K133*VLOOKUP(A133, BACKEND1!$A:$G,6,FALSE),0)))+ (C133+D133-E133)*VLOOKUP(A133, BACKEND1!$A:$G,5,FALSE)+G133 -> 0.06
A134: Salt | B134: Pkt | C134: ='22ndMAY'!E134 | F134: Kg | H134: ='22ndMAY'!J134 | I134: 1 | L134: Kg | M134: =IF(AND(H134<>"", J134<>""), H134-J134, IF(H134<>"", H134-I134*VLOOKUP(A134, BACKEND1!$A:$G,6,FALSE), IF(J134<>"", -J134+K134*VLOOKUP(A134, BACKEND1!$A:$G,6,FALSE),0)))+ (C134+D134-E134)*VLOOKUP(A134, BACKEND1!$A:$G,5,FALSE)+G134 -> 0
A135: Sweet corn | B135: Tins | C135: ='22ndMAY'!E135 -> 1 | F135: Kg | H135: ='22ndMAY'!J135 -> 0.352 | I135: 1 | L135: Kg | M135: =IF(AND(H135<>"", J135<>""), H135-J135, IF(H135<>"", H135-I135*VLOOKUP(A135, BACKEND1!$A:$G,6,FALSE), IF(J135<>"", -J135+K135*VLOOKUP(A135, BACKEND1!$A:$G,6,FALSE),0)))+ (C135+D135-E135)*VLOOKUP(A135, BACKEND1!$A:$G,5,FALSE)+G135 -> 0.722
A136: Coconut Milk | B136: Tins | C136: ='22ndMAY'!E136 | F136: Kg | H136: ='22ndMAY'!J136 -> 0.28 | I136: 1 | L136: Kg | M136: =IF(AND(H136<>"", J136<>""), H136-J136, IF(H136<>"", H136-I136*VLOOKUP(A136, BACKEND1!$A:$G,6,FALSE), IF(J136<>"", -J136+K136*VLOOKUP(A136, BACKEND1!$A:$G,6,FALSE),0)))+ (C136+D136-E136)*VLOOKUP(A136, BACKEND1!$A:$G,5,FALSE)+G136 -> 0.224
A137: Peanut butter | B137: Tins | C137: ='22ndMAY'!E137 | F137: Kg | H137: ='22ndMAY'!J137 | I137: 1 | L137: Kg | M137: =IF(AND(H137<>"", J137<>""), H137-J137, IF(H137<>"", H137-I137*VLOOKUP(A137, BACKEND1!$A:$G,6,FALSE), IF(J137<>"", -J137+K137*VLOOKUP(A137, BACKEND1!$A:$G,6,FALSE),0)))+ (C137+D137-E137)*VLOOKUP(A137, BACKEND1!$A:$G,5,FALSE)+G137 -> 0
A138: Black olives | B138: Tins | C138: ='22ndMAY'!E138 | F138: Kg | H138: ='22ndMAY'!J138 -> 0.337 | I138: 1 | L138: Kg | M138: =IF(AND(H138<>"", J138<>""), H138-J138, IF(H138<>"", H138-I138*VLOOKUP(A138, BACKEND1!$A:$G,6,FALSE), IF(J138<>"", -J138+K138*VLOOKUP(A138, BACKEND1!$A:$G,6,FALSE),0)))+ (C138+D138-E138)*VLOOKUP(A138, BACKEND1!$A:$G,5,FALSE)+G138 -> 0.103
A139: Green olives | B139: Tins | C139: ='22ndMAY'!E139 | F139: Kg | H139: ='22ndMAY'!J139 -> 0.49 | I139: 1 | L139: Kg | M139: =IF(AND(H139<>"", J139<>""), H139-J139, IF(H139<>"", H139-I139*VLOOKUP(A139, BACKEND1!$A:$G,6,FALSE), IF(J139<>"", -J139+K139*VLOOKUP(A139, BACKEND1!$A:$G,6,FALSE),0)))+ (C139+D139-E139)*VLOOKUP(A139, BACKEND1!$A:$G,5,FALSE)+G139 -> 0.262
A140: Mushroom Tin | B140: Tins | C140: ='22ndMAY'!E140 | F140: Kg | H140: ='22ndMAY'!J140 -> 0.25 | I140: 1 | L140: Kg | M140: =IF(AND(H140<>"", J140<>""), H140-J140, IF(H140<>"", H140-I140*VLOOKUP(A140, BACKEND1!$A:$G,6,FALSE), IF(J140<>"", -J140+K140*VLOOKUP(A140, BACKEND1!$A:$G,6,FALSE),0)))+ (C140+D140-E140)*VLOOKUP(A140, BACKEND1!$A:$G,5,FALSE)+G140 -> 0.13
A141: Pickles | B141: Tins | C141: ='22ndMAY'!E141 | F141: Kg | H141: ='22ndMAY'!J141 -> 0.209 | I141: 1 | L141: Kg | M141: =IF(AND(H141<>"", J141<>""), H141-J141, IF(H141<>"", H141-I141*VLOOKUP(A141, BACKEND1!$A:$G,6,FALSE), IF(J141<>"", -J141+K141*VLOOKUP(A141, BACKEND1!$A:$G,6,FALSE),0)))+ (C141+D141-E141)*VLOOKUP(A141, BACKEND1!$A:$G,5,FALSE)+G141 -> -0.101
A142: Grapes | B142: Pkt | C142: ='22ndMAY'!E142 | F142: Kg | H142: ='22ndMAY'!J142 -> 0.198 | I142: 1 | L142: Kg | M142: =IF(AND(H142<>"", J142<>""), H142-J142, IF(H142<>"", H142-I142*VLOOKUP(A142, BACKEND1!$A:$G,6,FALSE), IF(J142<>"", -J142+K142*VLOOKUP(A142, BACKEND1!$A:$G,6,FALSE),0)))+ (C142+D142-E142)*VLOOKUP(A142, BACKEND1!$A:$G,5,FALSE)+G142 -> 0.094
A143: Dates | B143: Pkt | C143: ='22ndMAY'!E143 | F143: Kg | H143: ='22ndMAY'!J143 | I143: 1 | L143: Kg | M143: =IF(AND(H143<>"", J143<>""), H143-J143, IF(H143<>"", H143-I143*VLOOKUP(A143, BACKEND1!$A:$G,6,FALSE), IF(J143<>"", -J143+K143*VLOOKUP(A143, BACKEND1!$A:$G,6,FALSE),0)))+ (C143+D143-E143)*VLOOKUP(A143, BACKEND1!$A:$G,5,FALSE)+G143 -> 0
A144: Mayonnaise big tin | B144: Tin | C144: ='22ndMAY'!E144 | F144: Kg | H144: ='22ndMAY'!J144 | I144: 1 | L144: Kg | M144: =IF(AND(H144<>"", J144<>""), H144-J144, IF(H144<>"", H144-I144*VLOOKUP(A144, BACKEND1!$A:$G,6,FALSE), IF(J144<>"", -J144+K144*VLOOKUP(A144, BACKEND1!$A:$G,6,FALSE),0)))+ (C144+D144-E144)*VLOOKUP(A144, BACKEND1!$A:$G,5,FALSE)+G144 -> 0
... A151: Sprinkles | B151: Tin | C151: ='22ndMAY'!E151 | F151: kg | H151: ='22ndMAY'!J151 -> 0.321 | I151: 1 | L151: kg | M151: =IF(AND(H151<>"", J151<>""), H151-J151, IF(H151<>"", H151-I151*VLOOKUP(A151, BACKEND1!$A:$G,6,FALSE), IF(J151<>"", -J151+K151*VLOOKUP(A151, BACKEND1!$A:$G,6,FALSE),0)))+ (C151+D151-E151)*VLOOKUP(A151, BACKEND1!$A:$G,5,FALSE)+G151 -> 0.206
A152: Dairy | C152: ='22ndMAY'!E152 | H152: ='22ndMAY'!J152 | I152: 1 | M152: =IF(AND(H152<>"", J152<>""), H152-J152, IF(H152<>"", H152-I152*VLOOKUP(A152, BACKEND1!$A:$G,6,FALSE), IF(J152<>"", -J152+K152*VLOOKUP(A152, BACKEND1!$A:$G,6,FALSE),0)))+ (C152+D152-E152)*VLOOKUP(A152, BACKEND1!$A:$G,5,FALSE)+G152 -> 0
...

Sheet 22ndMAY
B2: WHOLE | F2: REMAINDER | L2: ACCOUNTABILITY
A3: Type | B3: U.O.M | C3: Opening | D3: Added | E3: Closing | F3: U.O.M | G3: Added | H3: Opening | I3: Units | J3: Closing | K3: Units | L3: U.O.M | M3: Used | N3: Transfer | O3: Damage
A4: Portioned Items: Meats & Others
A5: Carribean jerk | B5: Ptns | C5: ='19th-21stMAY'!E5 -> 26 | D5: 22 | E5: 38.02 | F5: Pcs | L5: Pcs | M5: =IF(AND(H5<>"", J5<>""), H5-J5, IF(H5<>"", H5-I5*VLOOKUP(A5, BACKEND2!$A:$G,6,FALSE), IF(J5<>"", -J5+K5*VLOOKUP(A5, BACKEND2!$A:$G,6,FALSE),0)))+ (C5+D5-E5)*VLOOKUP(A5, BACKEND2!$A:$G,5,FALSE)+G5 -> 29.94
A6: Chicken breast | B6: Ptns | C6: ='19th-21stMAY'!E6 -> 7 | E6: 6 | F6: Pcs | L6: Pcs | M6: =IF(AND(H6<>"", J6<>""), H6-J6, IF(H6<>"", H6-I6*VLOOKUP(A6, BACKEND2!$A:$G,6,FALSE), IF(J6<>"", -J6+K6*VLOOKUP(A6, BACKEND2!$A:$G,6,FALSE),0)))+ (C6+D6-E6)*VLOOKUP(A6, BACKEND2!$A:$G,5,FALSE)+G6 -> 2
A7: Chicken wings | B7: Ptns | C7: ='19th-21stMAY'!E7 -> 4 | D7: 7 | E7: 6 | F7: Pcs | L7: Pcs | M7: =IF(AND(H7<>"", J7<>""), H7-J7, IF(H7<>"", H7-I7*VLOOKUP(A7, BACKEND2!$A:$G,6,FALSE), IF(J7<>"", -J7+K7*VLOOKUP(A7, BACKEND2!$A:$G,6,FALSE),0)))+ (C7+D7-E7)*VLOOKUP(A7, BACKEND2!$A:$G,5,FALSE)+G7 -> 25
A8: Chicken burger | B8: Ptns | C8: ='19th-21stMAY'!E8 -> 13 | D8: 10 | E8: 18 | F8: Ptns | L8: Ptns | M8: =IF(AND(H8<>"", J8<>""), H8-J8, IF(H8<>"", H8-I8*VLOOKUP(A8, BACKEND2!$A:$G,6,FALSE), IF(J8<>"", -J8+K8*VLOOKUP(A8, BACKEND2!$A:$G,6,FALSE),0)))+ (C8+D8-E8)*VLOOKUP(A8, BACKEND2!$A:$G,5,FALSE)+G8 -> 5
A9: Min Chicken burger | B9: Ptns | C9: ='19th-21stMAY'!E9 | F9: Pcs | L9: Pcs | M9: =IF(AND(H9<>"", J9<>""), H9-J9, IF(H9<>"", H9-I9*VLOOKUP(A9, BACKEND2!$A:$G,6,FALSE), IF(J9<>"", -J9+K9*VLOOKUP(A9, BACKEND2!$A:$G,6,FALSE),0)))+ (C9+D9-E9)*VLOOKUP(A9, BACKEND2!$A:$G,5,FALSE)+G9 -> 0
A10: Chicken lollipos | B10: Ptns | C10: ='19th-21stMAY'!E10 -> 3 | D10: 4 | E10: 3 | F10: Pcs | L10: Pcs | M10: =IF(AND(H10<>"", J10<>""), H10-J10, IF(H10<>"", H10-I10*VLOOKUP(A10, BACKEND2!$A:$G,6,FALSE), IF(J10<>"", -J10+K10*VLOOKUP(A10, BACKEND2!$A:$G,6,FALSE),0)))+ (C10+D10-E10)*VLOOKUP(A10, BACKEND2!$A:$G,5,FALSE)+G10 -> 32
A11: Chicken pizza | B11: Ptns | C11: ='19th-21stMAY'!E11 -> 17 | D11: 10 | E11: 13 | F11: Ptns | L11: Ptns | M11: =IF(AND(H11<>"", J11<>""), H11-J11, IF(H11<>"", H11-I11*VLOOKUP(A11, BACKEND2!$A:$G,6,FALSE), IF(J11<>"", -J11+K11*VLOOKUP(A11, BACKEND2!$A:$G,6,FALSE),0)))+ (C11+D11-E11)*VLOOKUP(A11, BACKEND2!$A:$G,5,FALSE)+G11 -> 14
A12: Chicken Tenders | B12: Ptns | C12: ='19th-21stMAY'!E12 | F12: Ptns | L12: Ptns | M12: =IF(AND(H12<>"", J12<>""), H12-J12, IF(H12<>"", H12-I12*VLOOKUP(A12, BACKEND2!$A:$G,6,FALSE), IF(J12<>"", -J12+K12*VLOOKUP(A12, BACKEND2!$A:$G,6,FALSE),0)))+ (C12+D12-E12)*VLOOKUP(A12, BACKEND2!$A:$G,5,FALSE)+G12 -> 0
A13: Chicken skewers | B13: Ptns | C13: ='19th-21stMAY'!E13 -> 11 | E13: 8.5 | F13: Pcs | L13: Pcs | M13: =IF(AND(H13<>"", J13<>""), H13-J13, IF(H13<>"", H13-I13*VLOOKUP(A13, BACKEND2!$A:$G,6,FALSE), IF(J13<>"", -J13+K13*VLOOKUP(A13, BACKEND2!$A:$G,6,FALSE),0)))+ (C13+D13-E13)*VLOOKUP(A13, BACKEND2!$A:$G,5,FALSE)+G13 -> 22.5
A14: Chicken stroganoff | B14: Ptns | C14: ='19th-21stMAY'!E14 -> 16 | D14: 20 | E14: 20.5 | F14: Ptns | L14: Ptns | M14: =IF(AND(H14<>"", J14<>""), H14-J14, IF(H14<>"", H14-I14*VLOOKUP(A14, BACKEND2!$A:$G,6,FALSE), IF(J14<>"", -J14+K14*VLOOKUP(A14, BACKEND2!$A:$G,6,FALSE),0)))+ (C14+D14-E14)*VLOOKUP(A14, BACKEND2!$A:$G,5,FALSE)+G14 -> 15.5
A15: Chicken spring rolls | B15: Ptns | C15: ='19th-21stMAY'!E15 -> 1.5 | D15: 5 | E15: 5 | F15: Pcs | L15: Pcs | M15: =IF(AND(H15<>"", J15<>""), H15-J15, IF(H15<>"", H15-I15*VLOOKUP(A15, BACKEND2!$A:$G,6,FALSE), IF(J15<>"", -J15+K15*VLOOKUP(A15, BACKEND2!$A:$G,6,FALSE),0)))+ (C15+D15-E15)*VLOOKUP(A15, BACKEND2!$A:$G,5,FALSE)+G15 -> 6
A16: Chicken Samosas | B16: Ptns | C16: ='19th-21stMAY'!E16 -> 9 | E16: 6 | F16: Pcs | L16: Pcs | M16: =IF(AND(H16<>"", J16<>""), H16-J16, IF(H16<>"", H16-I16*VLOOKUP(A16, BACKEND2!$A:$G,6,FALSE), IF(J16<>"", -J16+K16*VLOOKUP(A16, BACKEND2!$A:$G,6,FALSE),0)))+ (C16+D16-E16)*VLOOKUP(A16, BACKEND2!$A:$G,5,FALSE)+G16 -> 12
A17: Pork ribs | B17: Ptns | C17: ='19th-21stMAY'!E17 -> 11 | D17: 5 | E17: 8 | F17: Pcs | L17: Pcs | M17: =IF(AND(H17<>"", J17<>""), H17-J17, IF(H17<>"", H17-I17*VLOOKUP(A17, BACKEND2!$A:$G,6,FALSE), IF(J17<>"", -J17+K17*VLOOKUP(A17, BACKEND2!$A:$G,6,FALSE),0)))+ (C17+D17-E17)*VLOOKUP(A17, BACKEND2!$A:$G,5,FALSE)+G17 -> 16
A18: Pork chops | B18: Ptns | C18: ='19th-21stMAY'!E18 -> 5 | F18: Pcs | L18: Pcs | M18: =IF(AND(H18<>"", J18<>""), H18-J18, IF(H18<>"", H18-I18*VLOOKUP(A18, BACKEND2!$A:$G,6,FALSE), IF(J18<>"", -J18+K18*VLOOKUP(A18, BACKEND2!$A:$G,6,FALSE),0)))+ (C18+D18-E18)*VLOOKUP(A18, BACKEND2!$A:$G,5,FALSE)+G18 -> 10
A19: Sizzling pork | B19: Ptns | C19: ='19th-21stMAY'!E19 -> 2 | D19: 5 | E19: 6 | F19: Ptns | L19: Ptns | M19: =IF(AND(H19<>"", J19<>""), H19-J19, IF(H19<>"", H19-I19*VLOOKUP(A19, BACKEND2!$A:$G,6,FALSE), IF(J19<>"", -J19+K19*VLOOKUP(A19, BACKEND2!$A:$G,6,FALSE),0)))+ (C19+D19-E19)*VLOOKUP(A19, BACKEND2!$A:$G,5,FALSE)+G19 -> 1
A20: Pork pizza | B20: Ptns | C20: ='19th-21stMAY'!E20 -> 5 | E20: 5 | F20: Ptns | L20: Ptns | M20: =IF(AND(H20<>"", J20<>""), H20-J20, IF(H20<>"", H20-I20*VLOOKUP(A20, BACKEND2!$A:$G,6,FALSE), IF(J20<>"", -J20+K20*VLOOKUP(A20, BACKEND2!$A:$G,6,FALSE),0)))+ (C20+D20-E20)*VLOOKUP(A20, BACKEND2!$A:$G,5,FALSE)+G20 -> 0
A21: Bacon | B21: Ptns | C21: ='19th-21stMAY'!E21 -> 5 | D21: 5 | E21: 9.5 | F21: Pcs | L21: Pcs | M21: =IF(AND(H21<>"", J21<>""), H21-J21, IF(H21<>"", H21-I21*VLOOKUP(A21, BACKEND2!$A:$G,6,FALSE), IF(J21<>"", -J21+K21*VLOOKUP(A21, BACKEND2!$A:$G,6,FALSE),0)))+ (C21+D21-E21)*VLOOKUP(A21, BACKEND2!$A:$G,5,FALSE)+G21 -> 2
A22: Bacon Warp | B22: Ptns | C22: ='19th-21stMAY'!E22 | F22: Pcs | L22: Pcs | M22: =IF(AND(H22<>"", J22<>""), H22-J22, IF(H22<>"", H22-I22*VLOOKUP(A22, BACKEND2!$A:$G,6,FALSE), IF(J22<>"", -J22+K22*VLOOKUP(A22, BACKEND2!$A:$G,6,FALSE),0)))+ (C22+D22-E22)*VLOOKUP(A22, BACKEND2!$A:$G,5,FALSE)+G22 -> 0
A23: Beef fillet | B23: Ptns | C23: ='19th-21stMAY'!E23 -> 7.5 | D23: 4 | F23: Pcs | L23: Pcs | M23: =IF(AND(H23<>"", J23<>""), H23-J23, IF(H23<>"", H23-I23*VLOOKUP(A23, BACKEND2!$A:$G,6,FALSE), IF(J23<>"", -J23+K23*VLOOKUP(A23, BACKEND2!$A:$G,6,FALSE),0)))+ (C23+D23-E23)*VLOOKUP(A23, BACKEND2!$A:$G,5,FALSE)+G23 -> 23
A24: Panfried goat | B24: Ptns | C24: ='19th-21stMAY'!E24 -> 8 | D24: 10 | F24: Ptns | L24: Ptns | M24: =IF(AND(H24<>"", J24<>""), H24-J24, IF(H24<>"", H24-I24*VLOOKUP(A24, BACKEND2!$A:$G,6,FALSE), IF(J24<>"", -J24+K24*VLOOKUP(A24, BACKEND2!$A:$G,6,FALSE),0)))+ (C24+D24-E24)*VLOOKUP(A24, BACKEND2!$A:$G,5,FALSE)+G24 -> 18
A25: Goat ribs | B25: Ptns | C25: ='19th-21stMAY'!E25 -> 10 | E25: 7 | F25: Ptns | L25: Ptns | M25: =IF(AND(H25<>"", J25<>""), H25-J25, IF(H25<>"", H25-I25*VLOOKUP(A25, BACKEND2!$A:$G,6,FALSE), IF(J25<>"", -J25+K25*VLOOKUP(A25, BACKEND2!$A:$G,6,FALSE),0)))+ (C25+D25-E25)*VLOOKUP(A25, BACKEND2!$A:$G,5,FALSE)+G25 -> 3
A26: Goat stew | B26: Ptns | C26: ='19th-21stMAY'!E26 -> 4 | E26: 3 | F26: Ptns | L26: Ptns | M26: =IF(AND(H26<>"", J26<>""), H26-J26, IF(H26<>"", H26-I26*VLOOKUP(A26, BACKEND2!$A:$G,6,FALSE), IF(J26<>"", -J26+K26*VLOOKUP(A26, BACKEND2!$A:$G,6,FALSE),0)))+ (C26+D26-E26)*VLOOKUP(A26, BACKEND2!$A:$G,5,FALSE)+G26 -> 1
A27: Beef stragnoff | B27: Ptns | C27: ='19th-21stMAY'!E27 | F27: Ptns | L27: Ptns | M27: =IF(AND(H27<>"", J27<>""), H27-J27, IF(H27<>"", H27-I27*VLOOKUP(A27, BACKEND2!$A:$G,6,FALSE), IF(J27<>"", -J27+K27*VLOOKUP(A27, BACKEND2!$A:$G,6,FALSE),0)))+ (C27+D27-E27)*VLOOKUP(A27, BACKEND2!$A:$G,5,FALSE)+G27 -> 0
A28: Beef pizza | B28: Ptns | C28: ='19th-21stMAY'!E28 -> 8 | D28: 10 | E28: 17 | F28: Ptns | L28: Ptns | M28: =IF(AND(H28<>"", J28<>""), H28-J28, IF(H28<>"", H28-I28*VLOOKUP(A28, BACKEND2!$A:$G,6,FALSE), IF(J28<>"", -J28+K28*VLOOKUP(A28, BACKEND2!$A:$G,6,FALSE),0)))+ (C28+D28-E28)*VLOOKUP(A28, BACKEND2!$A:$G,5,FALSE)+G28 -> 1
A29: Beef sausages | B29: Ptns | C29: ='19th-21stMAY'!E29 -> 8.5 | D29: 11 | E29: 14.1 | F29: Pcs | L29: Pcs | M29: =IF(AND(H29<>"", J29<>""), H29-J29, IF(H29<>"", H29-I29*VLOOKUP(A29, BACKEND2!$A:$G,6,FALSE), IF(J29<>"", -J29+K29*VLOOKUP(A29, BACKEND2!$A:$G,6,FALSE),0)))+ (C29+D29-E29)*VLOOKUP(A29, BACKEND2!$A:$G,5,FALSE)+G29 -> 10.8
A30: Beef burger patty | B30: Ptns | C30: ='19th-21stMAY'!E30 -> 5 | D30: 5 | E30: 4 | F30: Ptns | L30: Ptns | M30: =IF(AND(H30<>"", J30<>""), H30-J30, IF(H30<>"", H30-I30*VLOOKUP(A30, BACKEND2!$A:$G,6,FALSE), IF(J30<>"", -J30+K30*VLOOKUP(A30, BACKEND2!$A:$G,6,FALSE),0)))+ (C30+D30-E30)*VLOOKUP(A30, BACKEND2!$A:$G,5,FALSE)+G30 -> 6
A31: Bolognese | B31: Ptns | C31: ='19th-21stMAY'!E31 -> 2 | D31: 11 | E31: 13 | F31: Ptns | L31: Ptns | M31: =IF(AND(H31<>"", J31<>""), H31-J31, IF(H31<>"", H31-I31*VLOOKUP(A31, BACKEND2!$A:$G,6,FALSE), IF(J31<>"", -J31+K31*VLOOKUP(A31, BACKEND2!$A:$G,6,FALSE),0)))+ (C31+D31-E31)*VLOOKUP(A31, BACKEND2!$A:$G,5,FALSE)+G31 -> 0
A32: Beef samosas | B32: Ptns | C32: ='19th-21stMAY'!E32 -> 3 | D32: 7 | E32: 2 | F32: Pcs | L32: Pcs | M32: =IF(AND(H32<>"", J32<>""), H32-J32, IF(H32<>"", H32-I32*VLOOKUP(A32, BACKEND2!$A:$G,6,FALSE), IF(J32<>"", -J32+K32*VLOOKUP(A32, BACKEND2!$A:$G,6,FALSE),0)))+ (C32+D32-E32)*VLOOKUP(A32, BACKEND2!$A:$G,5,FALSE)+G32 -> 32
A33: Beef mini burger | B33: Ptns | C33: ='19th-21stMAY'!E33 | F33: Ptns | L33: Ptns | M33: =IF(AND(H33<>"", J33<>""), H33-J33, IF(H33<>"", H33-I33*VLOOKUP(A33, BACKEND2!$A:$G,6,FALSE), IF(J33<>"", -J33+K33*VLOOKUP(A33, BACKEND2!$A:$G,6,FALSE),0)))+ (C33+D33-E33)*VLOOKUP(A33, BACKEND2!$A:$G,5,FALSE)+G33 -> 0
A34: Whole fish | B34: Ptns | C34: ='19th-21stMAY'!E34 -> 5 | D34: 5 | E34: 7 | F34: Ptns | L34: Ptns | M34: =IF(AND(H34<>"", J34<>""), H34-J34, IF(H34<>"", H34-I34*VLOOKUP(A34, BACKEND2!$A:$G,6,FALSE), IF(J34<>"", -J34+K34*VLOOKUP(A34, BACKEND2!$A:$G,6,FALSE),0)))+ (C34+D34-E34)*VLOOKUP(A34, BACKEND2!$A:$G,5,FALSE)+G34 -> 3
A35: Salmon | B35: Ptns | C35: ='19th-21stMAY'!E35 -> 1 | D35: 4 | E35: 5 | F35: Ptns | L35: Ptns | M35: =IF(AND(H35<>"", J35<>""), H35-J35, IF(H35<>"", H35-I35*VLOOKUP(A35, BACKEND2!$A:$G,6,FALSE), IF(J35<>"", -J35+K35*VLOOKUP(A35, BACKEND2!$A:$G,6,FALSE),0)))+ (C35+D35-E35)*VLOOKUP(A35, BACKEND2!$A:$G,5,FALSE)+G35 -> 0
A36: Tilapia fillet | B36: Ptns | C36: ='19th-21stMAY'!E36 -> 10 | E36: 4 | F36: Pcs | L36: Pcs | M36: =IF(AND(H36<>"", J36<>""), H36-J36, IF(H36<>"", H36-I36*VLOOKUP(A36, BACKEND2!$A:$G,6,FALSE), IF(J36<>"", -J36+K36*VLOOKUP(A36, BACKEND2!$A:$G,6,FALSE),0)))+ (C36+D36-E36)*VLOOKUP(A36, BACKEND2!$A:$G,5,FALSE)+G36 -> 12
A37: Fish fingers | B37: Ptns | C37: ='19th-21stMAY'!E37 -> 14 | E37: 14 | F37: Pcs | L37: Pcs | M37: =IF(AND(H37<>"", J37<>""), H37-J37, IF(H37<>"", H37-I37*VLOOKUP(A37, BACKEND2!$A:$G,6,FALSE), IF(J37<>"", -J37+K37*VLOOKUP(A37, BACKEND2!$A:$G,6,FALSE),0)))+ (C37+D37-E37)*VLOOKUP(A37, BACKEND2!$A:$G,5,FALSE)+G37 -> 0
A38: Veg Springs rolls | B38: Ptns | C38: ='19th-21stMAY'!E38 -> 1 | E38: 1 | F38: Pcs | L38: Pcs | M38: =IF(AND(H38<>"", J38<>""), H38-J38, IF(H38<>"", H38-I38*VLOOKUP(A38, BACKEND2!$A:$G,6,FALSE), IF(J38<>"", -J38+K38*VLOOKUP(A38, BACKEND2!$A:$G,6,FALSE),0)))+ (C38+D38-E38)*VLOOKUP(A38, BACKEND2!$A:$G,5,FALSE)+G38 -> 0
A39: Veg Samosas | B39: Ptns | C39: ='19th-21stMAY'!E39 -> 1 | D39: 3 | E39: 4 | F39: Pcs | L39: Pcs | M39: =IF(AND(H39<>"", J39<>""), H39-J39, IF(H39<>"", H39-I39*VLOOKUP(A39, BACKEND2!$A:$G,6,FALSE), IF(J39<>"", -J39+K39*VLOOKUP(A39, BACKEND2!$A:$G,6,FALSE),0)))+ (C39+D39-E39)*VLOOKUP(A39, BACKEND2!$A:$G,5,FALSE)+G39 -> 0
A40: Beef Stew | B40: Ptns | C40: ='19th-21stMAY'!E40 -> 3 | D40: 5 | E40: 4 | F40: Pcs | L40: Pcs | M40: =IF(AND(H40<>"", J40<>""), H40-J40, IF(H40<>"", H40-I40*VLOOKUP(A40, BACKEND2!$A:$G,6,FALSE), IF(J40<>"", -J40+K40*VLOOKUP(A40, BACKEND2!$A:$G,6,FALSE),0)))+ (C40+D40-E40)*VLOOKUP(A40, BACKEND2!$A:$G,5,FALSE)+G40 -> 4
A41: Beef Minced Meat | B41: Ptns | C41: ='19th-21stMAY'!E41 | F41: Pcs | L41: Pcs | M41: =IF(AND(H41<>"", J41<>""), H41-J41, IF(H41<>"", H41-I41*VLOOKUP(A41, BACKEND2!$A:$G,6,FALSE), IF(J41<>"", -J41+K41*VLOOKUP(A41, BACKEND2!$A:$G,6,FALSE),0)))+ (C41+D41-E41)*VLOOKUP(A41, BACKEND2!$A:$G,5,FALSE)+G41 -> 0
A42: Other Kitchen & Food Supplies | C42: ='19th-21stMAY'!E42
A43: Condiments | C43: ='19th-21stMAY'!E43
A44: Bread Loaf | B44: Loaf | C44: ='19th-21stMAY'!E44 | F44: kg | H44: ='19th-21stMAY'!J44 -> 2.25 | I44: 1 | J44: 1.5 | L44: kg | M44: =IF(AND(H44<>"", J44<>""), H44-J44, IF(H44<>"", H44-I44*VLOOKUP(A44, BACKEND1!$A:$G,6,FALSE), IF(J44<>"", -J44+K44*VLOOKUP(A44, BACKEND1!$A:$G,6,FALSE),0)))+ (C44+D44-E44)*VLOOKUP(A44, BACKEND1!$A:$G,5,FALSE)+G44 -> 0.75
A45: Burger Buns | B45: Pcs | C45: ='19th-21stMAY'!E45 | D45: 5 | F45: Pcs | H45: ='19th-21stMAY'!J45 -> 11 | I45: 1 | J45: 15 | L45: Pcs | M45: =IF(AND(H45<>"", J45<>""), H45-J45, IF(H45<>"", H45-I45*VLOOKUP(A45, BACKEND1!$A:$G,6,FALSE), IF(J45<>"", -J45+K45*VLOOKUP(A45, BACKEND1!$A:$G,6,FALSE),0)))+ (C45+D45-E45)*VLOOKUP(A45, BACKEND1!$A:$G,5,FALSE)+G45 -> 1
A46: Slider Buns | B46: Pcs | C46: ='19th-21stMAY'!E46 | D46: 5 | F46: Pcs | H46: 6 | I46: 1 | J46: 11 | L46: Pcs | M46: =IF(AND(H46<>"", J46<>""), H46-J46, IF(H46<>"", H46-I46*VLOOKUP(A46, BACKEND1!$A:$G,6,FALSE), IF(J46<>"", -J46+K46*VLOOKUP(A46, BACKEND1!$A:$G,6,FALSE),0)))+ (C46+D46-E46)*VLOOKUP(A46, BACKEND1!$A:$G,5,FALSE)+G46 -> 0
A47: Soup Buns | B47: Pcs | C47: ='19th-21stMAY'!E47 | D47: 10 | F47: Pcs | H47: ='19th-21stMAY'!J47 -> 3 | I47: 1 | J47: 6 | L47: Pcs | M47: =IF(AND(H47<>"", J47<>""), H47-J47, IF(H47<>"", H47-I47*VLOOKUP(A47, BACKEND1!$A:$G,6,FALSE), IF(J47<>"", -J47+K47*VLOOKUP(A47, BACKEND1!$A:$G,6,FALSE),0)))+ (C47+D47-E47)*VLOOKUP(A47, BACKEND1!$A:$G,5,FALSE)+G47 -> 7
A48: Baguette Bread | B48: Pcs | C48: ='19th-21stMAY'!E48 | D48: 2 | F48: Pcs | H48: ='19th-21stMAY'!J48 -> 4 | I48: 1 | J48: 4 | L48: Pcs | M48: =IF(AND(H48<>"", J48<>""), H48-J48, IF(H48<>"", H48-I48*VLOOKUP(A48, BACKEND1!$A:$G,6,FALSE), IF(J48<>"", -J48+K48*VLOOKUP(A48, BACKEND1!$A:$G,6,FALSE),0)))+ (C48+D48-E48)*VLOOKUP(A48, BACKEND1!$A:$G,5,FALSE)+G48 -> 2
A49: Foccacia Bread | B49: Pcs | C49: ='19th-21stMAY'!E49 | F49: Pcs | H49: ='19th-21stMAY'!J49 | I49: 1 | L49: Pcs | M49: =IF(AND(H49<>"", J49<>""), H49-J49, IF(H49<>"", H49-I49*VLOOKUP(A49, BACKEND1!$A:$G,6,FALSE), IF(J49<>"", -J49+K49*VLOOKUP(A49, BACKEND1!$A:$G,6,FALSE),0)))+ (C49+D49-E49)*VLOOKUP(A49, BACKEND1!$A:$G,5,FALSE)+G49 -> 0
A50: White vinegar | B50: Bottles | C50: ='19th-21stMAY'!E50 | D50: 1 | F50: Liters | H50: ='19th-21stMAY'!J50 -> 0.497 | I50: 1 | J50: 0.51 | L50: Liters | M50: =IF(AND(H50<>"", J50<>""), H50-J50, IF(H50<>"", H50-I50*VLOOKUP(A50, BACKEND1!$A:$G,6,FALSE), IF(J50<>"", -J50+K50*VLOOKUP(A50, BACKEND1!$A:$G,6,FALSE),0)))+ (C50+D50-E50)*VLOOKUP(A50, BACKEND1!$A:$G,5,FALSE)+G50 -> 0.687
A51: Heinz ketchup bottles | B51: Bottles | C51: ='19th-21stMAY'!E51 | F51: Bottles | H51: ='19th-21stMAY'!J51 | I51: 1 | L51: Bottles | M51: =IF(AND(H51<>"", J51<>""), H51-J51, IF(H51<>"", H51-I51*VLOOKUP(A51, BACKEND1!$A:$G,6,FALSE), IF(J51<>"", -J51+K51*VLOOKUP(A51, BACKEND1!$A:$G,6,FALSE),0)))+ (C51+D51-E51)*VLOOKUP(A51, BACKEND1!$A:$G,5,FALSE)+G51 -> 0
A52: Apple cider vinegar | B52: Pcs | C52: ='19th-21stMAY'!E52 | D52: 2 | F52: kg | H52: ='19th-21stMAY'!J52 -> 0.488 | I52: 1 | J52: 0.485 | L52: kg | M52: =IF(AND(H52<>"", J52<>""), H52-J52, IF(H52<>"", H52-I52*VLOOKUP(A52, BACKEND1!$A:$G,6,FALSE), IF(J52<>"", -J52+K52*VLOOKUP(A52, BACKEND1!$A:$G,6,FALSE),0)))+ (C52+D52-E52)*VLOOKUP(A52, BACKEND1!$A:$G,5,FALSE)+G52 -> 0.949
A53: Balsamic Vinegar | B53: Bottles | C53: ='19th-21stMAY'!E53 | F53: Kg | H53: ='19th-21stMAY'!J53 -> 0.733 | I53: 1 | J53: 0.713 | L53: Kg | M53: =IF(AND(H53<>"", J53<>""), H53-J53, IF(H53<>"", H53-I53*VLOOKUP(A53, BACKEND1!$A:$G,6,FALSE), IF(J53<>"", -J53+K53*VLOOKUP(A53, BACKEND1!$A:$G,6,FALSE),0)))+ (C53+D53-E53)*VLOOKUP(A53, BACKEND1!$A:$G,5,FALSE)+G53 -> 0.02
A54: Tomato paste | B54: Tins | C54: ='19th-21stMAY'!E54 | D54: 1 | F54: Kg | H54: ='19th-21stMAY'!J54 | I54: 1 | J54: 0.278 | L54: Kg | M54: =IF(AND(H54<>"", J54<>""), H54-J54, IF(H54<>"", H54-I54*VLOOKUP(A54, BACKEND1!$A:$G,6,FALSE), IF(J54<>"", -J54+K54*VLOOKUP(A54, BACKEND1!$A:$G,6,FALSE),0)))+ (C54+D54-E54)*VLOOKUP(A54, BACKEND1!$A:$G,5,FALSE)+G54 -> 0.122
A55: Tabasco | B55: Pcs | C55: ='19th-21stMAY'!E55 | F55: Kgs | H55: ='19th-21stMAY'!J55 | I55: 1 | L55: Kgs | M55: =IF(AND(H55<>"", J55<>""), H55-J55, IF(H55<>"", H55-I55*VLOOKUP(A55, BACKEND1!$A:$G,6,FALSE), IF(J55<>"", -J55+K55*VLOOKUP(A55, BACKEND1!$A:$G,6,FALSE),0)))+ (C55+D55-E55)*VLOOKUP(A55, BACKEND1!$A:$G,5,FALSE)+G55 -> 0
A56: Ketchup sachets | B56: Packet | C56: ='19th-21stMAY'!E56 -> 1 | F56: Pcs | H56: ='19th-21stMAY'!J56 | I56: 1 | J56: 50 | L56: Pcs | M56: =IF(AND(H56<>"", J56<>""), H56-J56, IF(H56<>"", H56-I56*VLOOKUP(A56, BACKEND1!$A:$G,6,FALSE), IF(J56<>"", -J56+K56*VLOOKUP(A56, BACKEND1!$A:$G,6,FALSE),0)))+ (C56+D56-E56)*VLOOKUP(A56, BACKEND1!$A:$G,5,FALSE)+G56 -> 50
A57: Mustard | B57: Bottles | C57: ='19th-21stMAY'!E57 | D57: 1 | E57: 1 | F57: Kg | H57: ='19th-21stMAY'!J57 -> 0.428 | I57: 1 | J57: 0.184 | L57: Kg | M57: =IF(AND(H57<>"", J57<>""), H57-J57, IF(H57<>"", H57-I57*VLOOKUP(A57, BACKEND1!$A:$G,6,FALSE), IF(J57<>"", -J57+K57*VLOOKUP(A57, BACKEND1!$A:$G,6,FALSE),0)))+ (C57+D57-E57)*VLOOKUP(A57, BACKEND1!$A:$G,5,FALSE)+G57 -> 0.244
A58: Pancake syrup 710ml | B58: Bottles | C58: ='19th-21stMAY'!E58 | D58: 1 | E58: 1 | F58: Liters | H58: ='19th-21stMAY'!J58 | I58: 1 | L58: Liters | M58: =IF(AND(H58<>"", J58<>""), H58-J58, IF(H58<>"", H58-I58*VLOOKUP(A58, BACKEND1!$A:$G,6,FALSE), IF(J58<>"", -J58+K58*VLOOKUP(A58, BACKEND1!$A:$G,6,FALSE),0)))+ (C58+D58-E58)*VLOOKUP(A58, BACKEND1!$A:$G,5,FALSE)+G58 -> 0
A59: Vanilla esscence | B59: Bottles | C59: ='19th-21stMAY'!E59 | F59: Liters | H59: ='19th-21stMAY'!J59 -> 0.828 | I59: 1 | J59: 0.817 | L59: Liters | M59: =IF(AND(H59<>"", J59<>""), H59-J59, IF(H59<>"", H59-I59*VLOOKUP(A59, BACKEND1!$A:$G,6,FALSE), IF(J59<>"", -J59+K59*VLOOKUP(A59, BACKEND1!$A:$G,6,FALSE),0)))+ (C59+D59-E59)*VLOOKUP(A59, BACKEND1!$A:$G,5,FALSE)+G59 -> 0.011
A60: Srawberry Syrup | B60: Btls | C60: ='19th-21stMAY'!E60 | F60: Ltr | H60: ='19th-21stMAY'!J60 | I60: 1 | L60: Ltr | M60: =IF(AND(H60<>"", J60<>""), H60-J60, IF(H60<>"", H60-I60*VLOOKUP(A60, BACKEND1!$A:$G,6,FALSE), IF(J60<>"", -J60+K60*VLOOKUP(A60, BACKEND1!$A:$G,6,FALSE),0)))+ (C60+D60-E60)*VLOOKUP(A60, BACKEND1!$A:$G,5,FALSE)+G60 -> 0
A61: Caramel syrup | B61: Btls | C61: ='19th-21stMAY'!E61 | F61: Ltr | H61: ='19th-21stMAY'!J61 | I61: 1 | L61: Ltr | M61: =IF(AND(H61<>"", J61<>""), H61-J61, IF(H61<>"", H61-I61*VLOOKUP(A61, BACKEND1!$A:$G,6,FALSE), IF(J61<>"", -J61+K61*VLOOKUP(A61, BACKEND1!$A:$G,6,FALSE),0)))+ (C61+D61-E61)*VLOOKUP(A61, BACKEND1!$A:$G,5,FALSE)+G61 -> 0
A62: Chocolate syrup | B62: Btls | C62: ='19th-21stMAY'!E62 | F62: Ltr | G62: 0.518 | H62: ='19th-21stMAY'!J62 -> 0.118 | I62: 1 | J62: 0.636 | L62: Ltr | M62: =IF(AND(H62<>"", J62<>""), H62-J62, IF(H62<>"", H62-I62*VLOOKUP(A62, BACKEND1!$A:$G,6,FALSE), IF(J62<>"", -J62+K62*VLOOKUP(A62, BACKEND1!$A:$G,6,FALSE),0)))+ (C62+D62-E62)*VLOOKUP(A62, BACKEND1!$A:$G,5,FALSE)+G62 -> 0
A63: Honey | B63: Kg | C63: ='19th-21stMAY'!E63 | F63: Kg | G63: 1 | H63: ='19th-21stMAY'!J63 -> 1.136 | I63: 1 | J63: 0.921 | L63: Kg | M63: =IF(AND(H63<>"", J63<>""), H63-J63, IF(H63<>"", H63-I63*VLOOKUP(A63, BACKEND1!$A:$G,6,FALSE), IF(J63<>"", -J63+K63*VLOOKUP(A63, BACKEND1!$A:$G,6,FALSE),0)))+ (C63+D63-E63)*VLOOKUP(A63, BACKEND1!$A:$G,5,FALSE)+G63 -> 1.215
A64: Ketchup 5L | B64: Jerrycan | C64: ='19th-21stMAY'!E64 | F64: kg | H64: ='19th-21stMAY'!J64 -> 3.853 | I64: 1 | J64: 3.771 | L64: kg | M64: =IF(AND(H64<>"", J64<>""), H64-J64, IF(H64<>"", H64-I64*VLOOKUP(A64, BACKEND1!$A:$G,6,FALSE), IF(J64<>"", -J64+K64*VLOOKUP(A64, BACKEND1!$A:$G,6,FALSE),0)))+ (C64+D64-E64)*VLOOKUP(A64, BACKEND1!$A:$G,5,FALSE)+G64 -> 0.082
A65: Dry Foods | C65: ='19th-21stMAY'!E65 | H65: ='19th-21stMAY'!J65 | I65: 1 | M65: =IF(AND(H65<>"", J65<>""), H65-J65, IF(H65<>"", H65-I65*VLOOKUP(A65, BACKEND1!$A:$G,6,FALSE), IF(J65<>"", -J65+K65*VLOOKUP(A65, BACKEND1!$A:$G,6,FALSE),0)))+ (C65+D65-E65)*VLOOKUP(A65, BACKEND1!$A:$G,5,FALSE)+G65 -> 0
A66: Baking flour | B66: Pkts | C66: ='19th-21stMAY'!E66 | D66: 6 | E66: 1 | F66: Kg | H66: ='19th-21stMAY'!J66 -> 1.281 | I66: 1 | L66: Kg | M66: =IF(AND(H66<>"", J66<>""), H66-J66, IF(H66<>"", H66-I66*VLOOKUP(A66, BACKEND1!$A:$G,6,FALSE), IF(J66<>"", -J66+K66*VLOOKUP(A66, BACKEND1!$A:$G,6,FALSE),0)))+ (C66+D66-E66)*VLOOKUP(A66, BACKEND1!$A:$G,5,FALSE)+G66 -> 11.231
A67: Baking Powder | B67: Pkts | C67: ='19th-21stMAY'!E67 | D67: 1 | E67: 1 | F67: Kg | H67: ='19th-21stMAY'!J67 -> 0.121 | I67: 1 | J67: 0.093 | L67: Kg | M67: =IF(AND(H67<>"", J67<>""), H67-J67, IF(H67<>"", H67-I67*VLOOKUP(A67, BACKEND1!$A:$G,6,FALSE), IF(J67<>"", -J67+K67*VLOOKUP(A67, BACKEND1!$A:$G,6,FALSE),0)))+ (C67+D67-E67)*VLOOKUP(A67, BACKEND1!$A:$G,5,FALSE)+G67 -> 0.028
A68: Basmati rice | B68: Kg | C68: ='19th-21stMAY'!E68 | F68: Kg | H68: ='19th-21stMAY'!J68 -> 5 | I68: 1 | L68: Kg | M68: =IF(AND(H68<>"", J68<>""), H68-J68, IF(H68<>"", H68-I68*VLOOKUP(A68, BACKEND1!$A:$G,6,FALSE), IF(J68<>"", -J68+K68*VLOOKUP(A68, BACKEND1!$A:$G,6,FALSE),0)))+ (C68+D68-E68)*VLOOKUP(A68, BACKEND1!$A:$G,5,FALSE)+G68 -> 4.9
A69: Corn flour | B69: Pkts | C69: ='19th-21stMAY'!E69 -> 1 | D69: 1 | F69: Kg | H69: ='19th-21stMAY'!J69 | I69: 1 | J69: 0.23 | L69: Kg | M69: =IF(AND(H69<>"", J69<>""), H69-J69, IF(H69<>"", H69-I69*VLOOKUP(A69, BACKEND1!$A:$G,6,FALSE), IF(J69<>"", -J69+K69*VLOOKUP(A69, BACKEND1!$A:$G,6,FALSE),0)))+ (C69+D69-E69)*VLOOKUP(A69, BACKEND1!$A:$G,5,FALSE)+G69 -> 0.57
A70: Oils, Fats & Creams | C70: ='19th-21stMAY'!E70 | H70: ='19th-21stMAY'!J70 | I70: 1 | M70: =IF(AND(H70<>"", J70<>""), H70-J70, IF(H70<>"", H70-I70*VLOOKUP(A70, BACKEND1!$A:$G,6,FALSE), IF(J70<>"", -J70+K70*VLOOKUP(A70, BACKEND1!$A:$G,6,FALSE),0)))+ (C70+D70-E70)*VLOOKUP(A70, BACKEND1!$A:$G,5,FALSE)+G70 -> 0
A71: Cooking oil 20L | B71: Jerrycan | C71: ='19th-21stMAY'!E71 | F71: Liters | G71: 8 | H71: ='19th-21stMAY'!J71 -> 0.988 | I71: 1 | J71: 0.311 | L71: Liters | M71: =IF(AND(H71<>"", J71<>""), H71-J71, IF(H71<>"", H71-I71*VLOOKUP(A71, BACKEND1!$A:$G,6,FALSE), IF(J71<>"", -J71+K71*VLOOKUP(A71, BACKEND1!$A:$G,6,FALSE),0)))+ (C71+D71-E71)*VLOOKUP(A71, BACKEND1!$A:$G,5,FALSE)+G71 -> 8.677
A72: Croma Butter | B72: Kg | C72: ='19th-21stMAY'!E72 | D72: 0.8 | F72: Kg | H72: ='19th-21stMAY'!J72 -> 0.63 | I72: 1 | J72: 0.56 | L72: Kg | M72: =IF(AND(H72<>"", J72<>""), H72-J72, IF(H72<>"", H72-I72*VLOOKUP(A72, BACKEND1!$A:$G,6,FALSE), IF(J72<>"", -J72+K72*VLOOKUP(A72, BACKEND1!$A:$G,6,FALSE),0)))+ (C72+D72-E72)*VLOOKUP(A72, BACKEND1!$A:$G,5,FALSE)+G72 -> 0.87
A73: Prestige | B73: Kg | C73: ='19th-21stMAY'!E73 | F73: Kg | G73: 0.56 | H73: ='19th-21stMAY'!J73 | I73: 1 | J73: 0.56 | L73: Kg | M73: =IF(AND(H73<>"", J73<>""), H73-J73, IF(H73<>"", H73-I73*VLOOKUP(A73, BACKEND1!$A:$G,6,FALSE), IF(J73<>"", -J73+K73*VLOOKUP(A73, BACKEND1!$A:$G,6,FALSE),0)))+ (C73+D73-E73)*VLOOKUP(A73, BACKEND1!$A:$G,5,FALSE)+G73 -> 0
A74: Cooking cream | B74: Packs | C74: ='19th-21stMAY'!E74 | D74: 1 | F74: Liters | H74: ='19th-21stMAY'!J74 -> 0.813 | I74: 1 | L74: Liters | M74: =IF(AND(H74<>"", J74<>""), H74-J74, IF(H74<>"", H74-I74*VLOOKUP(A74, BACKEND1!$A:$G,6,FALSE), IF(J74<>"", -J74+K74*VLOOKUP(A74, BACKEND1!$A:$G,6,FALSE),0)))+ (C74+D74-E74)*VLOOKUP(A74, BACKEND1!$A:$G,5,FALSE)+G74 -> 1.751
A75: Sunseed Oil 5L | B75: Pcs | C75: ='19th-21stMAY'!E75 | F75: Liters | H75: ='19th-21stMAY'!J75 -> 0.928 | I75: 1 | J75: 0.781 | L75: Liters | M75: =IF(AND(H75<>"", J75<>""), H75-J75, IF(H75<>"", H75-I75*VLOOKUP(A75, BACKEND1!$A:$G,6,FALSE), IF(J75<>"", -J75+K75*VLOOKUP(A75, BACKEND1!$A:$G,6,FALSE),0)))+ (C75+D75-E75)*VLOOKUP(A75, BACKEND1!$A:$G,5,FALSE)+G75 -> 0.147
A76: Whipping cream | B76: Packs | C76: ='19th-21stMAY'!E76 | F76: Kg | H76: ='19th-21stMAY'!J76 -> 1 | I76: 1 | J76: 1 | L76: Kg | M76: =IF(AND(H76<>"", J76<>""), H76-J76, IF(H76<>"", H76-I76*VLOOKUP(A76, BACKEND1!$A:$G,6,FALSE), IF(J76<>"", -J76+K76*VLOOKUP(A76, BACKEND1!$A:$G,6,FALSE),0)))+ (C76+D76-E76)*VLOOKUP(A76, BACKEND1!$A:$G,5,FALSE)+G76 -> 0
A77: Olive Oil | B77: Can | C77: ='19th-21stMAY'!E77 | F77: Liters | H77: ='19th-21stMAY'!J77 -> 1.029 | I77: 1 | J77: 0.742 | L77: Liters | M77: =IF(AND(H77<>"", J77<>""), H77-J77, IF(H77<>"", H77-I77*VLOOKUP(A77, BACKEND1!$A:$G,6,FALSE), IF(J77<>"", -J77+K77*VLOOKUP(A77, BACKEND1!$A:$G,6,FALSE),0)))+ (C77+D77-E77)*VLOOKUP(A77, BACKEND1!$A:$G,5,FALSE)+G77 -> 0.287
A78: Coconut Oil | B78: Jerrycan | C78: ='19th-21stMAY'!E78 | F78: Kg | H78: ='19th-21stMAY'!J78 | I78: 1 | L78: Kg | M78: =IF(AND(H78<>"", J78<>""), H78-J78, IF(H78<>"", H78-I78*VLOOKUP(A78, BACKEND1!$A:$G,6,FALSE), IF(J78<>"", -J78+K78*VLOOKUP(A78, BACKEND1!$A:$G,6,FALSE),0)))+ (C78+D78-E78)*VLOOKUP(A78, BACKEND1!$A:$G,5,FALSE)+G78 -> 0
A79: Seseame Oil | B79: Bottle | C79: ='19th-21stMAY'!E79 | F79: Kg | G79: 1 | H79: ='19th-21stMAY'!J79 -> 0.045 | I79: 1 | J79: 1 | L79: Kg | M79: =IF(AND(H79<>"", J79<>""), H79-J79, IF(H79<>"", H79-I79*VLOOKUP(A79, BACKEND1!$A:$G,6,FALSE), IF(J79<>"", -J79+K79*VLOOKUP(A79, BACKEND1!$A:$G,6,FALSE),0)))+ (C79+D79-E79)*VLOOKUP(A79, BACKEND1!$A:$G,5,FALSE)+G79 -> 0.045
A80: Sauces | C80: ='19th-21stMAY'!E80 | H80: ='19th-21stMAY'!J80 | I80: 1 | M80: =IF(AND(H80<>"", J80<>""), H80-J80, IF(H80<>"", H80-I80*VLOOKUP(A80, BACKEND1!$A:$G,6,FALSE), IF(J80<>"", -J80+K80*VLOOKUP(A80, BACKEND1!$A:$G,6,FALSE),0)))+ (C80+D80-E80)*VLOOKUP(A80, BACKEND1!$A:$G,5,FALSE)+G80 -> 0
A81: Light soy sauce | B81: Bottle | C81: ='19th-21stMAY'!E81 | D81: 1 | F81: Liters | H81: ='19th-21stMAY'!J81 -> 0.138 | I81: 1 | L81: Liters | M81: =IF(AND(H81<>"", J81<>""), H81-J81, IF(H81<>"", H81-I81*VLOOKUP(A81, BACKEND1!$A:$G,6,FALSE), IF(J81<>"", -J81+K81*VLOOKUP(A81, BACKEND1!$A:$G,6,FALSE),0)))+ (C81+D81-E81)*VLOOKUP(A81, BACKEND1!$A:$G,5,FALSE)+G81 -> 0.226
A82: Dark soy sauce | B82: Bottle | C82: ='19th-21stMAY'!E82 | D82: 2 | E82: 1 | F82: Liters | H82: ='19th-21stMAY'!J82 -> 0.574 | I82: 1 | J82: 0.143 | L82: Liters | M82: =IF(AND(H82<>"", J82<>""), H82-J82, IF(H82<>"", H82-I82*VLOOKUP(A82, BACKEND1!$A:$G,6,FALSE), IF(J82<>"", -J82+K82*VLOOKUP(A82, BACKEND1!$A:$G,6,FALSE),0)))+ (C82+D82-E82)*VLOOKUP(A82, BACKEND1!$A:$G,5,FALSE)+G82 -> 0.931
A83: Sweet chilli sauce | B83: Bottle | C83: ='19th-21stMAY'!E83 | F83: Liters | H83: ='19th-21stMAY'!J83 -> 1.16 | I83: 1 | J83: 0.734 | L83: Liters | M83: =IF(AND(H83<>"", J83<>""), H83-J83, IF(H83<>"", H83-I83*VLOOKUP(A83, BACKEND1!$A:$G,6,FALSE), IF(J83<>"", -J83+K83*VLOOKUP(A83, BACKEND1!$A:$G,6,FALSE),0)))+ (C83+D83-E83)*VLOOKUP(A83, BACKEND1!$A:$G,5,FALSE)+G83 -> 0.426
A84: Oyster sauce | B84: Bottle | C84: ='19th-21stMAY'!E84 | D84: 1 | F84: Liters | H84: ='19th-21stMAY'!J84 -> 0.583 | I84: 1 | J84: 0.667 | L84: Liters | M84: =IF(AND(H84<>"", J84<>""), H84-J84, IF(H84<>"", H84-I84*VLOOKUP(A84, BACKEND1!$A:$G,6,FALSE), IF(J84<>"", -J84+K84*VLOOKUP(A84, BACKEND1!$A:$G,6,FALSE),0)))+ (C84+D84-E84)*VLOOKUP(A84, BACKEND1!$A:$G,5,FALSE)+G84 -> 0.426
A85: Worcestershire sauce | B85: Bottles | C85: ='19th-21stMAY'!E85 -> 1 | D85: 1 | F85: Liters | H85: ='19th-21stMAY'!J85 | I85: 1 | J85: 0.288 | L85: Liters | M85: =IF(AND(H85<>"", J85<>""), H85-J85, IF(H85<>"", H85-I85*VLOOKUP(A85, BACKEND1!$A:$G,6,FALSE), IF(J85<>"", -J85+K85*VLOOKUP(A85, BACKEND1!$A:$G,6,FALSE),0)))+ (C85+D85-E85)*VLOOKUP(A85, BACKEND1!$A:$G,5,FALSE)+G85 -> 0.302
A86: Top up sauce | B86: Jerrycan | C86: ='19th-21stMAY'!E86 -> 1 | D86: 1 | F86: Liters | H86: ='19th-21stMAY'!J86 | I86: 1 | J86: 2.824 | L86: Liters | M86: =IF(AND(H86<>"", J86<>""), H86-J86, IF(H86<>"", H86-I86*VLOOKUP(A86, BACKEND1!$A:$G,6,FALSE), IF(J86<>"", -J86+K86*VLOOKUP(A86, BACKEND1!$A:$G,6,FALSE),0)))+ (C86+D86-E86)*VLOOKUP(A86, BACKEND1!$A:$G,5,FALSE)+G86 -> 7.176
A87: Fish Sauce | B87: Bottle | C87: ='19th-21stMAY'!E87 | F87: Liters | H87: ='19th-21stMAY'!J87 -> 0.839 | I87: 1 | J87: 0.751 | L87: Liters | M87: =IF(AND(H87<>"", J87<>""), H87-J87, IF(H87<>"", H87-I87*VLOOKUP(A87, BACKEND1!$A:$G,6,FALSE), IF(J87<>"", -J87+K87*VLOOKUP(A87, BACKEND1!$A:$G,6,FALSE),0)))+ (C87+D87-E87)*VLOOKUP(A87, BACKEND1!$A:$G,5,FALSE)+G87 -> 0.088
A88: Red Wine | B88: Bottle | C88: ='19th-21stMAY'!E88 | F88: Liters | H88: ='19th-21stMAY'!J88 -> 0.663 | I88: 1 | J88: 0.661 | L88: Liters | M88: =IF(AND(H88<>"", J88<>""), H88-J88, IF(H88<>"", H88-I88*VLOOKUP(A88, BACKEND1!$A:$G,6,FALSE), IF(J88<>"", -J88+K88*VLOOKUP(A88, BACKEND1!$A:$G,6,FALSE),0)))+ (C88+D88-E88)*VLOOKUP(A88, BACKEND1!$A:$G,5,FALSE)+G88 -> 0.002
A89: White Wine | B89: Bottle | C89: ='19th-21stMAY'!E89 | F89: Liters | H89: ='19th-21stMAY'!J89 -> 1.068 | I89: 1 | J89: 0.974 | L89: Liters | M89: =IF(AND(H89<>"", J89<>""), H89-J89, IF(H89<>"", H89-I89*VLOOKUP(A89, BACKEND1!$A:$G,6,FALSE), IF(J89<>"", -J89+K89*VLOOKUP(A89, BACKEND1!$A:$G,6,FALSE),0)))+ (C89+D89-E89)*VLOOKUP(A89, BACKEND1!$A:$G,5,FALSE)+G89 -> 0.094
A90: Spices | C90: ='19th-21stMAY'!E90 | H90: ='19th-21stMAY'!J90 | I90: 1 | M90: =IF(AND(H90<>"", J90<>""), H90-J90, IF(H90<>"", H90-I90*VLOOKUP(A90, BACKEND1!$A:$G,6,FALSE), IF(J90<>"", -J90+K90*VLOOKUP(A90, BACKEND1!$A:$G,6,FALSE),0)))+ (C90+D90-E90)*VLOOKUP(A90, BACKEND1!$A:$G,5,FALSE)+G90 -> 0
A91: Turmeric | B91: Packet | C91: ='19th-21stMAY'!E91 | F91: Kg | H91: ='19th-21stMAY'!J91 | I91: 1 | L91: Kg | M91: =IF(AND(H91<>"", J91<>""), H91-J91, IF(H91<>"", H91-I91*VLOOKUP(A91, BACKEND1!$A:$G,6,FALSE), IF(J91<>"", -J91+K91*VLOOKUP(A91, BACKEND1!$A:$G,6,FALSE),0)))+ (C91+D91-E91)*VLOOKUP(A91, BACKEND1!$A:$G,5,FALSE)+G91 -> 0
A92: Paprika | B92: Packet | C92: ='19th-21stMAY'!E92 | F92: Kg | H92: ='19th-21stMAY'!J92 -> 0.873 | I92: 1 | J92: 0.698 | L92: Kg | M92: =IF(AND(H92<>"", J92<>""), H92-J92, IF(H92<>"", H92-I92*VLOOKUP(A92, BACKEND1!$A:$G,6,FALSE), IF(J92<>"", -J92+K92*VLOOKUP(A92, BACKEND1!$A:$G,6,FALSE),0)))+ (C92+D92-E92)*VLOOKUP(A92, BACKEND1!$A:$G,5,FALSE)+G92 -> 0.175
A93: Origano | B93: Packet | C93: ='19th-21stMAY'!E93 | F93: Kg | H93: ='19th-21stMAY'!J93 -> 0.181 | I93: 1 | J93: 0.125 | L93: Kg | M93: =IF(AND(H93<>"", J93<>""), H93-J93, IF(H93<>"", H93-I93*VLOOKUP(A93, BACKEND1!$A:$G,6,FALSE), IF(J93<>"", -J93+K93*VLOOKUP(A93, BACKEND1!$A:$G,6,FALSE),0)))+ (C93+D93-E93)*VLOOKUP(A93, BACKEND1!$A:$G,5,FALSE)+G93 -> 0.056
A94: Curry powder | B94: Packet | C94: ='19th-21stMAY'!E94 | F94: Kg | H94: ='19th-21stMAY'!J94 | I94: 1 | L94: Kg | M94: =IF(AND(H94<>"", J94<>""), H94-J94, IF(H94<>"", H94-I94*VLOOKUP(A94, BACKEND1!$A:$G,6,FALSE), IF(J94<>"", -J94+K94*VLOOKUP(A94, BACKEND1!$A:$G,6,FALSE),0)))+ (C94+D94-E94)*VLOOKUP(A94, BACKEND1!$A:$G,5,FALSE)+G94 -> 0
A95: Black pepper powder | B95: Packet | C95: ='19th-21stMAY'!E95 | F95: Kg | H95: ='19th-21stMAY'!J95 -> 0.036 | I95: 1 | L95: Kg | M95: =IF(AND(H95<>"", J95<>""), H95-J95, IF(H95<>"", H95-I95*VLOOKUP(A95, BACKEND1!$A:$G,6,FALSE), IF(J95<>"", -J95+K95*VLOOKUP(A95, BACKEND1!$A:$G,6,FALSE),0)))+ (C95+D95-E95)*VLOOKUP(A95, BACKEND1!$A:$G,5,FALSE)+G95 -> 0.032
A96: Black pepper Seeds | B96: Packet | C96: ='19th-21stMAY'!E96 | F96: Kg | G96: 0.001 | H96: ='19th-21stMAY'!J96 -> 0.302 | I96: 1 | J96: 0.303 | L96: Kg | M96: =IF(AND(H96<>"", J96<>""), H96-J96, IF(H96<>"", H96-I96*VLOOKUP(A96, BACKEND1!$A:$G,6,FALSE), IF(J96<>"", -J96+K96*VLOOKUP(A96, BACKEND1!$A:$G,6,FALSE),0)))+ (C96+D96-E96)*VLOOKUP(A96, BACKEND1!$A:$G,5,FALSE)+G96 -> 0
A97: Cumin seeds | B97: Packet | C97: ='19th-21stMAY'!E97 | F97: Kg | H97: ='19th-21stMAY'!J97 | I97: 1 | L97: Kg | M97: =IF(AND(H97<>"", J97<>""), H97-J97, IF(H97<>"", H97-I97*VLOOKUP(A97, BACKEND1!$A:$G,6,FALSE), IF(J97<>"", -J97+K97*VLOOKUP(A97, BACKEND1!$A:$G,6,FALSE),0)))+ (C97+D97-E97)*VLOOKUP(A97, BACKEND1!$A:$G,5,FALSE)+G97 -> 0
A98: Simba mbili | B98: Tin | C98: ='19th-21stMAY'!E98 | F98: Kg | H98: ='19th-21stMAY'!J98 -> 0.33 | I98: 1 | J98: 0.273 | L98: Kg | M98: =IF(AND(H98<>"", J98<>""), H98-J98, IF(H98<>"", H98-I98*VLOOKUP(A98, BACKEND1!$A:$G,6,FALSE), IF(J98<>"", -J98+K98*VLOOKUP(A98, BACKEND1!$A:$G,6,FALSE),0)))+ (C98+D98-E98)*VLOOKUP(A98, BACKEND1!$A:$G,5,FALSE)+G98 -> 0.057
A99: Cinnamon powder | B99: Packet | C99: ='19th-21stMAY'!E99 | F99: Kg | H99: ='19th-21stMAY'!J99 -> 0.224 | I99: 1 | J99: 0.218 | L99: Kg | M99: =IF(AND(H99<>"", J99<>""), H99-J99, IF(H99<>"", H99-I99*VLOOKUP(A99, BACKEND1!$A:$G,6,FALSE), IF(J99<>"", -J99+K99*VLOOKUP(A99, BACKEND1!$A:$G,6,FALSE),0)))+ (C99+D99-E99)*VLOOKUP(A99, BACKEND1!$A:$G,5,FALSE)+G99 -> 0.006
A100: Ground cloves | B100: Packet | C100: ='19th-21stMAY'!E100 | F100: Kg | H100: ='19th-21stMAY'!J100 -> 0.242 | I100: 1 | J100: 0.233 | L100: Kg | M100: =IF(AND(H100<>"", J100<>""), H100-J100, IF(H100<>"", H100-I100*VLOOKUP(A100, BACKEND1!$A:$G,6,FALSE), IF(J100<>"", -J100+K100*VLOOKUP(A100, BACKEND1!$A:$G,6,FALSE),0)))+ (C100+D100-E100)*VLOOKUP(A100, BACKEND1!$A:$G,5,FALSE)+G100 -> 0.009
A101: Pilau masala | B101: Packet | C101: ='19th-21stMAY'!E101 | F101: Kg | H101: ='19th-21stMAY'!J101 -> 0.511 | I101: 1 | J101: 0.505 | L101: Kg | M101: =IF(AND(H101<>"", J101<>""), H101-J101, IF(H101<>"", H101-I101*VLOOKUP(A101, BACKEND1!$A:$G,6,FALSE), IF(J101<>"", -J101+K101*VLOOKUP(A101, BACKEND1!$A:$G,6,FALSE),0)))+ (C101+D101-E101)*VLOOKUP(A101, BACKEND1!$A:$G,5,FALSE)+G101 -> 0.006
...

Sheet 19th-21stMAY
B2: WHOLE | F2: REMAINDER | L2: ACCOUNTABILITY
A3: Type | B3: U.O.M | C3: Opening | D3: Added | E3: Closing | F3: U.O.M | G3: Added | H3: Opening | I3: Units | J3: Closing | K3: Units | L3: U.O.M | M3: Used | N3: Transfer | O3: Damage
A4: Portioned Items: Meats & Others
A5: Carribean jerk | B5: Ptns | C5: ='15th-18thMAY'!E5 -> 13 | D5: 28 | E5: 26 | F5: Pcs | L5: Pcs | M5: =IF(AND(H5<>"", J5<>""), H5-J5, IF(H5<>"", H5-I5*VLOOKUP(A5, BACKEND2!$A:$G,6,FALSE), IF(J5<>"", -J5+K5*VLOOKUP(A5, BACKEND2!$A:$G,6,FALSE),0)))+ (C5+D5-E5)*VLOOKUP(A5, BACKEND2!$A:$G,5,FALSE)+G5 -> 45
A6: Chicken breast | B6: Ptns | C6: ='15th-18thMAY'!E6 -> 6 | D6: 6 | E6: 7 | F6: Pcs | L6: Pcs | M6: =IF(AND(H6<>"", J6<>""), H6-J6, IF(H6<>"", H6-I6*VLOOKUP(A6, BACKEND2!$A:$G,6,FALSE), IF(J6<>"", -J6+K6*VLOOKUP(A6, BACKEND2!$A:$G,6,FALSE),0)))+ (C6+D6-E6)*VLOOKUP(A6, BACKEND2!$A:$G,5,FALSE)+G6 -> 10
A7: Chicken wings | B7: Ptns | C7: ='15th-18thMAY'!E7 -> 11 | E7: 4 | F7: Pcs | L7: Pcs | M7: =IF(AND(H7<>"", J7<>""), H7-J7, IF(H7<>"", H7-I7*VLOOKUP(A7, BACKEND2!$A:$G,6,FALSE), IF(J7<>"", -J7+K7*VLOOKUP(A7, BACKEND2!$A:$G,6,FALSE),0)))+ (C7+D7-E7)*VLOOKUP(A7, BACKEND2!$A:$G,5,FALSE)+G7 -> 35
A8: Chicken burger | B8: Ptns | C8: ='15th-18thMAY'!E8 -> 1 | D8: 22 | E8: 13 | F8: Ptns | L8: Ptns | M8: =IF(AND(H8<>"", J8<>""), H8-J8, IF(H8<>"", H8-I8*VLOOKUP(A8, BACKEND2!$A:$G,6,FALSE), IF(J8<>"", -J8+K8*VLOOKUP(A8, BACKEND2!$A:$G,6,FALSE),0)))+ (C8+D8-E8)*VLOOKUP(A8, BACKEND2!$A:$G,5,FALSE)+G8 -> 10
A9: Min Chicken burger | B9: Ptns | C9: ='15th-18thMAY'!E9 | F9: Pcs | L9: Pcs | M9: =IF(AND(H9<>"", J9<>""), H9-J9, IF(H9<>"", H9-I9*VLOOKUP(A9, BACKEND2!$A:$G,6,FALSE), IF(J9<>"", -J9+K9*VLOOKUP(A9, BACKEND2!$A:$G,6,FALSE),0)))+ (C9+D9-E9)*VLOOKUP(A9, BACKEND2!$A:$G,5,FALSE)+G9 -> 0
A10: Chicken lollipos | B10: Ptns | C10: ='15th-18thMAY'!E10 -> 5 | E10: 3 | F10: Pcs | L10: Pcs | M10: =IF(AND(H10<>"", J10<>""), H10-J10, IF(H10<>"", H10-I10*VLOOKUP(A10, BACKEND2!$A:$G,6,FALSE), IF(J10<>"", -J10+K10*VLOOKUP(A10, BACKEND2!$A:$G,6,FALSE),0)))+ (C10+D10-E10)*VLOOKUP(A10, BACKEND2!$A:$G,5,FALSE)+G10 -> 16
A11: Chicken pizza | B11: Ptns | C11: ='15th-18thMAY'!E11 -> 7 | D11: 45 | E11: 17 | F11: Ptns | L11: Ptns | M11: =IF(AND(H11<>"", J11<>""), H11-J11, IF(H11<>"", H11-I11*VLOOKUP(A11, BACKEND2!$A:$G,6,FALSE), IF(J11<>"", -J11+K11*VLOOKUP(A11, BACKEND2!$A:$G,6,FALSE),0)))+ (C11+D11-E11)*VLOOKUP(A11, BACKEND2!$A:$G,5,FALSE)+G11 -> 35
A12: Chicken Tenders | B12: Ptns | C12: ='15th-18thMAY'!E12 | F12: Ptns | L12: Ptns | M12: =IF(AND(H12<>"", J12<>""), H12-J12, IF(H12<>"", H12-I12*VLOOKUP(A12, BACKEND2!$A:$G,6,FALSE), IF(J12<>"", -J12+K12*VLOOKUP(A12, BACKEND2!$A:$G,6,FALSE),0)))+ (C12+D12-E12)*VLOOKUP(A12, BACKEND2!$A:$G,5,FALSE)+G12 -> 0
A13: Chicken skewers | B13: Ptns | C13: ='15th-18thMAY'!E13 -> 3 | D13: 18 | E13: 11 | F13: Pcs | L13: Pcs | M13: =IF(AND(H13<>"", J13<>""), H13-J13, IF(H13<>"", H13-I13*VLOOKUP(A13, BACKEND2!$A:$G,6,FALSE), IF(J13<>"", -J13+K13*VLOOKUP(A13, BACKEND2!$A:$G,6,FALSE),0)))+ (C13+D13-E13)*VLOOKUP(A13, BACKEND2!$A:$G,5,FALSE)+G13 -> 90
A14: Chicken stroganoff | B14: Ptns | C14: ='15th-18thMAY'!E14 -> 13 | D14: 20 | E14: 16 | F14: Ptns | L14: Ptns | M14: =IF(AND(H14<>"", J14<>""), H14-J14, IF(H14<>"", H14-I14*VLOOKUP(A14, BACKEND2!$A:$G,6,FALSE), IF(J14<>"", -J14+K14*VLOOKUP(A14, BACKEND2!$A:$G,6,FALSE),0)))+ (C14+D14-E14)*VLOOKUP(A14, BACKEND2!$A:$G,5,FALSE)+G14 -> 17
A15: Chicken spring rolls | B15: Ptns | C15: ='15th-18thMAY'!E15 -> 3.5 | E15: 1.5 | F15: Pcs | L15: Pcs | M15: =IF(AND(H15<>"", J15<>""), H15-J15, IF(H15<>"", H15-I15*VLOOKUP(A15, BACKEND2!$A:$G,6,FALSE), IF(J15<>"", -J15+K15*VLOOKUP(A15, BACKEND2!$A:$G,6,FALSE),0)))+ (C15+D15-E15)*VLOOKUP(A15, BACKEND2!$A:$G,5,FALSE)+G15 -> 8
A16: Chicken Samosas | B16: Ptns | C16: ='15th-18thMAY'!E16 -> 6 | D16: 6 | E16: 9 | F16: Pcs | L16: Pcs | M16: =IF(AND(H16<>"", J16<>""), H16-J16, IF(H16<>"", H16-I16*VLOOKUP(A16, BACKEND2!$A:$G,6,FALSE), IF(J16<>"", -J16+K16*VLOOKUP(A16, BACKEND2!$A:$G,6,FALSE),0)))+ (C16+D16-E16)*VLOOKUP(A16, BACKEND2!$A:$G,5,FALSE)+G16 -> 12
A17: Pork ribs | B17: Ptns | C17: ='15th-18thMAY'!E17 -> 1 | D17: 24 | E17: 11 | F17: Pcs | L17: Pcs | M17: =IF(AND(H17<>"", J17<>""), H17-J17, IF(H17<>"", H17-I17*VLOOKUP(A17, BACKEND2!$A:$G,6,FALSE), IF(J17<>"", -J17+K17*VLOOKUP(A17, BACKEND2!$A:$G,6,FALSE),0)))+ (C17+D17-E17)*VLOOKUP(A17, BACKEND2!$A:$G,5,FALSE)+G17 -> 28
A18: Pork chops | B18: Ptns | C18: ='15th-18thMAY'!E18 -> 5 | D18: 6 | E18: 5 | F18: Pcs | L18: Pcs | M18: =IF(AND(H18<>"", J18<>""), H18-J18, IF(H18<>"", H18-I18*VLOOKUP(A18, BACKEND2!$A:$G,6,FALSE), IF(J18<>"", -J18+K18*VLOOKUP(A18, BACKEND2!$A:$G,6,FALSE),0)))+ (C18+D18-E18)*VLOOKUP(A18, BACKEND2!$A:$G,5,FALSE)+G18 -> 12
A19: Sizzling pork | B19: Ptns | C19: ='15th-18thMAY'!E19 -> 3 | D19: 3 | E19: 2 | F19: Ptns | L19: Ptns | M19: =IF(AND(H19<>"", J19<>""), H19-J19, IF(H19<>"", H19-I19*VLOOKUP(A19, BACKEND2!$A:$G,6,FALSE), IF(J19<>"", -J19+K19*VLOOKUP(A19, BACKEND2!$A:$G,6,FALSE),0)))+ (C19+D19-E19)*VLOOKUP(A19, BACKEND2!$A:$G,5,FALSE)+G19 -> 4
A20: Pork pizza | B20: Ptns | C20: ='15th-18thMAY'!E20 -> 5 | E20: 5 | F20: Ptns | L20: Ptns | M20: =IF(AND(H20<>"", J20<>""), H20-J20, IF(H20<>"", H20-I20*VLOOKUP(A20, BACKEND2!$A:$G,6,FALSE), IF(J20<>"", -J20+K20*VLOOKUP(A20, BACKEND2!$A:$G,6,FALSE),0)))+ (C20+D20-E20)*VLOOKUP(A20, BACKEND2!$A:$G,5,FALSE)+G20 -> 0
A21: Bacon | B21: Ptns | C21: ='15th-18thMAY'!E21 -> 7 | E21: 5 | F21: Pcs | L21: Pcs | M21: =IF(AND(H21<>"", J21<>""), H21-J21, IF(H21<>"", H21-I21*VLOOKUP(A21, BACKEND2!$A:$G,6,FALSE), IF(J21<>"", -J21+K21*VLOOKUP(A21, BACKEND2!$A:$G,6,FALSE),0)))+ (C21+D21-E21)*VLOOKUP(A21, BACKEND2!$A:$G,5,FALSE)+G21 -> 8
A22: Bacon Warp | B22: Ptns | C22: ='15th-18thMAY'!E22 | F22: Pcs | L22: Pcs | M22: =IF(AND(H22<>"", J22<>""), H22-J22, IF(H22<>"", H22-I22*VLOOKUP(A22, BACKEND2!$A:$G,6,FALSE), IF(J22<>"", -J22+K22*VLOOKUP(A22, BACKEND2!$A:$G,6,FALSE),0)))+ (C22+D22-E22)*VLOOKUP(A22, BACKEND2!$A:$G,5,FALSE)+G22 -> 0
A23: Beef fillet | B23: Ptns | C23: ='15th-18thMAY'!E23 -> 1 | D23: 7 | E23: 7.5 | F23: Pcs | L23: Pcs | M23: =IF(AND(H23<>"", J23<>""), H23-J23, IF(H23<>"", H23-I23*VLOOKUP(A23, BACKEND2!$A:$G,6,FALSE), IF(J23<>"", -J23+K23*VLOOKUP(A23, BACKEND2!$A:$G,6,FALSE),0)))+ (C23+D23-E23)*VLOOKUP(A23, BACKEND2!$A:$G,5,FALSE)+G23 -> 1
A24: Panfried goat | B24: Ptns | C24: ='15th-18thMAY'!E24 -> 8 | D24: 24 | E24: 8 | F24: Ptns | L24: Ptns | M24: =IF(AND(H24<>"", J24<>""), H24-J24, IF(H24<>"", H24-I24*VLOOKUP(A24, BACKEND2!$A:$G,6,FALSE), IF(J24<>"", -J24+K24*VLOOKUP(A24, BACKEND2!$A:$G,6,FALSE),0)))+ (C24+D24-E24)*VLOOKUP(A24, BACKEND2!$A:$G,5,FALSE)+G24 -> 24
A25: Goat ribs | B25: Ptns | C25: ='15th-18thMAY'!E25 -> 4 | D25: 10 | E25: 10 | F25: Ptns | L25: Ptns | M25: =IF(AND(H25<>"", J25<>""), H25-J25, IF(H25<>"", H25-I25*VLOOKUP(A25, BACKEND2!$A:$G,6,FALSE), IF(J25<>"", -J25+K25*VLOOKUP(A25, BACKEND2!$A:$G,6,FALSE),0)))+ (C25+D25-E25)*VLOOKUP(A25, BACKEND2!$A:$G,5,FALSE)+G25 -> 4
A26: Goat stew | B26: Ptns | C26: ='15th-18thMAY'!E26 -> 6 | E26: 4 | F26: Ptns | L26: Ptns | M26: =IF(AND(H26<>"", J26<>""), H26-J26, IF(H26<>"", H26-I26*VLOOKUP(A26, BACKEND2!$A:$G,6,FALSE), IF(J26<>"", -J26+K26*VLOOKUP(A26, BACKEND2!$A:$G,6,FALSE),0)))+ (C26+D26-E26)*VLOOKUP(A26, BACKEND2!$A:$G,5,FALSE)+G26 -> 2
A27: Beef stragnoff | B27: Ptns | C27: ='15th-18thMAY'!E27 | F27: Ptns | L27: Ptns | M27: =IF(AND(H27<>"", J27<>""), H27-J27, IF(H27<>"", H27-I27*VLOOKUP(A27, BACKEND2!$A:$G,6,FALSE), IF(J27<>"", -J27+K27*VLOOKUP(A27, BACKEND2!$A:$G,6,FALSE),0)))+ (C27+D27-E27)*VLOOKUP(A27, BACKEND2!$A:$G,5,FALSE)+G27 -> 0
A28: Beef pizza | B28: Ptns | C28: ='15th-18thMAY'!E28 | D28: 17 | E28: 8 | F28: Ptns | L28: Ptns | M28: =IF(AND(H28<>"", J28<>""), H28-J28, IF(H28<>"", H28-I28*VLOOKUP(A28, BACKEND2!$A:$G,6,FALSE), IF(J28<>"", -J28+K28*VLOOKUP(A28, BACKEND2!$A:$G,6,FALSE),0)))+ (C28+D28-E28)*VLOOKUP(A28, BACKEND2!$A:$G,5,FALSE)+G28 -> 9
A29: Beef sausages | B29: Ptns | C29: ='15th-18thMAY'!E29 -> 5 | D29: 11 | E29: 8.5 | F29: Pcs | L29: Pcs | M29: =IF(AND(H29<>"", J29<>""), H29-J29, IF(H29<>"", H29-I29*VLOOKUP(A29, BACKEND2!$A:$G,6,FALSE), IF(J29<>"", -J29+K29*VLOOKUP(A29, BACKEND2!$A:$G,6,FALSE),0)))+ (C29+D29-E29)*VLOOKUP(A29, BACKEND2!$A:$G,5,FALSE)+G29 -> 15
A30: Beef burger patty | B30: Ptns | C30: ='15th-18thMAY'!E30 | D30: 8 | E30: 5 | F30: Ptns | L30: Ptns | M30: =IF(AND(H30<>"", J30<>""), H30-J30, IF(H30<>"", H30-I30*VLOOKUP(A30, BACKEND2!$A:$G,6,FALSE), IF(J30<>"", -J30+K30*VLOOKUP(A30, BACKEND2!$A:$G,6,FALSE),0)))+ (C30+D30-E30)*VLOOKUP(A30, BACKEND2!$A:$G,5,FALSE)+G30 -> 3
A31: Bolognese | B31: Ptns | C31: ='15th-18thMAY'!E31 -> 5 | E31: 2 | F31: Ptns | L31: Ptns | M31: =IF(AND(H31<>"", J31<>""), H31-J31, IF(H31<>"", H31-I31*VLOOKUP(A31, BACKEND2!$A:$G,6,FALSE), IF(J31<>"", -J31+K31*VLOOKUP(A31, BACKEND2!$A:$G,6,FALSE),0)))+ (C31+D31-E31)*VLOOKUP(A31, BACKEND2!$A:$G,5,FALSE)+G31 -> 3
A32: Beef samosas | B32: Ptns | C32: ='15th-18thMAY'!E32 -> 4 | E32: 3 | F32: Pcs | L32: Pcs | M32: =IF(AND(H32<>"", J32<>""), H32-J32, IF(H32<>"", H32-I32*VLOOKUP(A32, BACKEND2!$A:$G,6,FALSE), IF(J32<>"", -J32+K32*VLOOKUP(A32, BACKEND2!$A:$G,6,FALSE),0)))+ (C32+D32-E32)*VLOOKUP(A32, BACKEND2!$A:$G,5,FALSE)+G32 -> 4
A33: Beef mini burger | B33: Ptns | C33: ='15th-18thMAY'!E33 -> 1 | F33: Ptns | L33: Ptns | M33: =IF(AND(H33<>"", J33<>""), H33-J33, IF(H33<>"", H33-I33*VLOOKUP(A33, BACKEND2!$A:$G,6,FALSE), IF(J33<>"", -J33+K33*VLOOKUP(A33, BACKEND2!$A:$G,6,FALSE),0)))+ (C33+D33-E33)*VLOOKUP(A33, BACKEND2!$A:$G,5,FALSE)+G33 -> 1
A34: Whole fish | B34: Ptns | C34: ='15th-18thMAY'!E34 -> 7 | E34: 5 | F34: Ptns | L34: Ptns | M34: =IF(AND(H34<>"", J34<>""), H34-J34, IF(H34<>"", H34-I34*VLOOKUP(A34, BACKEND2!$A:$G,6,FALSE), IF(J34<>"", -J34+K34*VLOOKUP(A34, BACKEND2!$A:$G,6,FALSE),0)))+ (C34+D34-E34)*VLOOKUP(A34, BACKEND2!$A:$G,5,FALSE)+G34 -> 2
A35: Salmon | B35: Ptns | C35: ='15th-18thMAY'!E35 -> 2 | E35: 1 | F35: Ptns | L35: Ptns | M35: =IF(AND(H35<>"", J35<>""), H35-J35, IF(H35<>"", H35-I35*VLOOKUP(A35, BACKEND2!$A:$G,6,FALSE), IF(J35<>"", -J35+K35*VLOOKUP(A35, BACKEND2!$A:$G,6,FALSE),0)))+ (C35+D35-E35)*VLOOKUP(A35, BACKEND2!$A:$G,5,FALSE)+G35 -> 1
A36: Tilapia fillet | B36: Ptns | C36: ='15th-18thMAY'!E36 -> 4 | D36: 17 | E36: 10 | F36: Pcs | L36: Pcs | M36: =IF(AND(H36<>"", J36<>""), H36-J36, IF(H36<>"", H36-I36*VLOOKUP(A36, BACKEND2!$A:$G,6,FALSE), IF(J36<>"", -J36+K36*VLOOKUP(A36, BACKEND2!$A:$G,6,FALSE),0)))+ (C36+D36-E36)*VLOOKUP(A36, BACKEND2!$A:$G,5,FALSE)+G36 -> 22
A37: Fish fingers | B37: Ptns | C37: ='15th-18thMAY'!E37 -> 4 | D37: 10 | E37: 14 | F37: Pcs | L37: Pcs | M37: =IF(AND(H37<>"", J37<>""), H37-J37, IF(H37<>"", H37-I37*VLOOKUP(A37, BACKEND2!$A:$G,6,FALSE), IF(J37<>"", -J37+K37*VLOOKUP(A37, BACKEND2!$A:$G,6,FALSE),0)))+ (C37+D37-E37)*VLOOKUP(A37, BACKEND2!$A:$G,5,FALSE)+G37 -> 0
A38: Veg Springs rolls | B38: Ptns | C38: ='15th-18thMAY'!E38 -> 2 | E38: 1 | F38: Pcs | L38: Pcs | M38: =IF(AND(H38<>"", J38<>""), H38-J38, IF(H38<>"", H38-I38*VLOOKUP(A38, BACKEND2!$A:$G,6,FALSE), IF(J38<>"", -J38+K38*VLOOKUP(A38, BACKEND2!$A:$G,6,FALSE),0)))+ (C38+D38-E38)*VLOOKUP(A38, BACKEND2!$A:$G,5,FALSE)+G38 -> 4
A39: Veg Samosas | B39: Ptns | C39: ='15th-18thMAY'!E39 -> 5 | E39: 1 | F39: Pcs | L39: Pcs | M39: =IF(AND(H39<>"", J39<>""), H39-J39, IF(H39<>"", H39-I39*VLOOKUP(A39, BACKEND2!$A:$G,6,FALSE), IF(J39<>"", -J39+K39*VLOOKUP(A39, BACKEND2!$A:$G,6,FALSE),0)))+ (C39+D39-E39)*VLOOKUP(A39, BACKEND2!$A:$G,5,FALSE)+G39 -> 16
A40: Beef Stew | B40: Ptns | C40: ='15th-18thMAY'!E40 -> 6 | D40: 8 | E40: 3 | F40: Pcs | L40: Pcs | M40: =IF(AND(H40<>"", J40<>""), H40-J40, IF(H40<>"", H40-I40*VLOOKUP(A40, BACKEND2!$A:$G,6,FALSE), IF(J40<>"", -J40+K40*VLOOKUP(A40, BACKEND2!$A:$G,6,FALSE),0)))+ (C40+D40-E40)*VLOOKUP(A40, BACKEND2!$A:$G,5,FALSE)+G40 -> 11
A41: Beef Minced Meat | B41: Ptns | C41: ='15th-18thMAY'!E41 | F41: Pcs | L41: Pcs | M41: =IF(AND(H41<>"", J41<>""), H41-J41, IF(H41<>"", H41-I41*VLOOKUP(A41, BACKEND2!$A:$G,6,FALSE), IF(J41<>"", -J41+K41*VLOOKUP(A41, BACKEND2!$A:$G,6,FALSE),0)))+ (C41+D41-E41)*VLOOKUP(A41, BACKEND2!$A:$G,5,FALSE)+G41 -> 0
A42: Other Kitchen & Food Supplies | C42: ='15th-18thMAY'!E42
A43: Condiments | C43: ='15th-18thMAY'!E43
A44: Bread Loaf | B44: Loaf | C44: ='15th-18thMAY'!E44 | D44: 3 | F44: kg | H44: ='15th-18thMAY'!J44 -> 0.25 | I44: 1 | J44: 2.25 | L44: kg | M44: =IF(AND(H44<>"", J44<>""), H44-J44, IF(H44<>"", H44-I44*VLOOKUP(A44, BACKEND1!$A:$G,6,FALSE), IF(J44<>"", -J44+K44*VLOOKUP(A44, BACKEND1!$A:$G,6,FALSE),0)))+ (C44+D44-E44)*VLOOKUP(A44, BACKEND1!$A:$G,5,FALSE)+G44 -> 1
A45: Burger Buns | B45: Pcs | C45: ='15th-18thMAY'!E45 | D45: 18 | F45: Pcs | H45: ='15th-18thMAY'!J45 -> 3 | I45: 1 | J45: 11 | L45: Pcs | M45: =IF(AND(H45<>"", J45<>""), H45-J45, IF(H45<>"", H45-I45*VLOOKUP(A45, BACKEND1!$A:$G,6,FALSE), IF(J45<>"", -J45+K45*VLOOKUP(A45, BACKEND1!$A:$G,6,FALSE),0)))+ (C45+D45-E45)*VLOOKUP(A45, BACKEND1!$A:$G,5,FALSE)+G45 -> 10
A46: Slider Buns | B46: Pcs | C46: ='15th-18thMAY'!E46 | F46: Pcs | H46: ='15th-18thMAY'!J46 -> 9 | I46: 1 | J46: 3 | L46: Pcs | M46: =IF(AND(H46<>"", J46<>""), H46-J46, IF(H46<>"", H46-I46*VLOOKUP(A46, BACKEND1!$A:$G,6,FALSE), IF(J46<>"", -J46+K46*VLOOKUP(A46, BACKEND1!$A:$G,6,FALSE),0)))+ (C46+D46-E46)*VLOOKUP(A46, BACKEND1!$A:$G,5,FALSE)+G46 -> 6
A47: Soup Buns | B47: Pcs | C47: ='15th-18thMAY'!E47 | D47: 11 | F47: Pcs | H47: ='15th-18thMAY'!J47 -> 3 | I47: 1 | J47: 3 | L47: Pcs | M47: =IF(AND(H47<>"", J47<>""), H47-J47, IF(H47<>"", H47-I47*VLOOKUP(A47, BACKEND1!$A:$G,6,FALSE), IF(J47<>"", -J47+K47*VLOOKUP(A47, BACKEND1!$A:$G,6,FALSE),0)))+ (C47+D47-E47)*VLOOKUP(A47, BACKEND1!$A:$G,5,FALSE)+G47 -> 11
A48: Baguette Bread | B48: Pcs | C48: ='15th-18thMAY'!E48 | D48: 5 | F48: Pcs | H48: ='15th-18thMAY'!J48 -> 3 | I48: 1 | J48: 4 | L48: Pcs | M48: =IF(AND(H48<>"", J48<>""), H48-J48, IF(H48<>"", H48-I48*VLOOKUP(A48, BACKEND1!$A:$G,6,FALSE), IF(J48<>"", -J48+K48*VLOOKUP(A48, BACKEND1!$A:$G,6,FALSE),0)))+ (C48+D48-E48)*VLOOKUP(A48, BACKEND1!$A:$G,5,FALSE)+G48 -> 4
A49: Foccacia Bread | B49: Pcs | C49: ='15th-18thMAY'!E49 | F49: Pcs | H49: ='15th-18thMAY'!J49 | I49: 1 | L49: Pcs | M49: =IF(AND(H49<>"", J49<>""), H49-J49, IF(H49<>"", H49-I49*VLOOKUP(A49, BACKEND1!$A:$G,6,FALSE), IF(J49<>"", -J49+K49*VLOOKUP(A49, BACKEND1!$A:$G,6,FALSE),0)))+ (C49+D49-E49)*VLOOKUP(A49, BACKEND1!$A:$G,5,FALSE)+G49 -> 0
A50: White vinegar | B50: Bottles | C50: ='15th-18thMAY'!E50 | D50: 1 | F50: Liters | H50: ='15th-18thMAY'!J50 -> 0.395 | I50: 1 | J50: 0.497 | L50: Liters | M50: =IF(AND(H50<>"", J50<>""), H50-J50, IF(H50<>"", H50-I50*VLOOKUP(A50, BACKEND1!$A:$G,6,FALSE), IF(J50<>"", -J50+K50*VLOOKUP(A50, BACKEND1!$A:$G,6,FALSE),0)))+ (C50+D50-E50)*VLOOKUP(A50, BACKEND1!$A:$G,5,FALSE)+G50 -> 0.598
A51: Heinz ketchup bottles | B51: Bottles | C51: ='15th-18thMAY'!E51 | F51: Bottles | H51: ='15th-18thMAY'!J51 | I51: 1 | L51: Bottles | M51: =IF(AND(H51<>"", J51<>""), H51-J51, IF(H51<>"", H51-I51*VLOOKUP(A51, BACKEND1!$A:$G,6,FALSE), IF(J51<>"", -J51+K51*VLOOKUP(A51, BACKEND1!$A:$G,6,FALSE),0)))+ (C51+D51-E51)*VLOOKUP(A51, BACKEND1!$A:$G,5,FALSE)+G51 -> 0
A52: Apple cider vinegar | B52: Pcs | C52: ='15th-18thMAY'!E52 | D52: 1 | F52: kg | G52: 0.015 | H52: ='15th-18thMAY'!J52 | I52: 1 | J52: 0.488 | L52: kg | M52: =IF(AND(H52<>"", J52<>""), H52-J52, IF(H52<>"", H52-I52*VLOOKUP(A52, BACKEND1!$A:$G,6,FALSE), IF(J52<>"", -J52+K52*VLOOKUP(A52, BACKEND1!$A:$G,6,FALSE),0)))+ (C52+D52-E52)*VLOOKUP(A52, BACKEND1!$A:$G,5,FALSE)+G52 -> 0
A53: Balsamic Vinegar | B53: Bottles | C53: ='15th-18thMAY'!E53 | D53: 1 | F53: Kg | G53: 0.233 | H53: ='15th-18thMAY'!J53 | I53: 1 | J53: 0.733 | L53: Kg | M53: =IF(AND(H53<>"", J53<>""), H53-J53, IF(H53<>"", H53-I53*VLOOKUP(A53, BACKEND1!$A:$G,6,FALSE), IF(J53<>"", -J53+K53*VLOOKUP(A53, BACKEND1!$A:$G,6,FALSE),0)))+ (C53+D53-E53)*VLOOKUP(A53, BACKEND1!$A:$G,5,FALSE)+G53 -> 0
A54: Tomato paste | B54: Tins | C54: ='15th-18thMAY'!E54 | D54: 2 | F54: Kg | H54: ='15th-18thMAY'!J54 -> 0.235 | I54: 1 | L54: Kg | M54: =IF(AND(H54<>"", J54<>""), H54-J54, IF(H54<>"", H54-I54*VLOOKUP(A54, BACKEND1!$A:$G,6,FALSE), IF(J54<>"", -J54+K54*VLOOKUP(A54, BACKEND1!$A:$G,6,FALSE),0)))+ (C54+D54-E54)*VLOOKUP(A54, BACKEND1!$A:$G,5,FALSE)+G54 -> 0.972
A55: Tabasco | B55: Pcs | C55: ='15th-18thMAY'!E55 | F55: Kgs | H55: ='15th-18thMAY'!J55 | I55: 1 | L55: Kgs | M55: =IF(AND(H55<>"", J55<>""), H55-J55, IF(H55<>"", H55-I55*VLOOKUP(A55, BACKEND1!$A:$G,6,FALSE), IF(J55<>"", -J55+K55*VLOOKUP(A55, BACKEND1!$A:$G,6,FALSE),0)))+ (C55+D55-E55)*VLOOKUP(A55, BACKEND1!$A:$G,5,FALSE)+G55 -> 0
A56: Ketchup sachets | B56: Packet | C56: ='15th-18thMAY'!E56 | D56: 1 | E56: 1 | F56: Pcs | H56: ='15th-18thMAY'!J56 -> 63 | I56: 1 | L56: Pcs | M56: =IF(AND(H56<>"", J56<>""), H56-J56, IF(H56<>"", H56-I56*VLOOKUP(A56, BACKEND1!$A:$G,6,FALSE), IF(J56<>"", -J56+K56*VLOOKUP(A56, BACKEND1!$A:$G,6,FALSE),0)))+ (C56+D56-E56)*VLOOKUP(A56, BACKEND1!$A:$G,5,FALSE)+G56 -> 63
A57: Mustard | B57: Bottles | C57: ='15th-18thMAY'!E57 | D57: 1 | F57: Kg | H57: ='15th-18thMAY'!J57 -> 0.385 | I57: 1 | J57: 0.428 | L57: Kg | M57: =IF(AND(H57<>"", J57<>""), H57-J57, IF(H57<>"", H57-I57*VLOOKUP(A57, BACKEND1!$A:$G,6,FALSE), IF(J57<>"", -J57+K57*VLOOKUP(A57, BACKEND1!$A:$G,6,FALSE),0)))+ (C57+D57-E57)*VLOOKUP(A57, BACKEND1!$A:$G,5,FALSE)+G57 -> 0.354
A58: Pancake syrup 710ml | B58: Bottles | C58: ='15th-18thMAY'!E58 | D58: 1 | F58: Liters | H58: ='15th-18thMAY'!J58 -> 0.485 | I58: 1 | L58: Liters | M58: =IF(AND(H58<>"", J58<>""), H58-J58, IF(H58<>"", H58-I58*VLOOKUP(A58, BACKEND1!$A:$G,6,FALSE), IF(J58<>"", -J58+K58*VLOOKUP(A58, BACKEND1!$A:$G,6,FALSE),0)))+ (C58+D58-E58)*VLOOKUP(A58, BACKEND1!$A:$G,5,FALSE)+G58 -> 0.902
A59: Vanilla esscence | B59: Bottles | C59: ='15th-18thMAY'!E59 | F59: Liters | G59: 0.343 | H59: ='15th-18thMAY'!J59 -> 0.485 | I59: 1 | J59: 0.828 | L59: Liters | M59: =IF(AND(H59<>"", J59<>""), H59-J59, IF(H59<>"", H59-I59*VLOOKUP(A59, BACKEND1!$A:$G,6,FALSE), IF(J59<>"", -J59+K59*VLOOKUP(A59, BACKEND1!$A:$G,6,FALSE),0)))+ (C59+D59-E59)*VLOOKUP(A59, BACKEND1!$A:$G,5,FALSE)+G59 -> 0
A60: Srawberry Syrup | B60: Btls | C60: ='15th-18thMAY'!E60 | F60: Ltr | H60: ='15th-18thMAY'!J60 | I60: 1 | L60: Ltr | M60: =IF(AND(H60<>"", J60<>""), H60-J60, IF(H60<>"", H60-I60*VLOOKUP(A60, BACKEND1!$A:$G,6,FALSE), IF(J60<>"", -J60+K60*VLOOKUP(A60, BACKEND1!$A:$G,6,FALSE),0)))+ (C60+D60-E60)*VLOOKUP(A60, BACKEND1!$A:$G,5,FALSE)+G60 -> 0
A61: Caramel syrup | B61: Btls | C61: ='15th-18thMAY'!E61 | F61: Ltr | H61: ='15th-18thMAY'!J61 | I61: 1 | L61: Ltr | M61: =IF(AND(H61<>"", J61<>""), H61-J61, IF(H61<>"", H61-I61*VLOOKUP(A61, BACKEND1!$A:$G,6,FALSE), IF(J61<>"", -J61+K61*VLOOKUP(A61, BACKEND1!$A:$G,6,FALSE),0)))+ (C61+D61-E61)*VLOOKUP(A61, BACKEND1!$A:$G,5,FALSE)+G61 -> 0
A62: Chocolate syrup | B62: Btls | C62: ='15th-18thMAY'!E62 | F62: Ltr | H62: ='15th-18thMAY'!J62 -> 0.27 | I62: 1 | J62: 0.118 | L62: Ltr | M62: =IF(AND(H62<>"", J62<>""), H62-J62, IF(H62<>"", H62-I62*VLOOKUP(A62, BACKEND1!$A:$G,6,FALSE), IF(J62<>"", -J62+K62*VLOOKUP(A62, BACKEND1!$A:$G,6,FALSE),0)))+ (C62+D62-E62)*VLOOKUP(A62, BACKEND1!$A:$G,5,FALSE)+G62 -> 0.152
A63: Honey | B63: Kg | C63: ='15th-18thMAY'!E63 | F63: Kg | G63: 1 | H63: ='15th-18thMAY'!J63 -> 0.285 | I63: 1 | J63: 1.136 | L63: Kg | M63: =IF(AND(H63<>"", J63<>""), H63-J63, IF(H63<>"", H63-I63*VLOOKUP(A63, BACKEND1!$A:$G,6,FALSE), IF(J63<>"", -J63+K63*VLOOKUP(A63, BACKEND1!$A:$G,6,FALSE),0)))+ (C63+D63-E63)*VLOOKUP(A63, BACKEND1!$A:$G,5,FALSE)+G63 -> 0.149
A64: Ketchup 5L | B64: Jerrycan | C64: ='15th-18thMAY'!E64 | D64: 1 | F64: kg | H64: ='15th-18thMAY'!J64 -> 0.825 | I64: 1 | J64: 3.853 | L64: kg | M64: =IF(AND(H64<>"", J64<>""), H64-J64, IF(H64<>"", H64-I64*VLOOKUP(A64, BACKEND1!$A:$G,6,FALSE), IF(J64<>"", -J64+K64*VLOOKUP(A64, BACKEND1!$A:$G,6,FALSE),0)))+ (C64+D64-E64)*VLOOKUP(A64, BACKEND1!$A:$G,5,FALSE)+G64 -> 1.972
A65: Dry Foods | C65: ='15th-18thMAY'!E65 | H65: ='15th-18thMAY'!J65 | I65: 1 | M65: =IF(AND(H65<>"", J65<>""), H65-J65, IF(H65<>"", H65-I65*VLOOKUP(A65, BACKEND1!$A:$G,6,FALSE), IF(J65<>"", -J65+K65*VLOOKUP(A65, BACKEND1!$A:$G,6,FALSE),0)))+ (C65+D65-E65)*VLOOKUP(A65, BACKEND1!$A:$G,5,FALSE)+G65 -> 0
A66: Baking flour | B66: Pkts | C66: ='15th-18thMAY'!E66 -> 2 | D66: 8 | F66: Kg | H66: ='15th-18thMAY'!J66 -> 0.5 | I66: 1 | J66: 1.281 | L66: Kg | M66: =IF(AND(H66<>"", J66<>""), H66-J66, IF(H66<>"", H66-I66*VLOOKUP(A66, BACKEND1!$A:$G,6,FALSE), IF(J66<>"", -J66+K66*VLOOKUP(A66, BACKEND1!$A:$G,6,FALSE),0)))+ (C66+D66-E66)*VLOOKUP(A66, BACKEND1!$A:$G,5,FALSE)+G66 -> 19.219
A67: Baking Powder | B67: Pkts | C67: ='15th-18thMAY'!E67 | F67: Kg | H67: ='15th-18thMAY'!J67 -> 0.14 | I67: 1 | J67: 0.121 | L67: Kg | M67: =IF(AND(H67<>"", J67<>""), H67-J67, IF(H67<>"", H67-I67*VLOOKUP(A67, BACKEND1!$A:$G,6,FALSE), IF(J67<>"", -J67+K67*VLOOKUP(A67, BACKEND1!$A:$G,6,FALSE),0)))+ (C67+D67-E67)*VLOOKUP(A67, BACKEND1!$A:$G,5,FALSE)+G67 -> 0.019
A68: Basmati rice | B68: Kg | C68: ='15th-18thMAY'!E68 | D68: 15 | F68: Kg | H68: ='15th-18thMAY'!J68 -> 2.76 | I68: 1 | J68: 5 | L68: Kg | M68: =IF(AND(H68<>"", J68<>""), H68-J68, IF(H68<>"", H68-I68*VLOOKUP(A68, BACKEND1!$A:$G,6,FALSE), IF(J68<>"", -J68+K68*VLOOKUP(A68, BACKEND1!$A:$G,6,FALSE),0)))+ (C68+D68-E68)*VLOOKUP(A68, BACKEND1!$A:$G,5,FALSE)+G68 -> 12.76
A69: Corn flour | B69: Pkts | C69: ='15th-18thMAY'!E69 | D69: 2 | E69: 1 | F69: Kg | H69: ='15th-18thMAY'!J69 -> 0.375 | I69: 1 | L69: Kg | M69: =IF(AND(H69<>"", J69<>""), H69-J69, IF(H69<>"", H69-I69*VLOOKUP(A69, BACKEND1!$A:$G,6,FALSE), IF(J69<>"", -J69+K69*VLOOKUP(A69, BACKEND1!$A:$G,6,FALSE),0)))+ (C69+D69-E69)*VLOOKUP(A69, BACKEND1!$A:$G,5,FALSE)+G69 -> 0.725
A70: Oils, Fats & Creams | C70: ='15th-18thMAY'!E70 | H70: ='15th-18thMAY'!J70 | I70: 1 | M70: =IF(AND(H70<>"", J70<>""), H70-J70, IF(H70<>"", H70-I70*VLOOKUP(A70, BACKEND1!$A:$G,6,FALSE), IF(J70<>"", -J70+K70*VLOOKUP(A70, BACKEND1!$A:$G,6,FALSE),0)))+ (C70+D70-E70)*VLOOKUP(A70, BACKEND1!$A:$G,5,FALSE)+G70 -> 0
